Workbook
Name A_Pitch: '06_Road_Engine'!$D$20
Name BX_ang: '04a_Box_Dims'!$B$8
Name BX_apL: '04a_Box_Dims'!$B$7
Name BX_bat: '04a_Box_Dims'!$G$10
Name BX_blind: '04a_Box_Dims'!$B$16
Name BX_ch: '04a_Box_Dims'!$B$6
Name BX_exX: '04a_Box_Dims'!$B$18
Name BX_frb: '04a_Box_Dims'!$B$10
Name BX_Hcov: '04a_Box_Dims'!$B$5
Name BX_hemin: '04a_Box_Dims'!$G$9
Name BX_hh: '04a_Box_Dims'!$B$9
Name BX_hook: '04b_Box_Bars'!$B$4
Name BX_Lnom: '04a_Box_Dims'!$G$11
Name BX_rho: '04b_Box_Bars'!$B$6
Name BX_tdiv: '04a_Box_Dims'!$B$14
Name BX_tinc: '04a_Box_Dims'!$B$15
Name BX_tmin: '04a_Box_Dims'!$B$13
Name BX_tmin2: '04a_Box_Dims'!$G$5
Name BX_tpf: '04a_Box_Dims'!$G$8
Name BX_tpmax: '04a_Box_Dims'!$G$7
Name BX_tpmin: '04a_Box_Dims'!$G$6
Name BX_twD: '04a_Box_Dims'!$B$12
Name BX_twW: '04a_Box_Dims'!$B$11
Name BX_work: '04a_Box_Dims'!$B$17
Name BX_wwbend: '04b_Box_Bars'!$B$5
Name H_Cut: '06_Road_Engine'!$D$15
Name H_FillW: '06_Road_Engine'!$D$18
Name H_Raise: '06_Road_Engine'!$D$12
Name L_Base: '06_Road_Engine'!$D$38
Name L_Blading: '06_Road_Engine'!$D$34
Name L_Cut: '06_Road_Engine'!$D$14
Name L_DitchCL: '06_Road_Engine'!$D$21
Name L_DitchEC: '06_Road_Engine'!$D$23
Name L_DitchRE: '06_Road_Engine'!$D$22
Name L_EB: '06_Road_Engine'!$D$6
Name L_FillW: '06_Road_Engine'!$D$17
Name L_GB: '06_Road_Engine'!$D$7
Name L_Kerb: '06_Road_Engine'!$D$29
Name L_LB: '06_Road_Engine'!$D$9
Name L_Prime: '06_Road_Engine'!$D$39
Name L_Raise: '06_Road_Engine'!$D$11
Name L_Reshape: '06_Road_Engine'!$D$35
Name L_RetW: '06_Road_Engine'!$D$33
Name L_SB: '06_Road_Engine'!$D$8
Name L_Scarify: '06_Road_Engine'!$D$36
Name L_Scour: '06_Road_Engine'!$D$30
Name L_Seal1: '06_Road_Engine'!$D$40
Name L_Seal2: '06_Road_Engine'!$D$41
Name L_Subbase: '06_Road_Engine'!$D$37
Name L_TB: '06_Road_Engine'!$D$10
Name L_Town: '06_Road_Engine'!$D$5
Name L_Trap: '06_Road_Engine'!$D$28
Name L_Turn: '06_Road_Engine'!$D$32
Name L_UD45: '06_Road_Engine'!$D$24
Name L_UD60: '06_Road_Engine'!$D$25
Name L_UD75: '06_Road_Engine'!$D$26
Name L_UD90: '06_Road_Engine'!$D$27
Name P_BaseT: '00_Project'!$C$25
Name P_BinderPct: '00_Project'!$C$32
Name P_CentreLnF: '00_Project'!$C$51

Sheet README
B1: MASTER ESTIMATOR — DFR FEEDER ROAD BILL OF QUANTITIES
B2: Department of Feeder Roads. Everything is done inside this workbook: no other file, no add-in, no internet.
B4: HOW TO PRICE A ROAD
B5: 1. Agree E_Rules | C5: What the surveyor SAW is recorded on Form C; what is DONE about it is written once here, on five rows. Settle them with the design engineer before the survey starts.
B6: 2. Fill F_Road_Data | C6: The project constants. Rows marked ! are template figures nobody has confirmed for your road. Overhaul and haulage distances alone routinely move a bill by a quarter.
B7: 3. Record the survey | C7: Forms A to D, one row per stretch of road that is the same all the way along — not one row per 50 m. An 8 km road usually takes about 30 rows.
B8: 4. Type the identity | C8: Road name, code, region and district on 00_Project. The road LENGTH is measured for you from the furthest chainage on the forms.
B9: 5. Read 90_Checks | C9: Every test must read OK before the bill is issued. Then 10_BOQ is the bill and 21/22_Takeoff are the dimension papers for manual checking.
B11: THE THREE RULES THAT MAKE THE FORMS WORK
B12: Chainages are METRES | C12: 8 km is 8000, not 8. A chainage written as 8 is eight metres and the road will price at almost nothing.
B13: Later rows override earlier | C13: Lay down the general case for the whole road on line 1, then refine short stretches below it.
B14: Blank vs dash | C14: A blank cell means "unchanged". A dash - means "explicitly none here", and is how you switch something back off that an earlier row switched on.
B16: WHAT YOU MAY AND MAY NOT TYPE INTO
B17: Type here | C17: README identity block aside: 00_Project identity only, E_Rules, F_Road_Data, and Forms A, B, C, D. Every input cell is shaded yellow.
B18: Never type here | C18: 01_Stations and 02_Culverts are now FORMULAS that resolve the forms. Typing into them destroys the link and the next change to a form will not reach the bill.
B19: Never type a rate in the bill | C19: 08_Rates is the only place a price is typed. A rate typed into 10_BOQ is overwritten the moment anything upstream changes.
B21: WHAT IS NOT SETTLED — read before issuing
B22: Rates | C22: 08_Rates carries a date and a source on every line. Check they are current before the bill leaves the building.
B23: Unpriced measured items | C23: Road widening, raising, gully filling, blading, scarifying, kerb and retaining wall are measured correctly but no bill line collects them. The coverage tests on 90_Checks count them.
B24: U-culvert rates | C24: All U-culvert rate lines are blank. Any job with a U-culvert shows measured quantities pricing at zero.
B25: Box culvert flotation | C25: Every 3x3, 4x3 and 4x4 box, and 2/3x2.4, needs hold-down against buoyancy, and every box needs deepened scour protection. Neither is in the bill.
B26: Not yet parallel-run | C26: No completed project has been priced through both this workbook and the legacy set. That is the outstanding validation.

Sheet 00_Project
A1: PROJECT CONSTANTS
A2: Every global input lives here, but the VALUES now come from the input forms: the constants from F_Road_Data and the road length from the survey extent on Forms A-D. Edit those sheets, not this one. Named cells are used by name in every formula in the workbook. A red ! on F_Road_Data marks a template figure not yet confirmed for this road.
A4: Name | B4: Parameter | C4: Value | D4: Unit | E4: Note
A5: PROJECT IDENTITY
A6: P_RoadName | B6: Road name
A7: P_RoadCode | B7: Road code
A8: P_Region | B8: Region
A9: P_District | B9: District
A10: P_Programme | B10: Programme
A11: ROAD EXTENT
A12: P_Length_km | B12: Road length | C12: =MAX(MAX(A_Corridor!$B$5:$B$204),MAX(B_Drainage!$B$5:$B$204),MAX(C_Pavement!$B$5:$B$204),MAX(D_Points!$A$5:$A$204))/1000 -> 0 | D12: km | E12: Measured from the furthest chainage on Forms A-D
A13: P_Interval | B13: Station interval | C13: 50 | D13: m | E13: Fixed; matches the legacy line-diagram grid
A14: P_NStations | B14: Number of stations | C14: =ROUNDUP(P_Length_km*1000/P_Interval,0) -> 0 | D14: nr | E14: Derived
A15: CROSS-SECTION
A16: P_CW | B16: Carriageway width | C16: =F_Road_Data!$C$6 -> 7 | D16: m
A17: P_SW | B17: Shoulder width (one side) | C17: =F_Road_Data!$C$7 -> 1 | D17: m
A18: P_FW | B18: Formation width | C18: =P_CW+2*P_SW -> 9 | D18: m | E18: Derived
A19: P_ExtCW | B19: Existing carriageway width | C19: =F_Road_Data!$C$8 -> 4 | D19: m
A20: P_ClearW | B20: Clearing width | C20: =P_FW+4 -> 13 | D20: m | E20: Derived: formation + 2 m each side
A21: P_PrimeW | B21: Width for primer seal | C21: =F_Road_Data!$C$9 -> 8 | D21: m
A22: P_SealW | B22: Width of sealing | C22: =F_Road_Data!$C$10 -> 7 | D22: m
A23: PAVEMENT
A24: P_SubbaseT | B24: Sub-base thickness | C24: =F_Road_Data!$C$12 -> 0.15 | D24: m
A25: P_BaseT | B25: Base thickness | C25: =F_Road_Data!$C$13 -> 0.15 | D25: m
A26: P_OH_Sub | B26: Overhaul distance, sub-base | C26: =F_Road_Data!$C$14 -> 31 | D26: km
A27: P_OH_Base | B27: Overhaul distance, base | C27: =F_Road_Data!$C$15 -> 40 | D27: km
A28: SURFACING DESIGN RATES
A29: P_PrimeRate | B29: Primer seal binder rate | C29: =F_Road_Data!$C$17 -> 1.4 | D29: l/m²
A30: P_Seal1Rate | B30: First seal binder rate | C30: =F_Road_Data!$C$18 -> 1.3 | D30: l/m²
A31: P_Seal2Rate | B31: Second seal binder rate | C31: =F_Road_Data!$C$19 -> 1.2 | D31: l/m²
A32: P_BinderPct | B32: Binder fraction of primer | C32: =F_Road_Data!$C$20 -> 0.84 | D32: - | E32: Balance is cutter oil
A33: P_CutterPct | B33: Cutter-oil fraction of primer | C33: =F_Road_Data!$C$21 -> 0.16 | D33: -
A34: P_Chip10 | B34: 10 mm chipping coverage | C34: =F_Road_Data!$C$22 -> 120 | D34: m²/m³
A35: P_Chip14 | B35: 14 mm chipping coverage | C35: =F_Road_Data!$C$23 -> 100 | D35: m²/m³
A36: HAULAGE DISTANCES
A37: P_HaulSand | B37: Sand (fine aggregate) | C37: =F_Road_Data!$C$25 -> 15 | D37: km | E37: Legacy Proposed_Culv!J2
A38: P_HaulCoarse | B38: Coarse aggregate | C38: =F_Road_Data!$C$26 -> 25 | D38: km | E38: Legacy Proposed_Culv!J1
A39: P_HaulChip | B39: Chippings | C39: =F_Road_Data!$C$27 -> 60 | D39: km
A40: P_HaulFill | B40: Fill material | C40: =F_Road_Data!$C$28 -> 2 | D40: km
A41: AGGREGATE YIELD FACTORS
A42: P_FineLean | B42: Fine agg. per m³ lean concrete | C42: =F_Road_Data!$C$30 -> 0.58 | D42: m³/m³ | E42: C10/40
A43: P_CoarseLean | B43: Coarse agg. per m³ lean concrete | C43: =F_Road_Data!$C$31 -> 0.92 | D43: m³/m³ | E43: C10/40
A44: P_FineStr | B44: Fine agg. per m³ structural conc. | C44: =F_Road_Data!$C$32 -> 0.55 | D44: m³/m³ | E44: C20/20 - C30/20
A45: P_CoarseStr | B45: Coarse agg. per m³ struct. conc. | C45: =F_Road_Data!$C$33 -> 0.88 | D45: m³/m³ | E45: C20/20 - C30/20
A46: ROAD FURNITURE RATES
A47: P_SignsPerKm | B47: Traffic signs per km (each type) | C47: =F_Road_Data!$C$35 -> 10 | D47: nr/km | E47: Legacy applied per metre - see 90_Checks
A48: P_StopPerKm | B48: STOP line per km | C48: =F_Road_Data!$C$36 -> 5 | D48: m/km | E48: Legacy applied per metre - see 90_Checks
A49: P_RampsPerKm | B49: Speed ramps per km | C49: =F_Road_Data!$C$37 -> 1 | D49: nr/km | E49: Legacy applied per metre - see 90_Checks
A50: P_LaneLineF | B50: Lane separation line factor | C50: =F_Road_Data!$C$38 -> 0.6 | D50: m/m | E50: of sealed length
A51: P_CentreLnF | B51: Centre line factor | C51: =F_Road_Data!$C$39 -> 0.4 | D51: m/m
A52: P_EdgeLnF | B52: Edge line factor | C52: =F_Road_Data!$C$40 -> 2 | D52: m/m | E52: both edges
A53: P_PedXF | B53: Pedestrian crossing factor | C53: =F_Road_Data!$C$41 -> 2 | D53: m/km
A56: HOW THIS WORKBOOK IS PUT TOGETHER
A57: Yellow cells | B57: Everything you edit. Nothing else should be typed into.
A58: 01_Stations | B58: The line diagram as data — one row per 50 m. Enter only where an activity occurs.
A59: 02_Culverts | B59: One row per culvert. Family + Cells + Size is the key the engines match on.
A60: 03 / 04 / 05 | B60: The three culvert engines. One row per culvert type; the geometry sits beside the quantities.
A61: 06_Road_Engine | B61: Part A aggregates the stations; Part B turns aggregates into BOQ quantities.
A62: 07_Items / 08_Rates | B62: Standing libraries. Descriptions and rates live here, never in the bill.
A63: 10_BOQ | B63: Reads everything above. The only cell you type into is the Misc. column.
A64: 90_Checks | B64: Must read OK before the bill is issued. Also holds the parallel run against the legacy files.
A65: Adding a road length | B65: Change P_Length_km. Capacity is 50 km of 50 m stations — no new sheets, ever.
A66: Adding a culvert size | B66: One new row in the relevant engine. Not a new sheet. The box engine holds 19 types: 2x2 (1-4), 3x2 (1-3), 3x3 (1-4), 4x3 (1-3), 4x4 (1-4) and 2/3x2.4 — all with AASHTO-designed bar schedules on 04b_Box_Bars.

Sheet A_Corridor
A1: FORM A — CORRIDOR, CLEARING AND EARTHWORKS
A2: One row per stretch of road that is the same all the way along. From/To in METRES (8 km = 8000). A later row overrides an earlier one, so lay down the general case first and refine it afterwards. Blank = unchanged; a dash - = explicitly none here.
A4: From | B4: To | C4: Township Y/N | D4: Vegetation | E4: Raise road: fill (cm) | F4: Cut to widen (cm) | G4: Cut width L+R (m) | H4: Fill to widen (cm) | I4: Fill width L+R (m) | J4: Notes

Sheet B_Drainage
A1: FORM B — DRAINAGE
A2: One row per stretch. Entering a U-drain size switches that drain on. Scour checks: 1 = one side, 2 = both. Type - to cancel something an earlier row switched on.
A4: From | B4: To | C4: Ditch L | D4: Ditch R | E4: U-drain L (cm) | F4: U-drain R (cm) | G4: Trap. drain L | H4: Trap. drain R | I4: Kerb L | J4: Kerb R | K4: Scour checks | L4: Scour spacing (m) | M4: Ret. wall L | N4: Ret. wall R | O4: Notes

Sheet C_Pavement
A1: FORM C — PAVEMENT AND SURFACING
A2: Record the SURFACE CONDITION you observed and stop there. Everything to its right is filled in from E_Rules. Type in the override columns only where this stretch genuinely departs from the rule.
A4: From | B4: To | C4: Surface condition | D4: Treatment (override) | E4: Sub-base cm (ovr) | F4: Base cm (ovr) | G4: Prime (ovr) | H4: Seal 1 (ovr) | I4: Seal 2 (ovr) | J4: Notes

Sheet D_Points
A1: FORM D — POINT ITEMS
A2: Things that happen at a spot rather than over a stretch. Chainage in METRES. A PR_CULVERT row also builds the culvert schedule on 02_Culverts. Size: pipes take the diameter in mm; U- and box culverts take span x rise (900X1200, 3x3).
A4: Chainage | B4: Type | C4: Family | D4: Cells | E4: Size | F4: Length (m) | G4: Orientation | H4: Quantity | I4: Notes | K4: 0
K5: =IF(AND(UPPER(TRIM($B5))="PR_CULVERT",$A5<>"",ISNUMBER(MATCH(UPPER(TRIM($C5)),{"PC","BC","UC"},0))),MAX($K$4:K4)+1,"")
K6: =IF(AND(UPPER(TRIM($B6))="PR_CULVERT",$A6<>"",ISNUMBER(MATCH(UPPER(TRIM($C6)),{"PC","BC","UC"},0))),MAX($K$4:K5)+1,"")
K7: =IF(AND(UPPER(TRIM($B7))="PR_CULVERT",$A7<>"",ISNUMBER(MATCH(UPPER(TRIM($C7)),{"PC","BC","UC"},0))),MAX($K$4:K6)+1,"")
K8: =IF(AND(UPPER(TRIM($B8))="PR_CULVERT",$A8<>"",ISNUMBER(MATCH(UPPER(TRIM($C8)),{"PC","BC","UC"},0))),MAX($K$4:K7)+1,"")
K9: =IF(AND(UPPER(TRIM($B9))="PR_CULVERT",$A9<>"",ISNUMBER(MATCH(UPPER(TRIM($C9)),{"PC","BC","UC"},0))),MAX($K$4:K8)+1,"")
K10: =IF(AND(UPPER(TRIM($B10))="PR_CULVERT",$A10<>"",ISNUMBER(MATCH(UPPER(TRIM($C10)),{"PC","BC","UC"},0))),MAX($K$4:K9)+1,"")
K11: =IF(AND(UPPER(TRIM($B11))="PR_CULVERT",$A11<>"",ISNUMBER(MATCH(UPPER(TRIM($C11)),{"PC","BC","UC"},0))),MAX($K$4:K10)+1,"")
K12: =IF(AND(UPPER(TRIM($B12))="PR_CULVERT",$A12<>"",ISNUMBER(MATCH(UPPER(TRIM($C12)),{"PC","BC","UC"},0))),MAX($K$4:K11)+1,"")
K13: =IF(AND(UPPER(TRIM($B13))="PR_CULVERT",$A13<>"",ISNUMBER(MATCH(UPPER(TRIM($C13)),{"PC","BC","UC"},0))),MAX($K$4:K12)+1,"")
K14: =IF(AND(UPPER(TRIM($B14))="PR_CULVERT",$A14<>"",ISNUMBER(MATCH(UPPER(TRIM($C14)),{"PC","BC","UC"},0))),MAX($K$4:K13)+1,"")
K15: =IF(AND(UPPER(TRIM($B15))="PR_CULVERT",$A15<>"",ISNUMBER(MATCH(UPPER(TRIM($C15)),{"PC","BC","UC"},0))),MAX($K$4:K14)+1,"")
K16: =IF(AND(UPPER(TRIM($B16))="PR_CULVERT",$A16<>"",ISNUMBER(MATCH(UPPER(TRIM($C16)),{"PC","BC","UC"},0))),MAX($K$4:K15)+1,"")
... K204: =IF(AND(UPPER(TRIM($B204))="PR_CULVERT",$A204<>"",ISNUMBER(MATCH(UPPER(TRIM($C204)),{"PC","BC","UC"},0))),MAX($K$4:K203)+1,"")

Sheet E_Rules
A1: FORM E — TREATMENT RULES (the engineering judgement, written once)
A2: Every stretch on Form C follows the row matching the surface condition recorded for it. Agree these five rows with the design engineer before the survey starts; change one number here and the whole road re-prices. A blank means the item is not done for that condition class.
A4: Condition | B4: What it looks like | C4: Treatment | D4: Sub-base (cm) | E4: Base (cm) | F4: Primer seal | G4: First seal | H4: Second seal
A5: G | B5: Good — shape and camber sound, light maintenance only | C5: BLADE
A6: F | B6: Fair — camber lost in places, some potholing | C6: RESHAPE | D6: 10 | E6: 15 | F6: Y | G6: Y | H6: Y
A7: P | B7: Poor — badly deformed, potholed, camber gone | C7: RESHAPE | D7: 15 | E7: 15 | F7: Y | G7: Y | H7: Y
A8: VP | B8: Very poor — impassable in rain, gravel lost | C8: SCARIFY | D8: 15 | E8: 15 | F8: Y | G8: Y | H8: Y
A9: NR | B9: No road — new alignment or total reconstruction | C9: SCARIFY | D9: 15 | E9: 20 | F9: Y | G9: Y | H9: Y

Sheet F_Road_Data
A1: FORM F — ROAD DATA (the project constants the estimator prices with)
A2: These are the values 00_Project uses — it now READS this sheet, so this is where you change them. A row marked ! is a template figure that has not been confirmed for any particular road: settle those with the design engineer before the bill is issued, because haulage and overhaul alone routinely move a bill by a quarter. Road length, formation width, clearing width and the station count are measured or computed by the workbook and are not set here.
A4: Confirm? | B4: Parameter | C4: Value | D4: Unit | E4: Note | G4: Name
A5: CROSS-SECTION
B6: Carriageway width | C6: 7 | D6: m | G6: P_CW
B7: Shoulder width (one side) | C7: 1 | D7: m | E7: Formation width = CW + 2×SW, computed | G7: P_SW
B8: Existing carriageway width | C8: 4 | D8: m | G8: P_ExtCW
B9: Width for primer seal | C9: 8 | D9: m | G9: P_PrimeW
B10: Width of sealing | C10: 7 | D10: m | G10: P_SealW
A11: PAVEMENT
B12: Sub-base thickness | C12: 0.15 | D12: m | E12: Design thickness; E_Rules sets it per stretch in cm | G12: P_SubbaseT
B13: Base thickness | C13: 0.15 | D13: m | G13: P_BaseT
A14: ! | B14: Overhaul distance, sub-base | C14: 31 | D14: km | E14: Borrow pit to site, less the 1 km free haul | G14: P_OH_Sub
A15: ! | B15: Overhaul distance, base | C15: 40 | D15: km | E15: Quarry to site, less the 1 km free haul | G15: P_OH_Base
A16: SURFACING DESIGN RATES
B17: Primer seal binder rate | C17: 1.4 | D17: l/m² | G17: P_PrimeRate
B18: First seal binder rate | C18: 1.3 | D18: l/m² | G18: P_Seal1Rate
B19: Second seal binder rate | C19: 1.2 | D19: l/m² | G19: P_Seal2Rate
B20: Binder fraction of primer | C20: 0.84 | D20: - | E20: Balance is cutter oil | G20: P_BinderPct
B21: Cutter-oil fraction of primer | C21: 0.16 | D21: - | E21: Binder + cutter must come to 1.00 | G21: P_CutterPct
B22: 10 mm chipping coverage | C22: 120 | D22: m²/m³ | G22: P_Chip10
B23: 14 mm chipping coverage | C23: 100 | D23: m²/m³ | G23: P_Chip14
A24: HAULAGE DISTANCES
A25: ! | B25: Sand (fine aggregate) | C25: 15 | D25: km | G25: P_HaulSand
A26: ! | B26: Coarse aggregate | C26: 25 | D26: km | G26: P_HaulCoarse
A27: ! | B27: Chippings | C27: 60 | D27: km | G27: P_HaulChip
A28: ! | B28: Fill material | C28: 2 | D28: km | G28: P_HaulFill
A29: AGGREGATE YIELD FACTORS
A30: ! | B30: Fine agg. per m³ lean concrete | C30: 0.58 | D30: m³/m³ | E30: C10/40 | G30: P_FineLean
A31: ! | B31: Coarse agg. per m³ lean concrete | C31: 0.92 | D31: m³/m³ | E31: C10/40 | G31: P_CoarseLean
A32: ! | B32: Fine agg. per m³ structural conc. | C32: 0.55 | D32: m³/m³ | E32: C20/20 – C30/20 | G32: P_FineStr
A33: ! | B33: Coarse agg. per m³ struct. conc. | C33: 0.88 | D33: m³/m³ | E33: C20/20 – C30/20 | G33: P_CoarseStr
A34: ROAD FURNITURE
A35: ! | B35: Traffic signs per km (each type) | C35: 10 | D35: nr/km | E35: Three types are billed, so this is ×3 | G35: P_SignsPerKm
A36: ! | B36: STOP line per km | C36: 5 | D36: m/km | G36: P_StopPerKm
A37: ! | B37: Speed ramps per km | C37: 1 | D37: nr/km | G37: P_RampsPerKm
A38: ! | B38: Lane separation line factor | C38: 0.6 | D38: m/m | E38: of sealed length | G38: P_LaneLineF
A39: ! | B39: Centre line factor | C39: 0.4 | D39: m/m | G39: P_CentreLnF
A40: ! | B40: Edge line factor | C40: 2 | D40: m/m | E40: both edges | G40: P_EdgeLnF
A41: ! | B41: Pedestrian crossing factor | C41: 2 | D41: m/km | G41: P_PedXF

Sheet 01_Stations
A1: STATION SCHEDULE — the line diagram, stored as data
A2: One row per 50 m station. Columns D onward are now FORMULAS that resolve the condition survey on Forms A-E — do not type into them. Record the road on those forms instead; this sheet is the result.
A4: Station no. | B4: Chainage from | C4: Chainage | D4: Township | E4: Vegetation | F4: Raise road in low-lying area | G4: Height of fill | H4: Deep gully filling | I4: Cut to widen | J4: Height of cut | K4: Cut width (L+R) | L4: Fill to widen | M4: Height of fill to widen | N4: Fill width (L+R) | O4: Stone pitching | P4: V-ditch left | Q4: V-ditch right | R4: Culvert / drift | S4: Bridge | T4: Conc. U-drain left | U4: U-drain size left | V4: Conc. U-drain right | W4: U-drain size right | X4: Trapezoidal drain left | Y4: Trapezoidal drain right | Z4: Kerb left | AA4: Kerb right | AB4: Scour checks | AC4: Scour check spacing | AD4: Turnout left | AE4: Turnout right | AF4: Retaining wall left | AG4: Retaining wall right | AH4: Blading | AI4: Reshaping | AJ4: Scarifying | AK4: Gravel sub-base | AL4: Gravel base | AM4: Primer seal | AN4: First seal | AO4: Second seal | AQ4: working columns — matched Form C row, then the treatment rule resolved for that stretch
A5: nr | B5: m | D5: 1 | E5: code | F5: 1 | G5: cm | H5: m³ | I5: 1 | J5: cm | K5: m | L5: 1 | M5: cm | N5: m | O5: m² | P5: code | Q5: code | R5: code | S5: code | T5: 1 | U5: cm | V5: 1 | W5: cm | X5: 1 | Y5: 1 | Z5: 1 | AA5: 1 | AB5: 1/2 | AC5: m | AD5: m | AE5: m | AF5: 1 | AG5: 1 | AH5: 1 | AI5: 1 | AJ5: 1 | AK5: cm | AL5: cm | AM5: 1 | AN5: 1 | AO5: 1 | AQ5: C row | AR5: cond | AS5: rule | AT5: treat | AU5: sub | AV5: base | AW5: prime | AX5: seal1 | AY5: seal2
A6: 1 | B6: 0 | C6: 0+000 | D6: =IFERROR(LOOKUP(2,1/((A_Corridor!$A$5:$A$204<>"")*(A_Corridor!$A$5:$A$204<=$B6)*(A_Corridor!$B$5:$B$204>$B6)*(A_Corridor!$C$5:$C$204<>"")),IF(UPPER(A_Corridor!$C$5:$C$204)="Y",1,"")),"") | E6: =IFERROR(LOOKUP(2,1/((A_Corridor!$A$5:$A$204<>"")*(A_Corridor!$A$5:$A$204<=$B6)*(A_Corridor!$B$5:$B$204>$B6)*(A_Corridor!$D$5:$D$204<>"")),IF(A_Corridor!$D$5:$D$204="-","",UPPER(A_Corridor!$D$5:$D$204))),"") | F6: =IFERROR(LOOKUP(2,1/((A_Corridor!$A$5:$A$204<>"")*(A_Corridor!$A$5:$A$204<=$B6)*(A_Corridor!$B$5:$B$204>$B6)*(A_Corridor!$E$5:$E$204<>"")),IF(A_Corridor!$E$5:$E$204="-","",1)),"") | G6: =IFERROR(LOOKUP(2,1/((A_Corridor!$A$5:$A$204<>"")*(A_Corridor!$A$5:$A$204<=$B6)*(A_Corridor!$B$5:$B$204>$B6)*(A_Corridor!$E$5:$E$204<>"")),IF(A_Corridor!$E$5:$E$204="-","",A_Corridor!$E$5:$E$204)),"") | H6: =IFERROR(LOOKUP(2,1/((D_Points!$A$5:$A$204<>"")*(D_Points!$A$5:$A$204>=$B6)*(D_Points!$A$5:$A$204<$B6+P_Interval)*(UPPER(TRIM(D_Points!$B$5:$B$204))="GULLY")*(D_Points!$H$5:$H$204<>"")),D_Points!$H$5:$H$204),"") | I6: =IFERROR(LOOKUP(2,1/((A_Corridor!$A$5:$A$204<>"")*(A_Corridor!$A$5:$A$204<=$B6)*(A_Corridor!$B$5:$B$204>$B6)*(A_Corridor!$F$5:$F$204<>"")),IF(A_Corridor!$F$5:$F$204="-","",1)),"") | J6: =IFERROR(LOOKUP(2,1/((A_Corridor!$A$5:$A$204<>"")*(A_Corridor!$A$5:$A$204<=$B6)*(A_Corridor!$B$5:$B$204>$B6)*(A_Corridor!$F$5:$F$204<>"")),IF(A_Corridor!$F$5:$F$204="-","",A_Corridor!$F$5:$F$204)),"") | K6: =IFERROR(LOOKUP(2,1/((A_Corridor!$A$5:$A$204<>"")*(A_Corridor!$A$5:$A$204<=$B6)*(A_Corridor!$B$5:$B$204>$B6)*(A_Corridor!$G$5:$G$204<>"")),IF(A_Corridor!$G$5:$G$204="-","",A_Corridor!$G$5:$G$204)),"") | L6: =IFERROR(LOOKUP(2,1/((A_Corridor!$A$5:$A$204<>"")*(A_Corridor!$A$5:$A$204<=$B6)*(A_Corridor!$B$5:$B$204>$B6)*(A_Corridor!$H$5:$H$204<>"")),IF(A_Corridor!$H$5:$H$204="-","",1)),"") | M6: =IFERROR(LOOKUP(2,1/((A_Corridor!$A$5:$A$204<>"")*(A_Corridor!$A$5:$A$204<=$B6)*(A_Corridor!$B$5:$B$204>$B6)*(A_Corridor!$H$5:$H$204<>"")),IF(A_Corridor!$H$5:$H$204="-","",A_Corridor!$H$5:$H$204)),"") | N6: =IFERROR(LOOKUP(2,1/((A_Corridor!$A$5:$A$204<>"")*(A_Corridor!$A$5:$A$204<=$B6)*(A_Corridor!$B$5:$B$204>$B6)*(A_Corridor!$I$5:$I$204<>"")),IF(A_Corridor!$I$5:$I$204="-","",A_Corridor!$I$5:$I$204)),"") | O6: =IFERROR(LOOKUP(2,1/((D_Points!$A$5:$A$204<>"")*(D_Points!$A$5:$A$204>=$B6)*(D_Points!$A$5:$A$204<$B6+P_Interval)*(UPPER(TRIM(D_Points!$B$5:$B$204))="PITCHING")*(D_Points!$H$5:$H$204<>"")),D_Points!$H$5:$H$204),"") | P6: =IFERROR(LOOKUP(2,1/((B_Drainage!$A$5:$A$204<>"")*(B_Drainage!$A$5:$A$204<=$B6)*(B_Drainage!$B$5:$B$204>$B6)*(B_Drainage!$C$5:$C$204<>"")),IF(B_Drainage!$C$5:$C$204="-","",UPPER(B_Drainage!$C$5:$C$204))),"") | Q6: =IFERROR(LOOKUP(2,1/((B_Drainage!$A$5:$A$204<>"")*(B_Drainage!$A$5:$A$204<=$B6)*(B_Drainage!$B$5:$B$204>$B6)*(B_Drainage!$D$5:$D$204<>"")),IF(B_Drainage!$D$5:$D$204="-","",UPPER(B_Drainage!$D$5:$D$204))),"") | R6: =IFERROR(LOOKUP(2,1/((D_Points!$A$5:$A$204<>"")*(D_Points!$A$5:$A$204>=$B6)*(D_Points!$A$5:$A$204<$B6+P_Interval)*(RIGHT(UPPER(TRIM(D_Points!$B$5:$B$204)),8)="_CULVERT")),IF(LEFT(UPPER(TRIM(D_Points!$B$5:$B$204)),2)="EX",1,IF(LEFT(UPPER(TRIM(D_Points!$B$5:$B$204)),2)="PR",2,3))),"") | S6: =IFERROR(LOOKUP(2,1/((D_Points!$A$5:$A$204<>"")*(D_Points!$A$5:$A$204>=$B6)*(D_Points!$A$5:$A$204<$B6+P_Interval)*(RIGHT(UPPER(TRIM(D_Points!$B$5:$B$204)),7)="_BRIDGE")),IF(LEFT(UPPER(TRIM(D_Points!$B$5:$B$204)),2)="EX",1,IF(LEFT(UPPER(TRIM(D_Points!$B$5:$B$204)),2)="PR",2,2))),"") | T6: =IFERROR(LOOKUP(2,1/((B_Drainage!$A$5:$A$204<>"")*(B_Drainage!$A$5:$A$204<=$B6)*(B_Drainage!$B$5:$B$204>$B6)*(B_Drainage!$E$5:$E$204<>"")),IF(B_Drainage!$E$5:$E$204="-","",1)),"") | U6: =IFERROR(LOOKUP(2,1/((B_Drainage!$A$5:$A$204<>"")*(B_Drainage!$A$5:$A$204<=$B6)*(B_Drainage!$B$5:$B$204>$B6)*(B_Drainage!$E$5:$E$204<>"")),IF(B_Drainage!$E$5:$E$204="-","",B_Drainage!$E$5:$E$204)),"") | V6: =IFERROR(LOOKUP(2,1/((B_Drainage!$A$5:$A$204<>"")*(B_Drainage!$A$5:$A$204<=$B6)*(B_Drainage!$B$5:$B$204>$B6)*(B_Drainage!$F$5:$F$204<>"")),IF(B_Drainage!$F$5:$F$204="-","",1)),"") | W6: =IFERROR(LOOKUP(2,1/((B_Drainage!$A$5:$A$204<>"")*(B_Drainage!$A$5:$A$204<=$B6)*(B_Drainage!$B$5:$B$204>$B6)*(B_Drainage!$F$5:$F$204<>"")),IF(B_Drainage!$F$5:$F$204="-","",B_Drainage!$F$5:$F$204)),"") | X6: =IFERROR(LOOKUP(2,1/((B_Drainage!$A$5:$A$204<>"")*(B_Drainage!$A$5:$A$204<=$B6)*(B_Drainage!$B$5:$B$204>$B6)*(B_Drainage!$G$5:$G$204<>"")),IF(UPPER(B_Drainage!$G$5:$G$204)="Y",1,"")),"") | Y6: =IFERROR(LOOKUP(2,1/((B_Drainage!$A$5:$A$204<>"")*(B_Drainage!$A$5:$A$204<=$B6)*(B_Drainage!$B$5:$B$204>$B6)*(B_Drainage!$H$5:$H$204<>"")),IF(UPPER(B_Drainage!$H$5:$H$204)="Y",1,"")),"") | Z6: =IFERROR(LOOKUP(2,1/((B_Drainage!$A$5:$A$204<>"")*(B_Drainage!$A$5:$A$204<=$B6)*(B_Drainage!$B$5:$B$204>$B6)*(B_Drainage!$I$5:$I$204<>"")),IF(UPPER(B_Drainage!$I$5:$I$204)="Y",1,"")),"") | AA6: =IFERROR(LOOKUP(2,1/((B_Drainage!$A$5:$A$204<>"")*(B_Drainage!$A$5:$A$204<=$B6)*(B_Drainage!$B$5:$B$204>$B6)*(B_Drainage!$J$5:$J$204<>"")),IF(UPPER(B_Drainage!$J$5:$J$204)="Y",1,"")),"") | AB6: =IFERROR(LOOKUP(2,1/((B_Drainage!$A$5:$A$204<>"")*(B_Drainage!$A$5:$A$204<=$B6)*(B_Drainage!$B$5:$B$204>$B6)*(B_Drainage!$K$5:$K$204<>"")),IF(B_Drainage!$K$5:$K$204="-","",B_Drainage!$K$5:$K$204)),"") | AC6: =IFERROR(LOOKUP(2,1/((B_Drainage!$A$5:$A$204<>"")*(B_Drainage!$A$5:$A$204<=$B6)*(B_Drainage!$B$5:$B$204>$B6)*(B_Drainage!$L$5:$L$204<>"")),IF(B_Drainage!$L$5:$L$204="-","",B_Drainage!$L$5:$L$204)),"") | AD6: =IFERROR(LOOKUP(2,1/((D_Points!$A$5:$A$204<>"")*(D_Points!$A$5:$A$204>=$B6)*(D_Points!$A$5:$A$204<$B6+P_Interval)*(UPPER(TRIM(D_Points!$B$5:$B$204))="TURNOUT_L")*(D_Points!$H$5:$H$204<>"")),D_Points!$H$5:$H$204),"") | AE6: =IFERROR(LOOKUP(2,1/((D_Points!$A$5:$A$204<>"")*(D_Points!$A$5:$A$204>=$B6)*(D_Points!$A$5:$A$204<$B6+P_Interval)*(UPPER(TRIM(D_Points!$B$5:$B$204))="TURNOUT_R")*(D_Points!$H$5:$H$204<>"")),D_Points!$H$5:$H$204),"") | AF6: =IFERROR(LOOKUP(2,1/((B_Drainage!$A$5:$A$204<>"")*(B_Drainage!$A$5:$A$204<=$B6)*(B_Drainage!$B$5:$B$204>$B6)*(B_Drainage!$M$5:$M$204<>"")),IF(UPPER(B_Drainage!$M$5:$M$204)="Y",1,"")),"") | AG6: =IFERROR(LOOKUP(2,1/((B_Drainage!$A$5:$A$204<>"")*(B_Drainage!$A$5:$A$204<=$B6)*(B_Drainage!$B$5:$B$204>$B6)*(B_Drainage!$N$5:$N$204<>"")),IF(UPPER(B_Drainage!$N$5:$N$204)="Y",1,"")),"") | AH6: =IF($AT6="BLADE",1,"") | AI6: =IF($AT6="RESHAPE",1,"") | AJ6: =IF($AT6="SCARIFY",1,"") | AK6: =$AU6 | AL6: =$AV6 | AM6: =IF(OR(UPPER($AW6)="Y",$AW6=1),1,"") | AN6: =IF(OR(UPPER($AX6)="Y",$AX6=1),1,"") | AO6: =IF(OR(UPPER($AY6)="Y",$AY6=1),1,"") | AQ6: =IFERROR(LOOKUP(2,1/((C_Pavement!$A$5:$A$204<>"")*(C_Pavement!$A$5:$A$204<=$B6)*(C_Pavement!$B$5:$B$204>$B6)*(C_Pavement!$C$5:$C$204<>"")),ROW(C_Pavement!$C$5:$C$204)-4),"") | AR6: =IF($AQ6="","",UPPER(TRIM(INDEX(C_Pavement!$C$5:$C$204,$AQ6)))) | AS6: =IF($AR6="","",IFERROR(MATCH($AR6,E_Rules!$A$5:$A$9,0),"")) | AT6: =IF($AQ6="","",IF(INDEX(C_Pavement!$D$5:$D$204,$AQ6)<>"",UPPER(TRIM(INDEX(C_Pavement!$D$5:$D$204,$AQ6))),IF($AS6="","",INDEX(E_Rules!$C$5:$C$9,$AS6)))) | AU6: =IF($AQ6="","",IF(INDEX(C_Pavement!$E$5:$E$204,$AQ6)<>"",IF(INDEX(C_Pavement!$E$5:$E$204,$AQ6)="-","",INDEX(C_Pavement!$E$5:$E$204,$AQ6)),IF($AS6="","",INDEX(E_Rules!$D$5:$D$9,$AS6)))) | AV6: =IF($AQ6="","",IF(INDEX(C_Pavement!$F$5:$F$204,$AQ6)<>"",IF(INDEX(C_Pavement!$F$5:$F$204,$AQ6)="-","",INDEX(C_Pavement!$F$5:$F$204,$AQ6)),IF($AS6="","",INDEX(E_Rules!$E$5:$E$9,$AS6)))) | AW6: =IF($AQ6="","",IF(INDEX(C_Pavement!$G$5:$G$204,$AQ6)<>"",IF(INDEX(C_Pavement!$G$5:$G$204,$AQ6)="-","",INDEX(C_Pavement!$G$5:$G$204,$AQ6)),IF($AS6="","",INDEX(E_Rules!$F$5:$F$9,$AS6)))) | AX6: =IF($AQ6="","",IF(INDEX(C_Pavement!$H$5:$H$204,$AQ6)<>"",IF(INDEX(C_Pavement!$H$5:$H$204,$AQ6)="-","",INDEX(C_Pavement!$H$5:$H$204,$AQ6)),IF($AS6="","",INDEX(E_Rules!$G$5:$G$9,$AS6)))) | AY6: =IF($AQ6="","",IF(INDEX(C_Pavement!$I$5:$I$204,$AQ6)<>"",IF(INDEX(C_Pavement!$I$5:$I$204,$AQ6)="-","",INDEX(C_Pavement!$I$5:$I$204,$AQ6)),IF($AS6="","",INDEX(E_Rules!$H$5:$H$9,$AS6))))
A7: 2 | B7: 50 | C7: 0+050 | D7: =IFERROR(LOOKUP(2,1/((A_Corridor!$A$5:$A$204<>"")*(A_Corridor!$A$5:$A$204<=$B7)*(A_Corridor!$B$5:$B$204>$B7)*(A_Corridor!$C$5:$C$204<>"")),IF(UPPER(A_Corridor!$C$5:$C$204)="Y",1,"")),"") | E7: =IFERROR(LOOKUP(2,1/((A_Corridor!$A$5:$A$204<>"")*(A_Corridor!$A$5:$A$204<=$B7)*(A_Corridor!$B$5:$B$204>$B7)*(A_Corridor!$D$5:$D$204<>"")),IF(A_Corridor!$D$5:$D$204="-","",UPPER(A_Corridor!$D$5:$D$204))),"") | F7: =IFERROR(LOOKUP(2,1/((A_Corridor!$A$5:$A$204<>"")*(A_Corridor!$A$5:$A$204<=$B7)*(A_Corridor!$B$5:$B$204>$B7)*(A_Corridor!$E$5:$E$204<>"")),IF(A_Corridor!$E$5:$E$204="-","",1)),"") | G7: =IFERROR(LOOKUP(2,1/((A_Corridor!$A$5:$A$204<>"")*(A_Corridor!$A$5:$A$204<=$B7)*(A_Corridor!$B$5:$B$204>$B7)*(A_Corridor!$E$5:$E$204<>"")),IF(A_Corridor!$E$5:$E$204="-","",A_Corridor!$E$5:$E$204)),"") | H7: =IFERROR(LOOKUP(2,1/((D_Points!$A$5:$A$204<>"")*(D_Points!$A$5:$A$204>=$B7)*(D_Points!$A$5:$A$204<$B7+P_Interval)*(UPPER(TRIM(D_Points!$B$5:$B$204))="GULLY")*(D_Points!$H$5:$H$204<>"")),D_Points!$H$5:$H$204),"") | I7: =IFERROR(LOOKUP(2,1/((A_Corridor!$A$5:$A$204<>"")*(A_Corridor!$A$5:$A$204<=$B7)*(A_Corridor!$B$5:$B$204>$B7)*(A_Corridor!$F$5:$F$204<>"")),IF(A_Corridor!$F$5:$F$204="-","",1)),"") | J7: =IFERROR(LOOKUP(2,1/((A_Corridor!$A$5:$A$204<>"")*(A_Corridor!$A$5:$A$204<=$B7)*(A_Corridor!$B$5:$B$204>$B7)*(A_Corridor!$F$5:$F$204<>"")),IF(A_Corridor!$F$5:$F$204="-","",A_Corridor!$F$5:$F$204)),"") | K7: =IFERROR(LOOKUP(2,1/((A_Corridor!$A$5:$A$204<>"")*(A_Corridor!$A$5:$A$204<=$B7)*(A_Corridor!$B$5:$B$204>$B7)*(A_Corridor!$G$5:$G$204<>"")),IF(A_Corridor!$G$5:$G$204="-","",A_Corridor!$G$5:$G$204)),"") | L7: =IFERROR(LOOKUP(2,1/((A_Corridor!$A$5:$A$204<>"")*(A_Corridor!$A$5:$A$204<=$B7)*(A_Corridor!$B$5:$B$204>$B7)*(A_Corridor!$H$5:$H$204<>"")),IF(A_Corridor!$H$5:$H$204="-","",1)),"") | M7: =IFERROR(LOOKUP(2,1/((A_Corridor!$A$5:$A$204<>"")*(A_Corridor!$A$5:$A$204<=$B7)*(A_Corridor!$B$5:$B$204>$B7)*(A_Corridor!$H$5:$H$204<>"")),IF(A_Corridor!$H$5:$H$204="-","",A_Corridor!$H$5:$H$204)),"") | N7: =IFERROR(LOOKUP(2,1/((A_Corridor!$A$5:$A$204<>"")*(A_Corridor!$A$5:$A$204<=$B7)*(A_Corridor!$B$5:$B$204>$B7)*(A_Corridor!$I$5:$I$204<>"")),IF(A_Corridor!$I$5:$I$204="-","",A_Corridor!$I$5:$I$204)),"") | O7: =IFERROR(LOOKUP(2,1/((D_Points!$A$5:$A$204<>"")*(D_Points!$A$5:$A$204>=$B7)*(D_Points!$A$5:$A$204<$B7+P_Interval)*(UPPER(TRIM(D_Points!$B$5:$B$204))="PITCHING")*(D_Points!$H$5:$H$204<>"")),D_Points!$H$5:$H$204),"") | P7: =IFERROR(LOOKUP(2,1/((B_Drainage!$A$5:$A$204<>"")*(B_Drainage!$A$5:$A$204<=$B7)*(B_Drainage!$B$5:$B$204>$B7)*(B_Drainage!$C$5:$C$204<>"")),IF(B_Drainage!$C$5:$C$204="-","",UPPER(B_Drainage!$C$5:$C$204))),"") | Q7: =IFERROR(LOOKUP(2,1/((B_Drainage!$A$5:$A$204<>"")*(B_Drainage!$A$5:$A$204<=$B7)*(B_Drainage!$B$5:$B$204>$B7)*(B_Drainage!$D$5:$D$204<>"")),IF(B_Drainage!$D$5:$D$204="-","",UPPER(B_Drainage!$D$5:$D$204))),"") | R7: =IFERROR(LOOKUP(2,1/((D_Points!$A$5:$A$204<>"")*(D_Points!$A$5:$A$204>=$B7)*(D_Points!$A$5:$A$204<$B7+P_Interval)*(RIGHT(UPPER(TRIM(D_Points!$B$5:$B$204)),8)="_CULVERT")),IF(LEFT(UPPER(TRIM(D_Points!$B$5:$B$204)),2)="EX",1,IF(LEFT(UPPER(TRIM(D_Points!$B$5:$B$204)),2)="PR",2,3))),"") | S7: =IFERROR(LOOKUP(2,1/((D_Points!$A$5:$A$204<>"")*(D_Points!$A$5:$A$204>=$B7)*(D_Points!$A$5:$A$204<$B7+P_Interval)*(RIGHT(UPPER(TRIM(D_Points!$B$5:$B$204)),7)="_BRIDGE")),IF(LEFT(UPPER(TRIM(D_Points!$B$5:$B$204)),2)="EX",1,IF(LEFT(UPPER(TRIM(D_Points!$B$5:$B$204)),2)="PR",2,2))),"") | T7: =IFERROR(LOOKUP(2,1/((B_Drainage!$A$5:$A$204<>"")*(B_Drainage!$A$5:$A$204<=$B7)*(B_Drainage!$B$5:$B$204>$B7)*(B_Drainage!$E$5:$E$204<>"")),IF(B_Drainage!$E$5:$E$204="-","",1)),"") | U7: =IFERROR(LOOKUP(2,1/((B_Drainage!$A$5:$A$204<>"")*(B_Drainage!$A$5:$A$204<=$B7)*(B_Drainage!$B$5:$B$204>$B7)*(B_Drainage!$E$5:$E$204<>"")),IF(B_Drainage!$E$5:$E$204="-","",B_Drainage!$E$5:$E$204)),"") | V7: =IFERROR(LOOKUP(2,1/((B_Drainage!$A$5:$A$204<>"")*(B_Drainage!$A$5:$A$204<=$B7)*(B_Drainage!$B$5:$B$204>$B7)*(B_Drainage!$F$5:$F$204<>"")),IF(B_Drainage!$F$5:$F$204="-","",1)),"") | W7: =IFERROR(LOOKUP(2,1/((B_Drainage!$A$5:$A$204<>"")*(B_Drainage!$A$5:$A$204<=$B7)*(B_Drainage!$B$5:$B$204>$B7)*(B_Drainage!$F$5:$F$204<>"")),IF(B_Drainage!$F$5:$F$204="-","",B_Drainage!$F$5:$F$204)),"") | X7: =IFERROR(LOOKUP(2,1/((B_Drainage!$A$5:$A$204<>"")*(B_Drainage!$A$5:$A$204<=$B7)*(B_Drainage!$B$5:$B$204>$B7)*(B_Drainage!$G$5:$G$204<>"")),IF(UPPER(B_Drainage!$G$5:$G$204)="Y",1,"")),"") | Y7: =IFERROR(LOOKUP(2,1/((B_Drainage!$A$5:$A$204<>"")*(B_Drainage!$A$5:$A$204<=$B7)*(B_Drainage!$B$5:$B$204>$B7)*(B_Drainage!$H$5:$H$204<>"")),IF(UPPER(B_Drainage!$H$5:$H$204)="Y",1,"")),"") | Z7: =IFERROR(LOOKUP(2,1/((B_Drainage!$A$5:$A$204<>"")*(B_Drainage!$A$5:$A$204<=$B7)*(B_Drainage!$B$5:$B$204>$B7)*(B_Drainage!$I$5:$I$204<>"")),IF(UPPER(B_Drainage!$I$5:$I$204)="Y",1,"")),"") | AA7: =IFERROR(LOOKUP(2,1/((B_Drainage!$A$5:$A$204<>"")*(B_Drainage!$A$5:$A$204<=$B7)*(B_Drainage!$B$5:$B$204>$B7)*(B_Drainage!$J$5:$J$204<>"")),IF(UPPER(B_Drainage!$J$5:$J$204)="Y",1,"")),"") | AB7: =IFERROR(LOOKUP(2,1/((B_Drainage!$A$5:$A$204<>"")*(B_Drainage!$A$5:$A$204<=$B7)*(B_Drainage!$B$5:$B$204>$B7)*(B_Drainage!$K$5:$K$204<>"")),IF(B_Drainage!$K$5:$K$204="-","",B_Drainage!$K$5:$K$204)),"") | AC7: =IFERROR(LOOKUP(2,1/((B_Drainage!$A$5:$A$204<>"")*(B_Drainage!$A$5:$A$204<=$B7)*(B_Drainage!$B$5:$B$204>$B7)*(B_Drainage!$L$5:$L$204<>"")),IF(B_Drainage!$L$5:$L$204="-","",B_Drainage!$L$5:$L$204)),"") | AD7: =IFERROR(LOOKUP(2,1/((D_Points!$A$5:$A$204<>"")*(D_Points!$A$5:$A$204>=$B7)*(D_Points!$A$5:$A$204<$B7+P_Interval)*(UPPER(TRIM(D_Points!$B$5:$B$204))="TURNOUT_L")*(D_Points!$H$5:$H$204<>"")),D_Points!$H$5:$H$204),"") | AE7: =IFERROR(LOOKUP(2,1/((D_Points!$A$5:$A$204<>"")*(D_Points!$A$5:$A$204>=$B7)*(D_Points!$A$5:$A$204<$B7+P_Interval)*(UPPER(TRIM(D_Points!$B$5:$B$204))="TURNOUT_R")*(D_Points!$H$5:$H$204<>"")),D_Points!$H$5:$H$204),"") | AF7: =IFERROR(LOOKUP(2,1/((B_Drainage!$A$5:$A$204<>"")*(B_Drainage!$A$5:$A$204<=$B7)*(B_Drainage!$B$5:$B$204>$B7)*(B_Drainage!$M$5:$M$204<>"")),IF(UPPER(B_Drainage!$M$5:$M$204)="Y",1,"")),"") | AG7: =IFERROR(LOOKUP(2,1/((B_Drainage!$A$5:$A$204<>"")*(B_Drainage!$A$5:$A$204<=$B7)*(B_Drainage!$B$5:$B$204>$B7)*(B_Drainage!$N$5:$N$204<>"")),IF(UPPER(B_Drainage!$N$5:$N$204)="Y",1,"")),"") | AH7: =IF($AT7="BLADE",1,"") | AI7: =IF($AT7="RESHAPE",1,"") | AJ7: =IF($AT7="SCARIFY",1,"") | AK7: =$AU7 | AL7: =$AV7 | AM7: =IF(OR(UPPER($AW7)="Y",$AW7=1),1,"") | AN7: =IF(OR(UPPER($AX7)="Y",$AX7=1),1,"") | AO7: =IF(OR(UPPER($AY7)="Y",$AY7=1),1,"") | AQ7: =IFERROR(LOOKUP(2,1/((C_Pavement!$A$5:$A$204<>"")*(C_Pavement!$A$5:$A$204<=$B7)*(C_Pavement!$B$5:$B$204>$B7)*(C_Pavement!$C$5:$C$204<>"")),ROW(C_Pavement!$C$5:$C$204)-4),"") | AR7: =IF($AQ7="","",UPPER(TRIM(INDEX(C_Pavement!$C$5:$C$204,$AQ7)))) | AS7: =IF($AR7="","",IFERROR(MATCH($AR7,E_Rules!$A$5:$A$9,0),"")) | AT7: =IF($AQ7="","",IF(INDEX(C_Pavement!$D$5:$D$204,$AQ7)<>"",UPPER(TRIM(INDEX(C_Pavement!$D$5:$D$204,$AQ7))),IF($AS7="","",INDEX(E_Rules!$C$5:$C$9,$AS7)))) | AU7: =IF($AQ7="","",IF(INDEX(C_Pavement!$E$5:$E$204,$AQ7)<>"",IF(INDEX(C_Pavement!$E$5:$E$204,$AQ7)="-","",INDEX(C_Pavement!$E$5:$E$204,$AQ7)),IF($AS7="","",INDEX(E_Rules!$D$5:$D$9,$AS7)))) | AV7: =IF($AQ7="","",IF(INDEX(C_Pavement!$F$5:$F$204,$AQ7)<>"",IF(INDEX(C_Pavement!$F$5:$F$204,$AQ7)="-","",INDEX(C_Pavement!$F$5:$F$204,$AQ7)),IF($AS7="","",INDEX(E_Rules!$E$5:$E$9,$AS7)))) | AW7: =IF($AQ7="","",IF(INDEX(C_Pavement!$G$5:$G$204,$AQ7)<>"",IF(INDEX(C_Pavement!$G$5:$G$204,$AQ7)="-","",INDEX(C_Pavement!$G$5:$G$204,$AQ7)),IF($AS7="","",INDEX(E_Rules!$F$5:$F$9,$AS7)))) | AX7: =IF($AQ7="","",IF(INDEX(C_Pavement!$H$5:$H$204,$AQ7)<>"",IF(INDEX(C_Pavement!$H$5:$H$204,$AQ7)="-","",INDEX(C_Pavement!$H$5:$H$204,$AQ7)),IF($AS7="","",INDEX(E_Rules!$G$5:$G$9,$AS7)))) | AY7: =IF($AQ7="","",IF(INDEX(C_Pavement!$I$5:$I$204,$AQ7)<>"",IF(INDEX(C_Pavement!$I$5:$I$204,$AQ7)="-","",INDEX(C_Pavement!$I$5:$I$204,$AQ7)),IF($AS7="","",INDEX(E_Rules!$H$5:$H$9,$AS7))))
A8: 3 | B8: 100 | C8: 0+100 | D8: =IFERROR(LOOKUP(2,1/((A_Corridor!$A$5:$A$204<>"")*(A_Corridor!$A$5:$A$204<=$B8)*(A_Corridor!$B$5:$B$204>$B8)*(A_Corridor!$C$5:$C$204<>"")),IF(UPPER(A_Corridor!$C$5:$C$204)="Y",1,"")),"") | E8: =IFERROR(LOOKUP(2,1/((A_Corridor!$A$5:$A$204<>"")*(A_Corridor!$A$5:$A$204<=$B8)*(A_Corridor!$B$5:$B$204>$B8)*(A_Corridor!$D$5:$D$204<>"")),IF(A_Corridor!$D$5:$D$204="-","",UPPER(A_Corridor!$D$5:$D$204))),"") | F8: =IFERROR(LOOKUP(2,1/((A_Corridor!$A$5:$A$204<>"")*(A_Corridor!$A$5:$A$204<=$B8)*(A_Corridor!$B$5:$B$204>$B8)*(A_Corridor!$E$5:$E$204<>"")),IF(A_Corridor!$E$5:$E$204="-","",1)),"") | G8: =IFERROR(LOOKUP(2,1/((A_Corridor!$A$5:$A$204<>"")*(A_Corridor!$A$5:$A$204<=$B8)*(A_Corridor!$B$5:$B$204>$B8)*(A_Corridor!$E$5:$E$204<>"")),IF(A_Corridor!$E$5:$E$204="-","",A_Corridor!$E$5:$E$204)),"") | H8: =IFERROR(LOOKUP(2,1/((D_Points!$A$5:$A$204<>"")*(D_Points!$A$5:$A$204>=$B8)*(D_Points!$A$5:$A$204<$B8+P_Interval)*(UPPER(TRIM(D_Points!$B$5:$B$204))="GULLY")*(D_Points!$H$5:$H$204<>"")),D_Points!$H$5:$H$204),"") | I8: =IFERROR(LOOKUP(2,1/((A_Corridor!$A$5:$A$204<>"")*(A_Corridor!$A$5:$A$204<=$B8)*(A_Corridor!$B$5:$B$204>$B8)*(A_Corridor!$F$5:$F$204<>"")),IF(A_Corridor!$F$5:$F$204="-","",1)),"") | J8: =IFERROR(LOOKUP(2,1/((A_Corridor!$A$5:$A$204<>"")*(A_Corridor!$A$5:$A$204<=$B8)*(A_Corridor!$B$5:$B$204>$B8)*(A_Corridor!$F$5:$F$204<>"")),IF(A_Corridor!$F$5:$F$204="-","",A_Corridor!$F$5:$F$204)),"") | K8: =IFERROR(LOOKUP(2,1/((A_Corridor!$A$5:$A$204<>"")*(A_Corridor!$A$5:$A$204<=$B8)*(A_Corridor!$B$5:$B$204>$B8)*(A_Corridor!$G$5:$G$204<>"")),IF(A_Corridor!$G$5:$G$204="-","",A_Corridor!$G$5:$G$204)),"") | L8: =IFERROR(LOOKUP(2,1/((A_Corridor!$A$5:$A$204<>"")*(A_Corridor!$A$5:$A$204<=$B8)*(A_Corridor!$B$5:$B$204>$B8)*(A_Corridor!$H$5:$H$204<>"")),IF(A_Corridor!$H$5:$H$204="-","",1)),"") | M8: =IFERROR(LOOKUP(2,1/((A_Corridor!$A$5:$A$204<>"")*(A_Corridor!$A$5:$A$204<=$B8)*(A_Corridor!$B$5:$B$204>$B8)*(A_Corridor!$H$5:$H$204<>"")),IF(A_Corridor!$H$5:$H$204="-","",A_Corridor!$H$5:$H$204)),"") | N8: =IFERROR(LOOKUP(2,1/((A_Corridor!$A$5:$A$204<>"")*(A_Corridor!$A$5:$A$204<=$B8)*(A_Corridor!$B$5:$B$204>$B8)*(A_Corridor!$I$5:$I$204<>"")),IF(A_Corridor!$I$5:$I$204="-","",A_Corridor!$I$5:$I$204)),"") | O8: =IFERROR(LOOKUP(2,1/((D_Points!$A$5:$A$204<>"")*(D_Points!$A$5:$A$204>=$B8)*(D_Points!$A$5:$A$204<$B8+P_Interval)*(UPPER(TRIM(D_Points!$B$5:$B$204))="PITCHING")*(D_Points!$H$5:$H$204<>"")),D_Points!$H$5:$H$204),"") | P8: =IFERROR(LOOKUP(2,1/((B_Drainage!$A$5:$A$204<>"")*(B_Drainage!$A$5:$A$204<=$B8)*(B_Drainage!$B$5:$B$204>$B8)*(B_Drainage!$C$5:$C$204<>"")),IF(B_Drainage!$C$5:$C$204="-","",UPPER(B_Drainage!$C$5:$C$204))),"") | Q8: =IFERROR(LOOKUP(2,1/((B_Drainage!$A$5:$A$204<>"")*(B_Drainage!$A$5:$A$204<=$B8)*(B_Drainage!$B$5:$B$204>$B8)*(B_Drainage!$D$5:$D$204<>"")),IF(B_Drainage!$D$5:$D$204="-","",UPPER(B_Drainage!$D$5:$D$204))),"") | R8: =IFERROR(LOOKUP(2,1/((D_Points!$A$5:$A$204<>"")*(D_Points!$A$5:$A$204>=$B8)*(D_Points!$A$5:$A$204<$B8+P_Interval)*(RIGHT(UPPER(TRIM(D_Points!$B$5:$B$204)),8)="_CULVERT")),IF(LEFT(UPPER(TRIM(D_Points!$B$5:$B$204)),2)="EX",1,IF(LEFT(UPPER(TRIM(D_Points!$B$5:$B$204)),2)="PR",2,3))),"") | S8: =IFERROR(LOOKUP(2,1/((D_Points!$A$5:$A$204<>"")*(D_Points!$A$5:$A$204>=$B8)*(D_Points!$A$5:$A$204<$B8+P_Interval)*(RIGHT(UPPER(TRIM(D_Points!$B$5:$B$204)),7)="_BRIDGE")),IF(LEFT(UPPER(TRIM(D_Points!$B$5:$B$204)),2)="EX",1,IF(LEFT(UPPER(TRIM(D_Points!$B$5:$B$204)),2)="PR",2,2))),"") | T8: =IFERROR(LOOKUP(2,1/((B_Drainage!$A$5:$A$204<>"")*(B_Drainage!$A$5:$A$204<=$B8)*(B_Drainage!$B$5:$B$204>$B8)*(B_Drainage!$E$5:$E$204<>"")),IF(B_Drainage!$E$5:$E$204="-","",1)),"") | U8: =IFERROR(LOOKUP(2,1/((B_Drainage!$A$5:$A$204<>"")*(B_Drainage!$A$5:$A$204<=$B8)*(B_Drainage!$B$5:$B$204>$B8)*(B_Drainage!$E$5:$E$204<>"")),IF(B_Drainage!$E$5:$E$204="-","",B_Drainage!$E$5:$E$204)),"") | V8: =IFERROR(LOOKUP(2,1/((B_Drainage!$A$5:$A$204<>"")*(B_Drainage!$A$5:$A$204<=$B8)*(B_Drainage!$B$5:$B$204>$B8)*(B_Drainage!$F$5:$F$204<>"")),IF(B_Drainage!$F$5:$F$204="-","",1)),"") | W8: =IFERROR(LOOKUP(2,1/((B_Drainage!$A$5:$A$204<>"")*(B_Drainage!$A$5:$A$204<=$B8)*(B_Drainage!$B$5:$B$204>$B8)*(B_Drainage!$F$5:$F$204<>"")),IF(B_Drainage!$F$5:$F$204="-","",B_Drainage!$F$5:$F$204)),"") | X8: =IFERROR(LOOKUP(2,1/((B_Drainage!$A$5:$A$204<>"")*(B_Drainage!$A$5:$A$204<=$B8)*(B_Drainage!$B$5:$B$204>$B8)*(B_Drainage!$G$5:$G$204<>"")),IF(UPPER(B_Drainage!$G$5:$G$204)="Y",1,"")),"") | Y8: =IFERROR(LOOKUP(2,1/((B_Drainage!$A$5:$A$204<>"")*(B_Drainage!$A$5:$A$204<=$B8)*(B_Drainage!$B$5:$B$204>$B8)*(B_Drainage!$H$5:$H$204<>"")),IF(UPPER(B_Drainage!$H$5:$H$204)="Y",1,"")),"") | Z8: =IFERROR(LOOKUP(2,1/((B_Drainage!$A$5:$A$204<>"")*(B_Drainage!$A$5:$A$204<=$B8)*(B_Drainage!$B$5:$B$204>$B8)*(B_Drainage!$I$5:$I$204<>"")),IF(UPPER(B_Drainage!$I$5:$I$204)="Y",1,"")),"") | AA8: =IFERROR(LOOKUP(2,1/((B_Drainage!$A$5:$A$204<>"")*(B_Drainage!$A$5:$A$204<=$B8)*(B_Drainage!$B$5:$B$204>$B8)*(B_Drainage!$J$5:$J$204<>"")),IF(UPPER(B_Drainage!$J$5:$J$204)="Y",1,"")),"") | AB8: =IFERROR(LOOKUP(2,1/((B_Drainage!$A$5:$A$204<>"")*(B_Drainage!$A$5:$A$204<=$B8)*(B_Drainage!$B$5:$B$204>$B8)*(B_Drainage!$K$5:$K$204<>"")),IF(B_Drainage!$K$5:$K$204="-","",B_Drainage!$K$5:$K$204)),"") | AC8: =IFERROR(LOOKUP(2,1/((B_Drainage!$A$5:$A$204<>"")*(B_Drainage!$A$5:$A$204<=$B8)*(B_Drainage!$B$5:$B$204>$B8)*(B_Drainage!$L$5:$L$204<>"")),IF(B_Drainage!$L$5:$L$204="-","",B_Drainage!$L$5:$L$204)),"") | AD8: =IFERROR(LOOKUP(2,1/((D_Points!$A$5:$A$204<>"")*(D_Points!$A$5:$A$204>=$B8)*(D_Points!$A$5:$A$204<$B8+P_Interval)*(UPPER(TRIM(D_Points!$B$5:$B$204))="TURNOUT_L")*(D_Points!$H$5:$H$204<>"")),D_Points!$H$5:$H$204),"") | AE8: =IFERROR(LOOKUP(2,1/((D_Points!$A$5:$A$204<>"")*(D_Points!$A$5:$A$204>=$B8)*(D_Points!$A$5:$A$204<$B8+P_Interval)*(UPPER(TRIM(D_Points!$B$5:$B$204))="TURNOUT_R")*(D_Points!$H$5:$H$204<>"")),D_Points!$H$5:$H$204),"") | AF8: =IFERROR(LOOKUP(2,1/((B_Drainage!$A$5:$A$204<>"")*(B_Drainage!$A$5:$A$204<=$B8)*(B_Drainage!$B$5:$B$204>$B8)*(B_Drainage!$M$5:$M$204<>"")),IF(UPPER(B_Drainage!$M$5:$M$204)="Y",1,"")),"") | AG8: =IFERROR(LOOKUP(2,1/((B_Drainage!$A$5:$A$204<>"")*(B_Drainage!$A$5:$A$204<=$B8)*(B_Drainage!$B$5:$B$204>$B8)*(B_Drainage!$N$5:$N$204<>"")),IF(UPPER(B_Drainage!$N$5:$N$204)="Y",1,"")),"") | AH8: =IF($AT8="BLADE",1,"") | AI8: =IF($AT8="RESHAPE",1,"") | AJ8: =IF($AT8="SCARIFY",1,"") | AK8: =$AU8 | AL8: =$AV8 | AM8: =IF(OR(UPPER($AW8)="Y",$AW8=1),1,"") | AN8: =IF(OR(UPPER($AX8)="Y",$AX8=1),1,"") | AO8: =IF(OR(UPPER($AY8)="Y",$AY8=1),1,"") | AQ8: =IFERROR(LOOKUP(2,1/((C_Pavement!$A$5:$A$204<>"")*(C_Pavement!$A$5:$A$204<=$B8)*(C_Pavement!$B$5:$B$204>$B8)*(C_Pavement!$C$5:$C$204<>"")),ROW(C_Pavement!$C$5:$C$204)-4),"") | AR8: =IF($AQ8="","",UPPER(TRIM(INDEX(C_Pavement!$C$5:$C$204,$AQ8)))) | AS8: =IF($AR8="","",IFERROR(MATCH($AR8,E_Rules!$A$5:$A$9,0),"")) | AT8: =IF($AQ8="","",IF(INDEX(C_Pavement!$D$5:$D$204,$AQ8)<>"",UPPER(TRIM(INDEX(C_Pavement!$D$5:$D$204,$AQ8))),IF($AS8="","",INDEX(E_Rules!$C$5:$C$9,$AS8)))) | AU8: =IF($AQ8="","",IF(INDEX(C_Pavement!$E$5:$E$204,$AQ8)<>"",IF(INDEX(C_Pavement!$E$5:$E$204,$AQ8)="-","",INDEX(C_Pavement!$E$5:$E$204,$AQ8)),IF($AS8="","",INDEX(E_Rules!$D$5:$D$9,$AS8)))) | AV8: =IF($AQ8="","",IF(INDEX(C_Pavement!$F$5:$F$204,$AQ8)<>"",IF(INDEX(C_Pavement!$F$5:$F$204,$AQ8)="-","",INDEX(C_Pavement!$F$5:$F$204,$AQ8)),IF($AS8="","",INDEX(E_Rules!$E$5:$E$9,$AS8)))) | AW8: =IF($AQ8="","",IF(INDEX(C_Pavement!$G$5:$G$204,$AQ8)<>"",IF(INDEX(C_Pavement!$G$5:$G$204,$AQ8)="-","",INDEX(C_Pavement!$G$5:$G$204,$AQ8)),IF($AS8="","",INDEX(E_Rules!$F$5:$F$9,$AS8)))) | AX8: =IF($AQ8="","",IF(INDEX(C_Pavement!$H$5:$H$204,$AQ8)<>"",IF(INDEX(C_Pavement!$H$5:$H$204,$AQ8)="-","",INDEX(C_Pavement!$H$5:$H$204,$AQ8)),IF($AS8="","",INDEX(E_Rules!$G$5:$G$9,$AS8)))) | AY8: =IF($AQ8="","",IF(INDEX(C_Pavement!$I$5:$I$204,$AQ8)<>"",IF(INDEX(C_Pavement!$I$5:$I$204,$AQ8)="-","",INDEX(C_Pavement!$I$5:$I$204,$AQ8)),IF($AS8="","",INDEX(E_Rules!$H$5:$H$9,$AS8))))
A9: 4 | B9: 150 | C9: 0+150 | D9: =IFERROR(LOOKUP(2,1/((A_Corridor!$A$5:$A$204<>"")*(A_Corridor!$A$5:$A$204<=$B9)*(A_Corridor!$B$5:$B$204>$B9)*(A_Corridor!$C$5:$C$204<>"")),IF(UPPER(A_Corridor!$C$5:$C$204)="Y",1,"")),"") | E9: =IFERROR(LOOKUP(2,1/((A_Corridor!$A$5:$A$204<>"")*(A_Corridor!$A$5:$A$204<=$B9)*(A_Corridor!$B$5:$B$204>$B9)*(A_Corridor!$D$5:$D$204<>"")),IF(A_Corridor!$D$5:$D$204="-","",UPPER(A_Corridor!$D$5:$D$204))),"") | F9: =IFERROR(LOOKUP(2,1/((A_Corridor!$A$5:$A$204<>"")*(A_Corridor!$A$5:$A$204<=$B9)*(A_Corridor!$B$5:$B$204>$B9)*(A_Corridor!$E$5:$E$204<>"")),IF(A_Corridor!$E$5:$E$204="-","",1)),"") | G9: =IFERROR(LOOKUP(2,1/((A_Corridor!$A$5:$A$204<>"")*(A_Corridor!$A$5:$A$204<=$B9)*(A_Corridor!$B$5:$B$204>$B9)*(A_Corridor!$E$5:$E$204<>"")),IF(A_Corridor!$E$5:$E$204="-","",A_Corridor!$E$5:$E$204)),"") | H9: =IFERROR(LOOKUP(2,1/((D_Points!$A$5:$A$204<>"")*(D_Points!$A$5:$A$204>=$B9)*(D_Points!$A$5:$A$204<$B9+P_Interval)*(UPPER(TRIM(D_Points!$B$5:$B$204))="GULLY")*(D_Points!$H$5:$H$204<>"")),D_Points!$H$5:$H$204),"") | I9: =IFERROR(LOOKUP(2,1/((A_Corridor!$A$5:$A$204<>"")*(A_Corridor!$A$5:$A$204<=$B9)*(A_Corridor!$B$5:$B$204>$B9)*(A_Corridor!$F$5:$F$204<>"")),IF(A_Corridor!$F$5:$F$204="-","",1)),"") | J9: =IFERROR(LOOKUP(2,1/((A_Corridor!$A$5:$A$204<>"")*(A_Corridor!$A$5:$A$204<=$B9)*(A_Corridor!$B$5:$B$204>$B9)*(A_Corridor!$F$5:$F$204<>"")),IF(A_Corridor!$F$5:$F$204="-","",A_Corridor!$F$5:$F$204)),"") | K9: =IFERROR(LOOKUP(2,1/((A_Corridor!$A$5:$A$204<>"")*(A_Corridor!$A$5:$A$204<=$B9)*(A_Corridor!$B$5:$B$204>$B9)*(A_Corridor!$G$5:$G$204<>"")),IF(A_Corridor!$G$5:$G$204="-","",A_Corridor!$G$5:$G$204)),"") | L9: =IFERROR(LOOKUP(2,1/((A_Corridor!$A$5:$A$204<>"")*(A_Corridor!$A$5:$A$204<=$B9)*(A_Corridor!$B$5:$B$204>$B9)*(A_Corridor!$H$5:$H$204<>"")),IF(A_Corridor!$H$5:$H$204="-","",1)),"") | M9: =IFERROR(LOOKUP(2,1/((A_Corridor!$A$5:$A$204<>"")*(A_Corridor!$A$5:$A$204<=$B9)*(A_Corridor!$B$5:$B$204>$B9)*(A_Corridor!$H$5:$H$204<>"")),IF(A_Corridor!$H$5:$H$204="-","",A_Corridor!$H$5:$H$204)),"") | N9: =IFERROR(LOOKUP(2,1/((A_Corridor!$A$5:$A$204<>"")*(A_Corridor!$A$5:$A$204<=$B9)*(A_Corridor!$B$5:$B$204>$B9)*(A_Corridor!$I$5:$I$204<>"")),IF(A_Corridor!$I$5:$I$204="-","",A_Corridor!$I$5:$I$204)),"") | O9: =IFERROR(LOOKUP(2,1/((D_Points!$A$5:$A$204<>"")*(D_Points!$A$5:$A$204>=$B9)*(D_Points!$A$5:$A$204<$B9+P_Interval)*(UPPER(TRIM(D_Points!$B$5:$B$204))="PITCHING")*(D_Points!$H$5:$H$204<>"")),D_Points!$H$5:$H$204),"") | P9: =IFERROR(LOOKUP(2,1/((B_Drainage!$A$5:$A$204<>"")*(B_Drainage!$A$5:$A$204<=$B9)*(B_Drainage!$B$5:$B$204>$B9)*(B_Drainage!$C$5:$C$204<>"")),IF(B_Drainage!$C$5:$C$204="-","",UPPER(B_Drainage!$C$5:$C$204))),"") | Q9: =IFERROR(LOOKUP(2,1/((B_Drainage!$A$5:$A$204<>"")*(B_Drainage!$A$5:$A$204<=$B9)*(B_Drainage!$B$5:$B$204>$B9)*(B_Drainage!$D$5:$D$204<>"")),IF(B_Drainage!$D$5:$D$204="-","",UPPER(B_Drainage!$D$5:$D$204))),"") | R9: =IFERROR(LOOKUP(2,1/((D_Points!$A$5:$A$204<>"")*(D_Points!$A$5:$A$204>=$B9)*(D_Points!$A$5:$A$204<$B9+P_Interval)*(RIGHT(UPPER(TRIM(D_Points!$B$5:$B$204)),8)="_CULVERT")),IF(LEFT(UPPER(TRIM(D_Points!$B$5:$B$204)),2)="EX",1,IF(LEFT(UPPER(TRIM(D_Points!$B$5:$B$204)),2)="PR",2,3))),"") | S9: =IFERROR(LOOKUP(2,1/((D_Points!$A$5:$A$204<>"")*(D_Points!$A$5:$A$204>=$B9)*(D_Points!$A$5:$A$204<$B9+P_Interval)*(RIGHT(UPPER(TRIM(D_Points!$B$5:$B$204)),7)="_BRIDGE")),IF(LEFT(UPPER(TRIM(D_Points!$B$5:$B$204)),2)="EX",1,IF(LEFT(UPPER(TRIM(D_Points!$B$5:$B$204)),2)="PR",2,2))),"") | T9: =IFERROR(LOOKUP(2,1/((B_Drainage!$A$5:$A$204<>"")*(B_Drainage!$A$5:$A$204<=$B9)*(B_Drainage!$B$5:$B$204>$B9)*(B_Drainage!$E$5:$E$204<>"")),IF(B_Drainage!$E$5:$E$204="-","",1)),"") | U9: =IFERROR(LOOKUP(2,1/((B_Drainage!$A$5:$A$204<>"")*(B_Drainage!$A$5:$A$204<=$B9)*(B_Drainage!$B$5:$B$204>$B9)*(B_Drainage!$E$5:$E$204<>"")),IF(B_Drainage!$E$5:$E$204="-","",B_Drainage!$E$5:$E$204)),"") | V9: =IFERROR(LOOKUP(2,1/((B_Drainage!$A$5:$A$204<>"")*(B_Drainage!$A$5:$A$204<=$B9)*(B_Drainage!$B$5:$B$204>$B9)*(B_Drainage!$F$5:$F$204<>"")),IF(B_Drainage!$F$5:$F$204="-","",1)),"") | W9: =IFERROR(LOOKUP(2,1/((B_Drainage!$A$5:$A$204<>"")*(B_Drainage!$A$5:$A$204<=$B9)*(B_Drainage!$B$5:$B$204>$B9)*(B_Drainage!$F$5:$F$204<>"")),IF(B_Drainage!$F$5:$F$204="-","",B_Drainage!$F$5:$F$204)),"") | X9: =IFERROR(LOOKUP(2,1/((B_Drainage!$A$5:$A$204<>"")*(B_Drainage!$A$5:$A$204<=$B9)*(B_Drainage!$B$5:$B$204>$B9)*(B_Drainage!$G$5:$G$204<>"")),IF(UPPER(B_Drainage!$G$5:$G$204)="Y",1,"")),"") | Y9: =IFERROR(LOOKUP(2,1/((B_Drainage!$A$5:$A$204<>"")*(B_Drainage!$A$5:$A$204<=$B9)*(B_Drainage!$B$5:$B$204>$B9)*(B_Drainage!$H$5:$H$204<>"")),IF(UPPER(B_Drainage!$H$5:$H$204)="Y",1,"")),"") | Z9: =IFERROR(LOOKUP(2,1/((B_Drainage!$A$5:$A$204<>"")*(B_Drainage!$A$5:$A$204<=$B9)*(B_Drainage!$B$5:$B$204>$B9)*(B_Drainage!$I$5:$I$204<>"")),IF(UPPER(B_Drainage!$I$5:$I$204)="Y",1,"")),"") | AA9: =IFERROR(LOOKUP(2,1/((B_Drainage!$A$5:$A$204<>"")*(B_Drainage!$A$5:$A$204<=$B9)*(B_Drainage!$B$5:$B$204>$B9)*(B_Drainage!$J$5:$J$204<>"")),IF(UPPER(B_Drainage!$J$5:$J$204)="Y",1,"")),"") | AB9: =IFERROR(LOOKUP(2,1/((B_Drainage!$A$5:$A$204<>"")*(B_Drainage!$A$5:$A$204<=$B9)*(B_Drainage!$B$5:$B$204>$B9)*(B_Drainage!$K$5:$K$204<>"")),IF(B_Drainage!$K$5:$K$204="-","",B_Drainage!$K$5:$K$204)),"") | AC9: =IFERROR(LOOKUP(2,1/((B_Drainage!$A$5:$A$204<>"")*(B_Drainage!$A$5:$A$204<=$B9)*(B_Drainage!$B$5:$B$204>$B9)*(B_Drainage!$L$5:$L$204<>"")),IF(B_Drainage!$L$5:$L$204="-","",B_Drainage!$L$5:$L$204)),"") | AD9: =IFERROR(LOOKUP(2,1/((D_Points!$A$5:$A$204<>"")*(D_Points!$A$5:$A$204>=$B9)*(D_Points!$A$5:$A$204<$B9+P_Interval)*(UPPER(TRIM(D_Points!$B$5:$B$204))="TURNOUT_L")*(D_Points!$H$5:$H$204<>"")),D_Points!$H$5:$H$204),"") | AE9: =IFERROR(LOOKUP(2,1/((D_Points!$A$5:$A$204<>"")*(D_Points!$A$5:$A$204>=$B9)*(D_Points!$A$5:$A$204<$B9+P_Interval)*(UPPER(TRIM(D_Points!$B$5:$B$204))="TURNOUT_R")*(D_Points!$H$5:$H$204<>"")),D_Points!$H$5:$H$204),"") | AF9: =IFERROR(LOOKUP(2,1/((B_Drainage!$A$5:$A$204<>"")*(B_Drainage!$A$5:$A$204<=$B9)*(B_Drainage!$B$5:$B$204>$B9)*(B_Drainage!$M$5:$M$204<>"")),IF(UPPER(B_Drainage!$M$5:$M$204)="Y",1,"")),"") | AG9: =IFERROR(LOOKUP(2,1/((B_Drainage!$A$5:$A$204<>"")*(B_Drainage!$A$5:$A$204<=$B9)*(B_Drainage!$B$5:$B$204>$B9)*(B_Drainage!$N$5:$N$204<>"")),IF(UPPER(B_Drainage!$N$5:$N$204)="Y",1,"")),"") | AH9: =IF($AT9="BLADE",1,"") | AI9: =IF($AT9="RESHAPE",1,"") | AJ9: =IF($AT9="SCARIFY",1,"") | AK9: =$AU9 | AL9: =$AV9 | AM9: =IF(OR(UPPER($AW9)="Y",$AW9=1),1,"") | AN9: =IF(OR(UPPER($AX9)="Y",$AX9=1),1,"") | AO9: =IF(OR(UPPER($AY9)="Y",$AY9=1),1,"") | AQ9: =IFERROR(LOOKUP(2,1/((C_Pavement!$A$5:$A$204<>"")*(C_Pavement!$A$5:$A$204<=$B9)*(C_Pavement!$B$5:$B$204>$B9)*(C_Pavement!$C$5:$C$204<>"")),ROW(C_Pavement!$C$5:$C$204)-4),"") | AR9: =IF($AQ9="","",UPPER(TRIM(INDEX(C_Pavement!$C$5:$C$204,$AQ9)))) | AS9: =IF($AR9="","",IFERROR(MATCH($AR9,E_Rules!$A$5:$A$9,0),"")) | AT9: =IF($AQ9="","",IF(INDEX(C_Pavement!$D$5:$D$204,$AQ9)<>"",UPPER(TRIM(INDEX(C_Pavement!$D$5:$D$204,$AQ9))),IF($AS9="","",INDEX(E_Rules!$C$5:$C$9,$AS9)))) | AU9: =IF($AQ9="","",IF(INDEX(C_Pavement!$E$5:$E$204,$AQ9)<>"",IF(INDEX(C_Pavement!$E$5:$E$204,$AQ9)="-","",INDEX(C_Pavement!$E$5:$E$204,$AQ9)),IF($AS9="","",INDEX(E_Rules!$D$5:$D$9,$AS9)))) | AV9: =IF($AQ9="","",IF(INDEX(C_Pavement!$F$5:$F$204,$AQ9)<>"",IF(INDEX(C_Pavement!$F$5:$F$204,$AQ9)="-","",INDEX(C_Pavement!$F$5:$F$204,$AQ9)),IF($AS9="","",INDEX(E_Rules!$E$5:$E$9,$AS9)))) | AW9: =IF($AQ9="","",IF(INDEX(C_Pavement!$G$5:$G$204,$AQ9)<>"",IF(INDEX(C_Pavement!$G$5:$G$204,$AQ9)="-","",INDEX(C_Pavement!$G$5:$G$204,$AQ9)),IF($AS9="","",INDEX(E_Rules!$F$5:$F$9,$AS9)))) | AX9: =IF($AQ9="","",IF(INDEX(C_Pavement!$H$5:$H$204,$AQ9)<>"",IF(INDEX(C_Pavement!$H$5:$H$204,$AQ9)="-","",INDEX(C_Pavement!$H$5:$H$204,$AQ9)),IF($AS9="","",INDEX(E_Rules!$G$5:$G$9,$AS9)))) | AY9: =IF($AQ9="","",IF(INDEX(C_Pavement!$I$5:$I$204,$AQ9)<>"",IF(INDEX(C_Pavement!$I$5:$I$204,$AQ9)="-","",INDEX(C_Pavement!$I$5:$I$204,$AQ9)),IF($AS9="","",INDEX(E_Rules!$H$5:$H$9,$AS9))))
A10: 5 | B10: 200 | C10: 0+200 | D10: =IFERROR(LOOKUP(2,1/((A_Corridor!$A$5:$A$204<>"")*(A_Corridor!$A$5:$A$204<=$B10)*(A_Corridor!$B$5:$B$204>$B10)*(A_Corridor!$C$5:$C$204<>"")),IF(UPPER(A_Corridor!$C$5:$C$204)="Y",1,"")),"") | E10: =IFERROR(LOOKUP(2,1/((A_Corridor!$A$5:$A$204<>"")*(A_Corridor!$A$5:$A$204<=$B10)*(A_Corridor!$B$5:$B$204>$B10)*(A_Corridor!$D$5:$D$204<>"")),IF(A_Corridor!$D$5:$D$204="-","",UPPER(A_Corridor!$D$5:$D$204))),"") | F10: =IFERROR(LOOKUP(2,1/((A_Corridor!$A$5:$A$204<>"")*(A_Corridor!$A$5:$A$204<=$B10)*(A_Corridor!$B$5:$B$204>$B10)*(A_Corridor!$E$5:$E$204<>"")),IF(A_Corridor!$E$5:$E$204="-","",1)),"") | G10: =IFERROR(LOOKUP(2,1/((A_Corridor!$A$5:$A$204<>"")*(A_Corridor!$A$5:$A$204<=$B10)*(A_Corridor!$B$5:$B$204>$B10)*(A_Corridor!$E$5:$E$204<>"")),IF(A_Corridor!$E$5:$E$204="-","",A_Corridor!$E$5:$E$204)),"") | H10: =IFERROR(LOOKUP(2,1/((D_Points!$A$5:$A$204<>"")*(D_Points!$A$5:$A$204>=$B10)*(D_Points!$A$5:$A$204<$B10+P_Interval)*(UPPER(TRIM(D_Points!$B$5:$B$204))="GULLY")*(D_Points!$H$5:$H$204<>"")),D_Points!$H$5:$H$204),"") | I10: =IFERROR(LOOKUP(2,1/((A_Corridor!$A$5:$A$204<>"")*(A_Corridor!$A$5:$A$204<=$B10)*(A_Corridor!$B$5:$B$204>$B10)*(A_Corridor!$F$5:$F$204<>"")),IF(A_Corridor!$F$5:$F$204="-","",1)),"") | J10: =IFERROR(LOOKUP(2,1/((A_Corridor!$A$5:$A$204<>"")*(A_Corridor!$A$5:$A$204<=$B10)*(A_Corridor!$B$5:$B$204>$B10)*(A_Corridor!$F$5:$F$204<>"")),IF(A_Corridor!$F$5:$F$204="-","",A_Corridor!$F$5:$F$204)),"") | K10: =IFERROR(LOOKUP(2,1/((A_Corridor!$A$5:$A$204<>"")*(A_Corridor!$A$5:$A$204<=$B10)*(A_Corridor!$B$5:$B$204>$B10)*(A_Corridor!$G$5:$G$204<>"")),IF(A_Corridor!$G$5:$G$204="-","",A_Corridor!$G$5:$G$204)),"") | L10: =IFERROR(LOOKUP(2,1/((A_Corridor!$A$5:$A$204<>"")*(A_Corridor!$A$5:$A$204<=$B10)*(A_Corridor!$B$5:$B$204>$B10)*(A_Corridor!$H$5:$H$204<>"")),IF(A_Corridor!$H$5:$H$204="-","",1)),"") | M10: =IFERROR(LOOKUP(2,1/((A_Corridor!$A$5:$A$204<>"")*(A_Corridor!$A$5:$A$204<=$B10)*(A_Corridor!$B$5:$B$204>$B10)*(A_Corridor!$H$5:$H$204<>"")),IF(A_Corridor!$H$5:$H$204="-","",A_Corridor!$H$5:$H$204)),"") | N10: =IFERROR(LOOKUP(2,1/((A_Corridor!$A$5:$A$204<>"")*(A_Corridor!$A$5:$A$204<=$B10)*(A_Corridor!$B$5:$B$204>$B10)*(A_Corridor!$I$5:$I$204<>"")),IF(A_Corridor!$I$5:$I$204="-","",A_Corridor!$I$5:$I$204)),"") | O10: =IFERROR(LOOKUP(2,1/((D_Points!$A$5:$A$204<>"")*(D_Points!$A$5:$A$204>=$B10)*(D_Points!$A$5:$A$204<$B10+P_Interval)*(UPPER(TRIM(D_Points!$B$5:$B$204))="PITCHING")*(D_Points!$H$5:$H$204<>"")),D_Points!$H$5:$H$204),"") | P10: =IFERROR(LOOKUP(2,1/((B_Drainage!$A$5:$A$204<>"")*(B_Drainage!$A$5:$A$204<=$B10)*(B_Drainage!$B$5:$B$204>$B10)*(B_Drainage!$C$5:$C$204<>"")),IF(B_Drainage!$C$5:$C$204="-","",UPPER(B_Drainage!$C$5:$C$204))),"") | Q10: =IFERROR(LOOKUP(2,1/((B_Drainage!$A$5:$A$204<>"")*(B_Drainage!$A$5:$A$204<=$B10)*(B_Drainage!$B$5:$B$204>$B10)*(B_Drainage!$D$5:$D$204<>"")),IF(B_Drainage!$D$5:$D$204="-","",UPPER(B_Drainage!$D$5:$D$204))),"") | R10: =IFERROR(LOOKUP(2,1/((D_Points!$A$5:$A$204<>"")*(D_Points!$A$5:$A$204>=$B10)*(D_Points!$A$5:$A$204<$B10+P_Interval)*(RIGHT(UPPER(TRIM(D_Points!$B$5:$B$204)),8)="_CULVERT")),IF(LEFT(UPPER(TRIM(D_Points!$B$5:$B$204)),2)="EX",1,IF(LEFT(UPPER(TRIM(D_Points!$B$5:$B$204)),2)="PR",2,3))),"") | S10: =IFERROR(LOOKUP(2,1/((D_Points!$A$5:$A$204<>"")*(D_Points!$A$5:$A$204>=$B10)*(D_Points!$A$5:$A$204<$B10+P_Interval)*(RIGHT(UPPER(TRIM(D_Points!$B$5:$B$204)),7)="_BRIDGE")),IF(LEFT(UPPER(TRIM(D_Points!$B$5:$B$204)),2)="EX",1,IF(LEFT(UPPER(TRIM(D_Points!$B$5:$B$204)),2)="PR",2,2))),"") | T10: =IFERROR(LOOKUP(2,1/((B_Drainage!$A$5:$A$204<>"")*(B_Drainage!$A$5:$A$204<=$B10)*(B_Drainage!$B$5:$B$204>$B10)*(B_Drainage!$E$5:$E$204<>"")),IF(B_Drainage!$E$5:$E$204="-","",1)),"") | U10: =IFERROR(LOOKUP(2,1/((B_Drainage!$A$5:$A$204<>"")*(B_Drainage!$A$5:$A$204<=$B10)*(B_Drainage!$B$5:$B$204>$B10)*(B_Drainage!$E$5:$E$204<>"")),IF(B_Drainage!$E$5:$E$204="-","",B_Drainage!$E$5:$E$204)),"") | V10: =IFERROR(LOOKUP(2,1/((B_Drainage!$A$5:$A$204<>"")*(B_Drainage!$A$5:$A$204<=$B10)*(B_Drainage!$B$5:$B$204>$B10)*(B_Drainage!$F$5:$F$204<>"")),IF(B_Drainage!$F$5:$F$204="-","",1)),"") | W10: =IFERROR(LOOKUP(2,1/((B_Drainage!$A$5:$A$204<>"")*(B_Drainage!$A$5:$A$204<=$B10)*(B_Drainage!$B$5:$B$204>$B10)*(B_Drainage!$F$5:$F$204<>"")),IF(B_Drainage!$F$5:$F$204="-","",B_Drainage!$F$5:$F$204)),"") | X10: =IFERROR(LOOKUP(2,1/((B_Drainage!$A$5:$A$204<>"")*(B_Drainage!$A$5:$A$204<=$B10)*(B_Drainage!$B$5:$B$204>$B10)*(B_Drainage!$G$5:$G$204<>"")),IF(UPPER(B_Drainage!$G$5:$G$204)="Y",1,"")),"") | Y10: =IFERROR(LOOKUP(2,1/((B_Drainage!$A$5:$A$204<>"")*(B_Drainage!$A$5:$A$204<=$B10)*(B_Drainage!$B$5:$B$204>$B10)*(B_Drainage!$H$5:$H$204<>"")),IF(UPPER(B_Drainage!$H$5:$H$204)="Y",1,"")),"") | Z10: =IFERROR(LOOKUP(2,1/((B_Drainage!$A$5:$A$204<>"")*(B_Drainage!$A$5:$A$204<=$B10)*(B_Drainage!$B$5:$B$204>$B10)*(B_Drainage!$I$5:$I$204<>"")),IF(UPPER(B_Drainage!$I$5:$I$204)="Y",1,"")),"") | AA10: =IFERROR(LOOKUP(2,1/((B_Drainage!$A$5:$A$204<>"")*(B_Drainage!$A$5:$A$204<=$B10)*(B_Drainage!$B$5:$B$204>$B10)*(B_Drainage!$J$5:$J$204<>"")),IF(UPPER(B_Drainage!$J$5:$J$204)="Y",1,"")),"") | AB10: =IFERROR(LOOKUP(2,1/((B_Drainage!$A$5:$A$204<>"")*(B_Drainage!$A$5:$A$204<=$B10)*(B_Drainage!$B$5:$B$204>$B10)*(B_Drainage!$K$5:$K$204<>"")),IF(B_Drainage!$K$5:$K$204="-","",B_Drainage!$K$5:$K$204)),"") | AC10: =IFERROR(LOOKUP(2,1/((B_Drainage!$A$5:$A$204<>"")*(B_Drainage!$A$5:$A$204<=$B10)*(B_Drainage!$B$5:$B$204>$B10)*(B_Drainage!$L$5:$L$204<>"")),IF(B_Drainage!$L$5:$L$204="-","",B_Drainage!$L$5:$L$204)),"") | AD10: =IFERROR(LOOKUP(2,1/((D_Points!$A$5:$A$204<>"")*(D_Points!$A$5:$A$204>=$B10)*(D_Points!$A$5:$A$204<$B10+P_Interval)*(UPPER(TRIM(D_Points!$B$5:$B$204))="TURNOUT_L")*(D_Points!$H$5:$H$204<>"")),D_Points!$H$5:$H$204),"") | AE10: =IFERROR(LOOKUP(2,1/((D_Points!$A$5:$A$204<>"")*(D_Points!$A$5:$A$204>=$B10)*(D_Points!$A$5:$A$204<$B10+P_Interval)*(UPPER(TRIM(D_Points!$B$5:$B$204))="TURNOUT_R")*(D_Points!$H$5:$H$204<>"")),D_Points!$H$5:$H$204),"") | AF10: =IFERROR(LOOKUP(2,1/((B_Drainage!$A$5:$A$204<>"")*(B_Drainage!$A$5:$A$204<=$B10)*(B_Drainage!$B$5:$B$204>$B10)*(B_Drainage!$M$5:$M$204<>"")),IF(UPPER(B_Drainage!$M$5:$M$204)="Y",1,"")),"") | AG10: =IFERROR(LOOKUP(2,1/((B_Drainage!$A$5:$A$204<>"")*(B_Drainage!$A$5:$A$204<=$B10)*(B_Drainage!$B$5:$B$204>$B10)*(B_Drainage!$N$5:$N$204<>"")),IF(UPPER(B_Drainage!$N$5:$N$204)="Y",1,"")),"") | AH10: =IF($AT10="BLADE",1,"") | AI10: =IF($AT10="RESHAPE",1,"") | AJ10: =IF($AT10="SCARIFY",1,"") | AK10: =$AU10 | AL10: =$AV10 | AM10: =IF(OR(UPPER($AW10)="Y",$AW10=1),1,"") | AN10: =IF(OR(UPPER($AX10)="Y",$AX10=1),1,"") | AO10: =IF(OR(UPPER($AY10)="Y",$AY10=1),1,"") | AQ10: =IFERROR(LOOKUP(2,1/((C_Pavement!$A$5:$A$204<>"")*(C_Pavement!$A$5:$A$204<=$B10)*(C_Pavement!$B$5:$B$204>$B10)*(C_Pavement!$C$5:$C$204<>"")),ROW(C_Pavement!$C$5:$C$204)-4),"") | AR10: =IF($AQ10="","",UPPER(TRIM(INDEX(C_Pavement!$C$5:$C$204,$AQ10)))) | AS10: =IF($AR10="","",IFERROR(MATCH($AR10,E_Rules!$A$5:$A$9,0),"")) | AT10: =IF($AQ10="","",IF(INDEX(C_Pavement!$D$5:$D$204,$AQ10)<>"",UPPER(TRIM(INDEX(C_Pavement!$D$5:$D$204,$AQ10))),IF($AS10="","",INDEX(E_Rules!$C$5:$C$9,$AS10)))) | AU10: =IF($AQ10="","",IF(INDEX(C_Pavement!$E$5:$E$204,$AQ10)<>"",IF(INDEX(C_Pavement!$E$5:$E$204,$AQ10)="-","",INDEX(C_Pavement!$E$5:$E$204,$AQ10)),IF($AS10="","",INDEX(E_Rules!$D$5:$D$9,$AS10)))) | AV10: =IF($AQ10="","",IF(INDEX(C_Pavement!$F$5:$F$204,$AQ10)<>"",IF(INDEX(C_Pavement!$F$5:$F$204,$AQ10)="-","",INDEX(C_Pavement!$F$5:$F$204,$AQ10)),IF($AS10="","",INDEX(E_Rules!$E$5:$E$9,$AS10)))) | AW10: =IF($AQ10="","",IF(INDEX(C_Pavement!$G$5:$G$204,$AQ10)<>"",IF(INDEX(C_Pavement!$G$5:$G$204,$AQ10)="-","",INDEX(C_Pavement!$G$5:$G$204,$AQ10)),IF($AS10="","",INDEX(E_Rules!$F$5:$F$9,$AS10)))) | AX10: =IF($AQ10="","",IF(INDEX(C_Pavement!$H$5:$H$204,$AQ10)<>"",IF(INDEX(C_Pavement!$H$5:$H$204,$AQ10)="-","",INDEX(C_Pavement!$H$5:$H$204,$AQ10)),IF($AS10="","",INDEX(E_Rules!$G$5:$G$9,$AS10)))) | AY10: =IF($AQ10="","",IF(INDEX(C_Pavement!$I$5:$I$204,$AQ10)<>"",IF(INDEX(C_Pavement!$I$5:$I$204,$AQ10)="-","",INDEX(C_Pavement!$I$5:$I$204,$AQ10)),IF($AS10="","",INDEX(E_Rules!$H$5:$H$9,$AS10))))
A11: 6 | B11: 250 | C11: 0+250 | D11: =IFERROR(LOOKUP(2,1/((A_Corridor!$A$5:$A$204<>"")*(A_Corridor!$A$5:$A$204<=$B11)*(A_Corridor!$B$5:$B$204>$B11)*(A_Corridor!$C$5:$C$204<>"")),IF(UPPER(A_Corridor!$C$5:$C$204)="Y",1,"")),"") | E11: =IFERROR(LOOKUP(2,1/((A_Corridor!$A$5:$A$204<>"")*(A_Corridor!$A$5:$A$204<=$B11)*(A_Corridor!$B$5:$B$204>$B11)*(A_Corridor!$D$5:$D$204<>"")),IF(A_Corridor!$D$5:$D$204="-","",UPPER(A_Corridor!$D$5:$D$204))),"") | F11: =IFERROR(LOOKUP(2,1/((A_Corridor!$A$5:$A$204<>"")*(A_Corridor!$A$5:$A$204<=$B11)*(A_Corridor!$B$5:$B$204>$B11)*(A_Corridor!$E$5:$E$204<>"")),IF(A_Corridor!$E$5:$E$204="-","",1)),"") | G11: =IFERROR(LOOKUP(2,1/((A_Corridor!$A$5:$A$204<>"")*(A_Corridor!$A$5:$A$204<=$B11)*(A_Corridor!$B$5:$B$204>$B11)*(A_Corridor!$E$5:$E$204<>"")),IF(A_Corridor!$E$5:$E$204="-","",A_Corridor!$E$5:$E$204)),"") | H11: =IFERROR(LOOKUP(2,1/((D_Points!$A$5:$A$204<>"")*(D_Points!$A$5:$A$204>=$B11)*(D_Points!$A$5:$A$204<$B11+P_Interval)*(UPPER(TRIM(D_Points!$B$5:$B$204))="GULLY")*(D_Points!$H$5:$H$204<>"")),D_Points!$H$5:$H$204),"") | I11: =IFERROR(LOOKUP(2,1/((A_Corridor!$A$5:$A$204<>"")*(A_Corridor!$A$5:$A$204<=$B11)*(A_Corridor!$B$5:$B$204>$B11)*(A_Corridor!$F$5:$F$204<>"")),IF(A_Corridor!$F$5:$F$204="-","",1)),"") | J11: =IFERROR(LOOKUP(2,1/((A_Corridor!$A$5:$A$204<>"")*(A_Corridor!$A$5:$A$204<=$B11)*(A_Corridor!$B$5:$B$204>$B11)*(A_Corridor!$F$5:$F$204<>"")),IF(A_Corridor!$F$5:$F$204="-","",A_Corridor!$F$5:$F$204)),"") | K11: =IFERROR(LOOKUP(2,1/((A_Corridor!$A$5:$A$204<>"")*(A_Corridor!$A$5:$A$204<=$B11)*(A_Corridor!$B$5:$B$204>$B11)*(A_Corridor!$G$5:$G$204<>"")),IF(A_Corridor!$G$5:$G$204="-","",A_Corridor!$G$5:$G$204)),"") | L11: =IFERROR(LOOKUP(2,1/((A_Corridor!$A$5:$A$204<>"")*(A_Corridor!$A$5:$A$204<=$B11)*(A_Corridor!$B$5:$B$204>$B11)*(A_Corridor!$H$5:$H$204<>"")),IF(A_Corridor!$H$5:$H$204="-","",1)),"") | M11: =IFERROR(LOOKUP(2,1/((A_Corridor!$A$5:$A$204<>"")*(A_Corridor!$A$5:$A$204<=$B11)*(A_Corridor!$B$5:$B$204>$B11)*(A_Corridor!$H$5:$H$204<>"")),IF(A_Corridor!$H$5:$H$204="-","",A_Corridor!$H$5:$H$204)),"") | N11: =IFERROR(LOOKUP(2,1/((A_Corridor!$A$5:$A$204<>"")*(A_Corridor!$A$5:$A$204<=$B11)*(A_Corridor!$B$5:$B$204>$B11)*(A_Corridor!$I$5:$I$204<>"")),IF(A_Corridor!$I$5:$I$204="-","",A_Corridor!$I$5:$I$204)),"") | O11: =IFERROR(LOOKUP(2,1/((D_Points!$A$5:$A$204<>"")*(D_Points!$A$5:$A$204>=$B11)*(D_Points!$A$5:$A$204<$B11+P_Interval)*(UPPER(TRIM(D_Points!$B$5:$B$204))="PITCHING")*(D_Points!$H$5:$H$204<>"")),D_Points!$H$5:$H$204),"") | P11: =IFERROR(LOOKUP(2,1/((B_Drainage!$A$5:$A$204<>"")*(B_Drainage!$A$5:$A$204<=$B11)*(B_Drainage!$B$5:$B$204>$B11)*(B_Drainage!$C$5:$C$204<>"")),IF(B_Drainage!$C$5:$C$204="-","",UPPER(B_Drainage!$C$5:$C$204))),"") | Q11: =IFERROR(LOOKUP(2,1/((B_Drainage!$A$5:$A$204<>"")*(B_Drainage!$A$5:$A$204<=$B11)*(B_Drainage!$B$5:$B$204>$B11)*(B_Drainage!$D$5:$D$204<>"")),IF(B_Drainage!$D$5:$D$204="-","",UPPER(B_Drainage!$D$5:$D$204))),"") | R11: =IFERROR(LOOKUP(2,1/((D_Points!$A$5:$A$204<>"")*(D_Points!$A$5:$A$204>=$B11)*(D_Points!$A$5:$A$204<$B11+P_Interval)*(RIGHT(UPPER(TRIM(D_Points!$B$5:$B$204)),8)="_CULVERT")),IF(LEFT(UPPER(TRIM(D_Points!$B$5:$B$204)),2)="EX",1,IF(LEFT(UPPER(TRIM(D_Points!$B$5:$B$204)),2)="PR",2,3))),"") | S11: =IFERROR(LOOKUP(2,1/((D_Points!$A$5:$A$204<>"")*(D_Points!$A$5:$A$204>=$B11)*(D_Points!$A$5:$A$204<$B11+P_Interval)*(RIGHT(UPPER(TRIM(D_Points!$B$5:$B$204)),7)="_BRIDGE")),IF(LEFT(UPPER(TRIM(D_Points!$B$5:$B$204)),2)="EX",1,IF(LEFT(UPPER(TRIM(D_Points!$B$5:$B$204)),2)="PR",2,2))),"") | T11: =IFERROR(LOOKUP(2,1/((B_Drainage!$A$5:$A$204<>"")*(B_Drainage!$A$5:$A$204<=$B11)*(B_Drainage!$B$5:$B$204>$B11)*(B_Drainage!$E$5:$E$204<>"")),IF(B_Drainage!$E$5:$E$204="-","",1)),"") | U11: =IFERROR(LOOKUP(2,1/((B_Drainage!$A$5:$A$204<>"")*(B_Drainage!$A$5:$A$204<=$B11)*(B_Drainage!$B$5:$B$204>$B11)*(B_Drainage!$E$5:$E$204<>"")),IF(B_Drainage!$E$5:$E$204="-","",B_Drainage!$E$5:$E$204)),"") | V11: =IFERROR(LOOKUP(2,1/((B_Drainage!$A$5:$A$204<>"")*(B_Drainage!$A$5:$A$204<=$B11)*(B_Drainage!$B$5:$B$204>$B11)*(B_Drainage!$F$5:$F$204<>"")),IF(B_Drainage!$F$5:$F$204="-","",1)),"") | W11: =IFERROR(LOOKUP(2,1/((B_Drainage!$A$5:$A$204<>"")*(B_Drainage!$A$5:$A$204<=$B11)*(B_Drainage!$B$5:$B$204>$B11)*(B_Drainage!$F$5:$F$204<>"")),IF(B_Drainage!$F$5:$F$204="-","",B_Drainage!$F$5:$F$204)),"") | X11: =IFERROR(LOOKUP(2,1/((B_Drainage!$A$5:$A$204<>"")*(B_Drainage!$A$5:$A$204<=$B11)*(B_Drainage!$B$5:$B$204>$B11)*(B_Drainage!$G$5:$G$204<>"")),IF(UPPER(B_Drainage!$G$5:$G$204)="Y",1,"")),"") | Y11: =IFERROR(LOOKUP(2,1/((B_Drainage!$A$5:$A$204<>"")*(B_Drainage!$A$5:$A$204<=$B11)*(B_Drainage!$B$5:$B$204>$B11)*(B_Drainage!$H$5:$H$204<>"")),IF(UPPER(B_Drainage!$H$5:$H$204)="Y",1,"")),"") | Z11: =IFERROR(LOOKUP(2,1/((B_Drainage!$A$5:$A$204<>"")*(B_Drainage!$A$5:$A$204<=$B11)*(B_Drainage!$B$5:$B$204>$B11)*(B_Drainage!$I$5:$I$204<>"")),IF(UPPER(B_Drainage!$I$5:$I$204)="Y",1,"")),"") | AA11: =IFERROR(LOOKUP(2,1/((B_Drainage!$A$5:$A$204<>"")*(B_Drainage!$A$5:$A$204<=$B11)*(B_Drainage!$B$5:$B$204>$B11)*(B_Drainage!$J$5:$J$204<>"")),IF(UPPER(B_Drainage!$J$5:$J$204)="Y",1,"")),"") | AB11: =IFERROR(LOOKUP(2,1/((B_Drainage!$A$5:$A$204<>"")*(B_Drainage!$A$5:$A$204<=$B11)*(B_Drainage!$B$5:$B$204>$B11)*(B_Drainage!$K$5:$K$204<>"")),IF(B_Drainage!$K$5:$K$204="-","",B_Drainage!$K$5:$K$204)),"") | AC11: =IFERROR(LOOKUP(2,1/((B_Drainage!$A$5:$A$204<>"")*(B_Drainage!$A$5:$A$204<=$B11)*(B_Drainage!$B$5:$B$204>$B11)*(B_Drainage!$L$5:$L$204<>"")),IF(B_Drainage!$L$5:$L$204="-","",B_Drainage!$L$5:$L$204)),"") | AD11: =IFERROR(LOOKUP(2,1/((D_Points!$A$5:$A$204<>"")*(D_Points!$A$5:$A$204>=$B11)*(D_Points!$A$5:$A$204<$B11+P_Interval)*(UPPER(TRIM(D_Points!$B$5:$B$204))="TURNOUT_L")*(D_Points!$H$5:$H$204<>"")),D_Points!$H$5:$H$204),"") | AE11: =IFERROR(LOOKUP(2,1/((D_Points!$A$5:$A$204<>"")*(D_Points!$A$5:$A$204>=$B11)*(D_Points!$A$5:$A$204<$B11+P_Interval)*(UPPER(TRIM(D_Points!$B$5:$B$204))="TURNOUT_R")*(D_Points!$H$5:$H$204<>"")),D_Points!$H$5:$H$204),"") | AF11: =IFERROR(LOOKUP(2,1/((B_Drainage!$A$5:$A$204<>"")*(B_Drainage!$A$5:$A$204<=$B11)*(B_Drainage!$B$5:$B$204>$B11)*(B_Drainage!$M$5:$M$204<>"")),IF(UPPER(B_Drainage!$M$5:$M$204)="Y",1,"")),"") | AG11: =IFERROR(LOOKUP(2,1/((B_Drainage!$A$5:$A$204<>"")*(B_Drainage!$A$5:$A$204<=$B11)*(B_Drainage!$B$5:$B$204>$B11)*(B_Drainage!$N$5:$N$204<>"")),IF(UPPER(B_Drainage!$N$5:$N$204)="Y",1,"")),"") | AH11: =IF($AT11="BLADE",1,"") | AI11: =IF($AT11="RESHAPE",1,"") | AJ11: =IF($AT11="SCARIFY",1,"") | AK11: =$AU11 | AL11: =$AV11 | AM11: =IF(OR(UPPER($AW11)="Y",$AW11=1),1,"") | AN11: =IF(OR(UPPER($AX11)="Y",$AX11=1),1,"") | AO11: =IF(OR(UPPER($AY11)="Y",$AY11=1),1,"") | AQ11: =IFERROR(LOOKUP(2,1/((C_Pavement!$A$5:$A$204<>"")*(C_Pavement!$A$5:$A$204<=$B11)*(C_Pavement!$B$5:$B$204>$B11)*(C_Pavement!$C$5:$C$204<>"")),ROW(C_Pavement!$C$5:$C$204)-4),"") | AR11: =IF($AQ11="","",UPPER(TRIM(INDEX(C_Pavement!$C$5:$C$204,$AQ11)))) | AS11: =IF($AR11="","",IFERROR(MATCH($AR11,E_Rules!$A$5:$A$9,0),"")) | AT11: =IF($AQ11="","",IF(INDEX(C_Pavement!$D$5:$D$204,$AQ11)<>"",UPPER(TRIM(INDEX(C_Pavement!$D$5:$D$204,$AQ11))),IF($AS11="","",INDEX(E_Rules!$C$5:$C$9,$AS11)))) | AU11: =IF($AQ11="","",IF(INDEX(C_Pavement!$E$5:$E$204,$AQ11)<>"",IF(INDEX(C_Pavement!$E$5:$E$204,$AQ11)="-","",INDEX(C_Pavement!$E$5:$E$204,$AQ11)),IF($AS11="","",INDEX(E_Rules!$D$5:$D$9,$AS11)))) | AV11: =IF($AQ11="","",IF(INDEX(C_Pavement!$F$5:$F$204,$AQ11)<>"",IF(INDEX(C_Pavement!$F$5:$F$204,$AQ11)="-","",INDEX(C_Pavement!$F$5:$F$204,$AQ11)),IF($AS11="","",INDEX(E_Rules!$E$5:$E$9,$AS11)))) | AW11: =IF($AQ11="","",IF(INDEX(C_Pavement!$G$5:$G$204,$AQ11)<>"",IF(INDEX(C_Pavement!$G$5:$G$204,$AQ11)="-","",INDEX(C_Pavement!$G$5:$G$204,$AQ11)),IF($AS11="","",INDEX(E_Rules!$F$5:$F$9,$AS11)))) | AX11: =IF($AQ11="","",IF(INDEX(C_Pavement!$H$5:$H$204,$AQ11)<>"",IF(INDEX(C_Pavement!$H$5:$H$204,$AQ11)="-","",INDEX(C_Pavement!$H$5:$H$204,$AQ11)),IF($AS11="","",INDEX(E_Rules!$G$5:$G$9,$AS11)))) | AY11: =IF($AQ11="","",IF(INDEX(C_Pavement!$I$5:$I$204,$AQ11)<>"",IF(INDEX(C_Pavement!$I$5:$I$204,$AQ11)="-","",INDEX(C_Pavement!$I$5:$I$204,$AQ11)),IF($AS11="","",INDEX(E_Rules!$H$5:$H$9,$AS11))))
A12: 7 | B12: 300 | C12: 0+300 | D12: =IFERROR(LOOKUP(2,1/((A_Corridor!$A$5:$A$204<>"")*(A_Corridor!$A$5:$A$204<=$B12)*(A_Corridor!$B$5:$B$204>$B12)*(A_Corridor!$C$5:$C$204<>"")),IF(UPPER(A_Corridor!$C$5:$C$204)="Y",1,"")),"") | E12: =IFERROR(LOOKUP(2,1/((A_Corridor!$A$5:$A$204<>"")*(A_Corridor!$A$5:$A$204<=$B12)*(A_Corridor!$B$5:$B$204>$B12)*(A_Corridor!$D$5:$D$204<>"")),IF(A_Corridor!$D$5:$D$204="-","",UPPER(A_Corridor!$D$5:$D$204))),"") | F12: =IFERROR(LOOKUP(2,1/((A_Corridor!$A$5:$A$204<>"")*(A_Corridor!$A$5:$A$204<=$B12)*(A_Corridor!$B$5:$B$204>$B12)*(A_Corridor!$E$5:$E$204<>"")),IF(A_Corridor!$E$5:$E$204="-","",1)),"") | G12: =IFERROR(LOOKUP(2,1/((A_Corridor!$A$5:$A$204<>"")*(A_Corridor!$A$5:$A$204<=$B12)*(A_Corridor!$B$5:$B$204>$B12)*(A_Corridor!$E$5:$E$204<>"")),IF(A_Corridor!$E$5:$E$204="-","",A_Corridor!$E$5:$E$204)),"") | H12: =IFERROR(LOOKUP(2,1/((D_Points!$A$5:$A$204<>"")*(D_Points!$A$5:$A$204>=$B12)*(D_Points!$A$5:$A$204<$B12+P_Interval)*(UPPER(TRIM(D_Points!$B$5:$B$204))="GULLY")*(D_Points!$H$5:$H$204<>"")),D_Points!$H$5:$H$204),"") | I12: =IFERROR(LOOKUP(2,1/((A_Corridor!$A$5:$A$204<>"")*(A_Corridor!$A$5:$A$204<=$B12)*(A_Corridor!$B$5:$B$204>$B12)*(A_Corridor!$F$5:$F$204<>"")),IF(A_Corridor!$F$5:$F$204="-","",1)),"") | J12: =IFERROR(LOOKUP(2,1/((A_Corridor!$A$5:$A$204<>"")*(A_Corridor!$A$5:$A$204<=$B12)*(A_Corridor!$B$5:$B$204>$B12)*(A_Corridor!$F$5:$F$204<>"")),IF(A_Corridor!$F$5:$F$204="-","",A_Corridor!$F$5:$F$204)),"") | K12: =IFERROR(LOOKUP(2,1/((A_Corridor!$A$5:$A$204<>"")*(A_Corridor!$A$5:$A$204<=$B12)*(A_Corridor!$B$5:$B$204>$B12)*(A_Corridor!$G$5:$G$204<>"")),IF(A_Corridor!$G$5:$G$204="-","",A_Corridor!$G$5:$G$204)),"") | L12: =IFERROR(LOOKUP(2,1/((A_Corridor!$A$5:$A$204<>"")*(A_Corridor!$A$5:$A$204<=$B12)*(A_Corridor!$B$5:$B$204>$B12)*(A_Corridor!$H$5:$H$204<>"")),IF(A_Corridor!$H$5:$H$204="-","",1)),"") | M12: =IFERROR(LOOKUP(2,1/((A_Corridor!$A$5:$A$204<>"")*(A_Corridor!$A$5:$A$204<=$B12)*(A_Corridor!$B$5:$B$204>$B12)*(A_Corridor!$H$5:$H$204<>"")),IF(A_Corridor!$H$5:$H$204="-","",A_Corridor!$H$5:$H$204)),"") | N12: =IFERROR(LOOKUP(2,1/((A_Corridor!$A$5:$A$204<>"")*(A_Corridor!$A$5:$A$204<=$B12)*(A_Corridor!$B$5:$B$204>$B12)*(A_Corridor!$I$5:$I$204<>"")),IF(A_Corridor!$I$5:$I$204="-","",A_Corridor!$I$5:$I$204)),"") | O12: =IFERROR(LOOKUP(2,1/((D_Points!$A$5:$A$204<>"")*(D_Points!$A$5:$A$204>=$B12)*(D_Points!$A$5:$A$204<$B12+P_Interval)*(UPPER(TRIM(D_Points!$B$5:$B$204))="PITCHING")*(D_Points!$H$5:$H$204<>"")),D_Points!$H$5:$H$204),"") | P12: =IFERROR(LOOKUP(2,1/((B_Drainage!$A$5:$A$204<>"")*(B_Drainage!$A$5:$A$204<=$B12)*(B_Drainage!$B$5:$B$204>$B12)*(B_Drainage!$C$5:$C$204<>"")),IF(B_Drainage!$C$5:$C$204="-","",UPPER(B_Drainage!$C$5:$C$204))),"") | Q12: =IFERROR(LOOKUP(2,1/((B_Drainage!$A$5:$A$204<>"")*(B_Drainage!$A$5:$A$204<=$B12)*(B_Drainage!$B$5:$B$204>$B12)*(B_Drainage!$D$5:$D$204<>"")),IF(B_Drainage!$D$5:$D$204="-","",UPPER(B_Drainage!$D$5:$D$204))),"") | R12: =IFERROR(LOOKUP(2,1/((D_Points!$A$5:$A$204<>"")*(D_Points!$A$5:$A$204>=$B12)*(D_Points!$A$5:$A$204<$B12+P_Interval)*(RIGHT(UPPER(TRIM(D_Points!$B$5:$B$204)),8)="_CULVERT")),IF(LEFT(UPPER(TRIM(D_Points!$B$5:$B$204)),2)="EX",1,IF(LEFT(UPPER(TRIM(D_Points!$B$5:$B$204)),2)="PR",2,3))),"") | S12: =IFERROR(LOOKUP(2,1/((D_Points!$A$5:$A$204<>"")*(D_Points!$A$5:$A$204>=$B12)*(D_Points!$A$5:$A$204<$B12+P_Interval)*(RIGHT(UPPER(TRIM(D_Points!$B$5:$B$204)),7)="_BRIDGE")),IF(LEFT(UPPER(TRIM(D_Points!$B$5:$B$204)),2)="EX",1,IF(LEFT(UPPER(TRIM(D_Points!$B$5:$B$204)),2)="PR",2,2))),"") | T12: =IFERROR(LOOKUP(2,1/((B_Drainage!$A$5:$A$204<>"")*(B_Drainage!$A$5:$A$204<=$B12)*(B_Drainage!$B$5:$B$204>$B12)*(B_Drainage!$E$5:$E$204<>"")),IF(B_Drainage!$E$5:$E$204="-","",1)),"") | U12: =IFERROR(LOOKUP(2,1/((B_Drainage!$A$5:$A$204<>"")*(B_Drainage!$A$5:$A$204<=$B12)*(B_Drainage!$B$5:$B$204>$B12)*(B_Drainage!$E$5:$E$204<>"")),IF(B_Drainage!$E$5:$E$204="-","",B_Drainage!$E$5:$E$204)),"") | V12: =IFERROR(LOOKUP(2,1/((B_Drainage!$A$5:$A$204<>"")*(B_Drainage!$A$5:$A$204<=$B12)*(B_Drainage!$B$5:$B$204>$B12)*(B_Drainage!$F$5:$F$204<>"")),IF(B_Drainage!$F$5:$F$204="-","",1)),"") | W12: =IFERROR(LOOKUP(2,1/((B_Drainage!$A$5:$A$204<>"")*(B_Drainage!$A$5:$A$204<=$B12)*(B_Drainage!$B$5:$B$204>$B12)*(B_Drainage!$F$5:$F$204<>"")),IF(B_Drainage!$F$5:$F$204="-","",B_Drainage!$F$5:$F$204)),"") | X12: =IFERROR(LOOKUP(2,1/((B_Drainage!$A$5:$A$204<>"")*(B_Drainage!$A$5:$A$204<=$B12)*(B_Drainage!$B$5:$B$204>$B12)*(B_Drainage!$G$5:$G$204<>"")),IF(UPPER(B_Drainage!$G$5:$G$204)="Y",1,"")),"") | Y12: =IFERROR(LOOKUP(2,1/((B_Drainage!$A$5:$A$204<>"")*(B_Drainage!$A$5:$A$204<=$B12)*(B_Drainage!$B$5:$B$204>$B12)*(B_Drainage!$H$5:$H$204<>"")),IF(UPPER(B_Drainage!$H$5:$H$204)="Y",1,"")),"") | Z12: =IFERROR(LOOKUP(2,1/((B_Drainage!$A$5:$A$204<>"")*(B_Drainage!$A$5:$A$204<=$B12)*(B_Drainage!$B$5:$B$204>$B12)*(B_Drainage!$I$5:$I$204<>"")),IF(UPPER(B_Drainage!$I$5:$I$204)="Y",1,"")),"") | AA12: =IFERROR(LOOKUP(2,1/((B_Drainage!$A$5:$A$204<>"")*(B_Drainage!$A$5:$A$204<=$B12)*(B_Drainage!$B$5:$B$204>$B12)*(B_Drainage!$J$5:$J$204<>"")),IF(UPPER(B_Drainage!$J$5:$J$204)="Y",1,"")),"") | AB12: =IFERROR(LOOKUP(2,1/((B_Drainage!$A$5:$A$204<>"")*(B_Drainage!$A$5:$A$204<=$B12)*(B_Drainage!$B$5:$B$204>$B12)*(B_Drainage!$K$5:$K$204<>"")),IF(B_Drainage!$K$5:$K$204="-","",B_Drainage!$K$5:$K$204)),"") | AC12: =IFERROR(LOOKUP(2,1/((B_Drainage!$A$5:$A$204<>"")*(B_Drainage!$A$5:$A$204<=$B12)*(B_Drainage!$B$5:$B$204>$B12)*(B_Drainage!$L$5:$L$204<>"")),IF(B_Drainage!$L$5:$L$204="-","",B_Drainage!$L$5:$L$204)),"") | AD12: =IFERROR(LOOKUP(2,1/((D_Points!$A$5:$A$204<>"")*(D_Points!$A$5:$A$204>=$B12)*(D_Points!$A$5:$A$204<$B12+P_Interval)*(UPPER(TRIM(D_Points!$B$5:$B$204))="TURNOUT_L")*(D_Points!$H$5:$H$204<>"")),D_Points!$H$5:$H$204),"") | AE12: =IFERROR(LOOKUP(2,1/((D_Points!$A$5:$A$204<>"")*(D_Points!$A$5:$A$204>=$B12)*(D_Points!$A$5:$A$204<$B12+P_Interval)*(UPPER(TRIM(D_Points!$B$5:$B$204))="TURNOUT_R")*(D_Points!$H$5:$H$204<>"")),D_Points!$H$5:$H$204),"") | AF12: =IFERROR(LOOKUP(2,1/((B_Drainage!$A$5:$A$204<>"")*(B_Drainage!$A$5:$A$204<=$B12)*(B_Drainage!$B$5:$B$204>$B12)*(B_Drainage!$M$5:$M$204<>"")),IF(UPPER(B_Drainage!$M$5:$M$204)="Y",1,"")),"") | AG12: =IFERROR(LOOKUP(2,1/((B_Drainage!$A$5:$A$204<>"")*(B_Drainage!$A$5:$A$204<=$B12)*(B_Drainage!$B$5:$B$204>$B12)*(B_Drainage!$N$5:$N$204<>"")),IF(UPPER(B_Drainage!$N$5:$N$204)="Y",1,"")),"") | AH12: =IF($AT12="BLADE",1,"") | AI12: =IF($AT12="RESHAPE",1,"") | AJ12: =IF($AT12="SCARIFY",1,"") | AK12: =$AU12 | AL12: =$AV12 | AM12: =IF(OR(UPPER($AW12)="Y",$AW12=1),1,"") | AN12: =IF(OR(UPPER($AX12)="Y",$AX12=1),1,"") | AO12: =IF(OR(UPPER($AY12)="Y",$AY12=1),1,"") | AQ12: =IFERROR(LOOKUP(2,1/((C_Pavement!$A$5:$A$204<>"")*(C_Pavement!$A$5:$A$204<=$B12)*(C_Pavement!$B$5:$B$204>$B12)*(C_Pavement!$C$5:$C$204<>"")),ROW(C_Pavement!$C$5:$C$204)-4),"") | AR12: =IF($AQ12="","",UPPER(TRIM(INDEX(C_Pavement!$C$5:$C$204,$AQ12)))) | AS12: =IF($AR12="","",IFERROR(MATCH($AR12,E_Rules!$A$5:$A$9,0),"")) | AT12: =IF($AQ12="","",IF(INDEX(C_Pavement!$D$5:$D$204,$AQ12)<>"",UPPER(TRIM(INDEX(C_Pavement!$D$5:$D$204,$AQ12))),IF($AS12="","",INDEX(E_Rules!$C$5:$C$9,$AS12)))) | AU12: =IF($AQ12="","",IF(INDEX(C_Pavement!$E$5:$E$204,$AQ12)<>"",IF(INDEX(C_Pavement!$E$5:$E$204,$AQ12)="-","",INDEX(C_Pavement!$E$5:$E$204,$AQ12)),IF($AS12="","",INDEX(E_Rules!$D$5:$D$9,$AS12)))) | AV12: =IF($AQ12="","",IF(INDEX(C_Pavement!$F$5:$F$204,$AQ12)<>"",IF(INDEX(C_Pavement!$F$5:$F$204,$AQ12)="-","",INDEX(C_Pavement!$F$5:$F$204,$AQ12)),IF($AS12="","",INDEX(E_Rules!$E$5:$E$9,$AS12)))) | AW12: =IF($AQ12="","",IF(INDEX(C_Pavement!$G$5:$G$204,$AQ12)<>"",IF(INDEX(C_Pavement!$G$5:$G$204,$AQ12)="-","",INDEX(C_Pavement!$G$5:$G$204,$AQ12)),IF($AS12="","",INDEX(E_Rules!$F$5:$F$9,$AS12)))) | AX12: =IF($AQ12="","",IF(INDEX(C_Pavement!$H$5:$H$204,$AQ12)<>"",IF(INDEX(C_Pavement!$H$5:$H$204,$AQ12)="-","",INDEX(C_Pavement!$H$5:$H$204,$AQ12)),IF($AS12="","",INDEX(E_Rules!$G$5:$G$9,$AS12)))) | AY12: =IF($AQ12="","",IF(INDEX(C_Pavement!$I$5:$I$204,$AQ12)<>"",IF(INDEX(C_Pavement!$I$5:$I$204,$AQ12)="-","",INDEX(C_Pavement!$I$5:$I$204,$AQ12)),IF($AS12="","",INDEX(E_Rules!$H$5:$H$9,$AS12))))
A13: 8 | B13: 350 | C13: 0+350 | D13: =IFERROR(LOOKUP(2,1/((A_Corridor!$A$5:$A$204<>"")*(A_Corridor!$A$5:$A$204<=$B13)*(A_Corridor!$B$5:$B$204>$B13)*(A_Corridor!$C$5:$C$204<>"")),IF(UPPER(A_Corridor!$C$5:$C$204)="Y",1,"")),"") | E13: =IFERROR(LOOKUP(2,1/((A_Corridor!$A$5:$A$204<>"")*(A_Corridor!$A$5:$A$204<=$B13)*(A_Corridor!$B$5:$B$204>$B13)*(A_Corridor!$D$5:$D$204<>"")),IF(A_Corridor!$D$5:$D$204="-","",UPPER(A_Corridor!$D$5:$D$204))),"") | F13: =IFERROR(LOOKUP(2,1/((A_Corridor!$A$5:$A$204<>"")*(A_Corridor!$A$5:$A$204<=$B13)*(A_Corridor!$B$5:$B$204>$B13)*(A_Corridor!$E$5:$E$204<>"")),IF(A_Corridor!$E$5:$E$204="-","",1)),"") | G13: =IFERROR(LOOKUP(2,1/((A_Corridor!$A$5:$A$204<>"")*(A_Corridor!$A$5:$A$204<=$B13)*(A_Corridor!$B$5:$B$204>$B13)*(A_Corridor!$E$5:$E$204<>"")),IF(A_Corridor!$E$5:$E$204="-","",A_Corridor!$E$5:$E$204)),"") | H13: =IFERROR(LOOKUP(2,1/((D_Points!$A$5:$A$204<>"")*(D_Points!$A$5:$A$204>=$B13)*(D_Points!$A$5:$A$204<$B13+P_Interval)*(UPPER(TRIM(D_Points!$B$5:$B$204))="GULLY")*(D_Points!$H$5:$H$204<>"")),D_Points!$H$5:$H$204),"") | I13: =IFERROR(LOOKUP(2,1/((A_Corridor!$A$5:$A$204<>"")*(A_Corridor!$A$5:$A$204<=$B13)*(A_Corridor!$B$5:$B$204>$B13)*(A_Corridor!$F$5:$F$204<>"")),IF(A_Corridor!$F$5:$F$204="-","",1)),"") | J13: =IFERROR(LOOKUP(2,1/((A_Corridor!$A$5:$A$204<>"")*(A_Corridor!$A$5:$A$204<=$B13)*(A_Corridor!$B$5:$B$204>$B13)*(A_Corridor!$F$5:$F$204<>"")),IF(A_Corridor!$F$5:$F$204="-","",A_Corridor!$F$5:$F$204)),"") | K13: =IFERROR(LOOKUP(2,1/((A_Corridor!$A$5:$A$204<>"")*(A_Corridor!$A$5:$A$204<=$B13)*(A_Corridor!$B$5:$B$204>$B13)*(A_Corridor!$G$5:$G$204<>"")),IF(A_Corridor!$G$5:$G$204="-","",A_Corridor!$G$5:$G$204)),"") | L13: =IFERROR(LOOKUP(2,1/((A_Corridor!$A$5:$A$204<>"")*(A_Corridor!$A$5:$A$204<=$B13)*(A_Corridor!$B$5:$B$204>$B13)*(A_Corridor!$H$5:$H$204<>"")),IF(A_Corridor!$H$5:$H$204="-","",1)),"") | M13: =IFERROR(LOOKUP(2,1/((A_Corridor!$A$5:$A$204<>"")*(A_Corridor!$A$5:$A$204<=$B13)*(A_Corridor!$B$5:$B$204>$B13)*(A_Corridor!$H$5:$H$204<>"")),IF(A_Corridor!$H$5:$H$204="-","",A_Corridor!$H$5:$H$204)),"") | N13: =IFERROR(LOOKUP(2,1/((A_Corridor!$A$5:$A$204<>"")*(A_Corridor!$A$5:$A$204<=$B13)*(A_Corridor!$B$5:$B$204>$B13)*(A_Corridor!$I$5:$I$204<>"")),IF(A_Corridor!$I$5:$I$204="-","",A_Corridor!$I$5:$I$204)),"") | O13: =IFERROR(LOOKUP(2,1/((D_Points!$A$5:$A$204<>"")*(D_Points!$A$5:$A$204>=$B13)*(D_Points!$A$5:$A$204<$B13+P_Interval)*(UPPER(TRIM(D_Points!$B$5:$B$204))="PITCHING")*(D_Points!$H$5:$H$204<>"")),D_Points!$H$5:$H$204),"") | P13: =IFERROR(LOOKUP(2,1/((B_Drainage!$A$5:$A$204<>"")*(B_Drainage!$A$5:$A$204<=$B13)*(B_Drainage!$B$5:$B$204>$B13)*(B_Drainage!$C$5:$C$204<>"")),IF(B_Drainage!$C$5:$C$204="-","",UPPER(B_Drainage!$C$5:$C$204))),"") | Q13: =IFERROR(LOOKUP(2,1/((B_Drainage!$A$5:$A$204<>"")*(B_Drainage!$A$5:$A$204<=$B13)*(B_Drainage!$B$5:$B$204>$B13)*(B_Drainage!$D$5:$D$204<>"")),IF(B_Drainage!$D$5:$D$204="-","",UPPER(B_Drainage!$D$5:$D$204))),"") | R13: =IFERROR(LOOKUP(2,1/((D_Points!$A$5:$A$204<>"")*(D_Points!$A$5:$A$204>=$B13)*(D_Points!$A$5:$A$204<$B13+P_Interval)*(RIGHT(UPPER(TRIM(D_Points!$B$5:$B$204)),8)="_CULVERT")),IF(LEFT(UPPER(TRIM(D_Points!$B$5:$B$204)),2)="EX",1,IF(LEFT(UPPER(TRIM(D_Points!$B$5:$B$204)),2)="PR",2,3))),"") | S13: =IFERROR(LOOKUP(2,1/((D_Points!$A$5:$A$204<>"")*(D_Points!$A$5:$A$204>=$B13)*(D_Points!$A$5:$A$204<$B13+P_Interval)*(RIGHT(UPPER(TRIM(D_Points!$B$5:$B$204)),7)="_BRIDGE")),IF(LEFT(UPPER(TRIM(D_Points!$B$5:$B$204)),2)="EX",1,IF(LEFT(UPPER(TRIM(D_Points!$B$5:$B$204)),2)="PR",2,2))),"") | T13: =IFERROR(LOOKUP(2,1/((B_Drainage!$A$5:$A$204<>"")*(B_Drainage!$A$5:$A$204<=$B13)*(B_Drainage!$B$5:$B$204>$B13)*(B_Drainage!$E$5:$E$204<>"")),IF(B_Drainage!$E$5:$E$204="-","",1)),"") | U13: =IFERROR(LOOKUP(2,1/((B_Drainage!$A$5:$A$204<>"")*(B_Drainage!$A$5:$A$204<=$B13)*(B_Drainage!$B$5:$B$204>$B13)*(B_Drainage!$E$5:$E$204<>"")),IF(B_Drainage!$E$5:$E$204="-","",B_Drainage!$E$5:$E$204)),"") | V13: =IFERROR(LOOKUP(2,1/((B_Drainage!$A$5:$A$204<>"")*(B_Drainage!$A$5:$A$204<=$B13)*(B_Drainage!$B$5:$B$204>$B13)*(B_Drainage!$F$5:$F$204<>"")),IF(B_Drainage!$F$5:$F$204="-","",1)),"") | W13: =IFERROR(LOOKUP(2,1/((B_Drainage!$A$5:$A$204<>"")*(B_Drainage!$A$5:$A$204<=$B13)*(B_Drainage!$B$5:$B$204>$B13)*(B_Drainage!$F$5:$F$204<>"")),IF(B_Drainage!$F$5:$F$204="-","",B_Drainage!$F$5:$F$204)),"") | X13: =IFERROR(LOOKUP(2,1/((B_Drainage!$A$5:$A$204<>"")*(B_Drainage!$A$5:$A$204<=$B13)*(B_Drainage!$B$5:$B$204>$B13)*(B_Drainage!$G$5:$G$204<>"")),IF(UPPER(B_Drainage!$G$5:$G$204)="Y",1,"")),"") | Y13: =IFERROR(LOOKUP(2,1/((B_Drainage!$A$5:$A$204<>"")*(B_Drainage!$A$5:$A$204<=$B13)*(B_Drainage!$B$5:$B$204>$B13)*(B_Drainage!$H$5:$H$204<>"")),IF(UPPER(B_Drainage!$H$5:$H$204)="Y",1,"")),"") | Z13: =IFERROR(LOOKUP(2,1/((B_Drainage!$A$5:$A$204<>"")*(B_Drainage!$A$5:$A$204<=$B13)*(B_Drainage!$B$5:$B$204>$B13)*(B_Drainage!$I$5:$I$204<>"")),IF(UPPER(B_Drainage!$I$5:$I$204)="Y",1,"")),"") | AA13: =IFERROR(LOOKUP(2,1/((B_Drainage!$A$5:$A$204<>"")*(B_Drainage!$A$5:$A$204<=$B13)*(B_Drainage!$B$5:$B$204>$B13)*(B_Drainage!$J$5:$J$204<>"")),IF(UPPER(B_Drainage!$J$5:$J$204)="Y",1,"")),"") | AB13: =IFERROR(LOOKUP(2,1/((B_Drainage!$A$5:$A$204<>"")*(B_Drainage!$A$5:$A$204<=$B13)*(B_Drainage!$B$5:$B$204>$B13)*(B_Drainage!$K$5:$K$204<>"")),IF(B_Drainage!$K$5:$K$204="-","",B_Drainage!$K$5:$K$204)),"") | AC13: =IFERROR(LOOKUP(2,1/((B_Drainage!$A$5:$A$204<>"")*(B_Drainage!$A$5:$A$204<=$B13)*(B_Drainage!$B$5:$B$204>$B13)*(B_Drainage!$L$5:$L$204<>"")),IF(B_Drainage!$L$5:$L$204="-","",B_Drainage!$L$5:$L$204)),"") | AD13: =IFERROR(LOOKUP(2,1/((D_Points!$A$5:$A$204<>"")*(D_Points!$A$5:$A$204>=$B13)*(D_Points!$A$5:$A$204<$B13+P_Interval)*(UPPER(TRIM(D_Points!$B$5:$B$204))="TURNOUT_L")*(D_Points!$H$5:$H$204<>"")),D_Points!$H$5:$H$204),"") | AE13: =IFERROR(LOOKUP(2,1/((D_Points!$A$5:$A$204<>"")*(D_Points!$A$5:$A$204>=$B13)*(D_Points!$A$5:$A$204<$B13+P_Interval)*(UPPER(TRIM(D_Points!$B$5:$B$204))="TURNOUT_R")*(D_Points!$H$5:$H$204<>"")),D_Points!$H$5:$H$204),"") | AF13: =IFERROR(LOOKUP(2,1/((B_Drainage!$A$5:$A$204<>"")*(B_Drainage!$A$5:$A$204<=$B13)*(B_Drainage!$B$5:$B$204>$B13)*(B_Drainage!$M$5:$M$204<>"")),IF(UPPER(B_Drainage!$M$5:$M$204)="Y",1,"")),"") | AG13: =IFERROR(LOOKUP(2,1/((B_Drainage!$A$5:$A$204<>"")*(B_Drainage!$A$5:$A$204<=$B13)*(B_Drainage!$B$5:$B$204>$B13)*(B_Drainage!$N$5:$N$204<>"")),IF(UPPER(B_Drainage!$N$5:$N$204)="Y",1,"")),"") | AH13: =IF($AT13="BLADE",1,"") | AI13: =IF($AT13="RESHAPE",1,"") | AJ13: =IF($AT13="SCARIFY",1,"") | AK13: =$AU13 | AL13: =$AV13 | AM13: =IF(OR(UPPER($AW13)="Y",$AW13=1),1,"") | AN13: =IF(OR(UPPER($AX13)="Y",$AX13=1),1,"") | AO13: =IF(OR(UPPER($AY13)="Y",$AY13=1),1,"") | AQ13: =IFERROR(LOOKUP(2,1/((C_Pavement!$A$5:$A$204<>"")*(C_Pavement!$A$5:$A$204<=$B13)*(C_Pavement!$B$5:$B$204>$B13)*(C_Pavement!$C$5:$C$204<>"")),ROW(C_Pavement!$C$5:$C$204)-4),"") | AR13: =IF($AQ13="","",UPPER(TRIM(INDEX(C_Pavement!$C$5:$C$204,$AQ13)))) | AS13: =IF($AR13="","",IFERROR(MATCH($AR13,E_Rules!$A$5:$A$9,0),"")) | AT13: =IF($AQ13="","",IF(INDEX(C_Pavement!$D$5:$D$204,$AQ13)<>"",UPPER(TRIM(INDEX(C_Pavement!$D$5:$D$204,$AQ13))),IF($AS13="","",INDEX(E_Rules!$C$5:$C$9,$AS13)))) | AU13: =IF($AQ13="","",IF(INDEX(C_Pavement!$E$5:$E$204,$AQ13)<>"",IF(INDEX(C_Pavement!$E$5:$E$204,$AQ13)="-","",INDEX(C_Pavement!$E$5:$E$204,$AQ13)),IF($AS13="","",INDEX(E_Rules!$D$5:$D$9,$AS13)))) | AV13: =IF($AQ13="","",IF(INDEX(C_Pavement!$F$5:$F$204,$AQ13)<>"",IF(INDEX(C_Pavement!$F$5:$F$204,$AQ13)="-","",INDEX(C_Pavement!$F$5:$F$204,$AQ13)),IF($AS13="","",INDEX(E_Rules!$E$5:$E$9,$AS13)))) | AW13: =IF($AQ13="","",IF(INDEX(C_Pavement!$G$5:$G$204,$AQ13)<>"",IF(INDEX(C_Pavement!$G$5:$G$204,$AQ13)="-","",INDEX(C_Pavement!$G$5:$G$204,$AQ13)),IF($AS13="","",INDEX(E_Rules!$F$5:$F$9,$AS13)))) | AX13: =IF($AQ13="","",IF(INDEX(C_Pavement!$H$5:$H$204,$AQ13)<>"",IF(INDEX(C_Pavement!$H$5:$H$204,$AQ13)="-","",INDEX(C_Pavement!$H$5:$H$204,$AQ13)),IF($AS13="","",INDEX(E_Rules!$G$5:$G$9,$AS13)))) | AY13: =IF($AQ13="","",IF(INDEX(C_Pavement!$I$5:$I$204,$AQ13)<>"",IF(INDEX(C_Pavement!$I$5:$I$204,$AQ13)="-","",INDEX(C_Pavement!$I$5:$I$204,$AQ13)),IF($AS13="","",INDEX(E_Rules!$H$5:$H$9,$AS13))))
A14: 9 | B14: 400 | C14: 0+400 | D14: =IFERROR(LOOKUP(2,1/((A_Corridor!$A$5:$A$204<>"")*(A_Corridor!$A$5:$A$204<=$B14)*(A_Corridor!$B$5:$B$204>$B14)*(A_Corridor!$C$5:$C$204<>"")),IF(UPPER(A_Corridor!$C$5:$C$204)="Y",1,"")),"") | E14: =IFERROR(LOOKUP(2,1/((A_Corridor!$A$5:$A$204<>"")*(A_Corridor!$A$5:$A$204<=$B14)*(A_Corridor!$B$5:$B$204>$B14)*(A_Corridor!$D$5:$D$204<>"")),IF(A_Corridor!$D$5:$D$204="-","",UPPER(A_Corridor!$D$5:$D$204))),"") | F14: =IFERROR(LOOKUP(2,1/((A_Corridor!$A$5:$A$204<>"")*(A_Corridor!$A$5:$A$204<=$B14)*(A_Corridor!$B$5:$B$204>$B14)*(A_Corridor!$E$5:$E$204<>"")),IF(A_Corridor!$E$5:$E$204="-","",1)),"") | G14: =IFERROR(LOOKUP(2,1/((A_Corridor!$A$5:$A$204<>"")*(A_Corridor!$A$5:$A$204<=$B14)*(A_Corridor!$B$5:$B$204>$B14)*(A_Corridor!$E$5:$E$204<>"")),IF(A_Corridor!$E$5:$E$204="-","",A_Corridor!$E$5:$E$204)),"") | H14: =IFERROR(LOOKUP(2,1/((D_Points!$A$5:$A$204<>"")*(D_Points!$A$5:$A$204>=$B14)*(D_Points!$A$5:$A$204<$B14+P_Interval)*(UPPER(TRIM(D_Points!$B$5:$B$204))="GULLY")*(D_Points!$H$5:$H$204<>"")),D_Points!$H$5:$H$204),"") | I14: =IFERROR(LOOKUP(2,1/((A_Corridor!$A$5:$A$204<>"")*(A_Corridor!$A$5:$A$204<=$B14)*(A_Corridor!$B$5:$B$204>$B14)*(A_Corridor!$F$5:$F$204<>"")),IF(A_Corridor!$F$5:$F$204="-","",1)),"") | J14: =IFERROR(LOOKUP(2,1/((A_Corridor!$A$5:$A$204<>"")*(A_Corridor!$A$5:$A$204<=$B14)*(A_Corridor!$B$5:$B$204>$B14)*(A_Corridor!$F$5:$F$204<>"")),IF(A_Corridor!$F$5:$F$204="-","",A_Corridor!$F$5:$F$204)),"") | K14: =IFERROR(LOOKUP(2,1/((A_Corridor!$A$5:$A$204<>"")*(A_Corridor!$A$5:$A$204<=$B14)*(A_Corridor!$B$5:$B$204>$B14)*(A_Corridor!$G$5:$G$204<>"")),IF(A_Corridor!$G$5:$G$204="-","",A_Corridor!$G$5:$G$204)),"") | L14: =IFERROR(LOOKUP(2,1/((A_Corridor!$A$5:$A$204<>"")*(A_Corridor!$A$5:$A$204<=$B14)*(A_Corridor!$B$5:$B$204>$B14)*(A_Corridor!$H$5:$H$204<>"")),IF(A_Corridor!$H$5:$H$204="-","",1)),"") | M14: =IFERROR(LOOKUP(2,1/((A_Corridor!$A$5:$A$204<>"")*(A_Corridor!$A$5:$A$204<=$B14)*(A_Corridor!$B$5:$B$204>$B14)*(A_Corridor!$H$5:$H$204<>"")),IF(A_Corridor!$H$5:$H$204="-","",A_Corridor!$H$5:$H$204)),"") | N14: =IFERROR(LOOKUP(2,1/((A_Corridor!$A$5:$A$204<>"")*(A_Corridor!$A$5:$A$204<=$B14)*(A_Corridor!$B$5:$B$204>$B14)*(A_Corridor!$I$5:$I$204<>"")),IF(A_Corridor!$I$5:$I$204="-","",A_Corridor!$I$5:$I$204)),"") | O14: =IFERROR(LOOKUP(2,1/((D_Points!$A$5:$A$204<>"")*(D_Points!$A$5:$A$204>=$B14)*(D_Points!$A$5:$A$204<$B14+P_Interval)*(UPPER(TRIM(D_Points!$B$5:$B$204))="PITCHING")*(D_Points!$H$5:$H$204<>"")),D_Points!$H$5:$H$204),"") | P14: =IFERROR(LOOKUP(2,1/((B_Drainage!$A$5:$A$204<>"")*(B_Drainage!$A$5:$A$204<=$B14)*(B_Drainage!$B$5:$B$204>$B14)*(B_Drainage!$C$5:$C$204<>"")),IF(B_Drainage!$C$5:$C$204="-","",UPPER(B_Drainage!$C$5:$C$204))),"") | Q14: =IFERROR(LOOKUP(2,1/((B_Drainage!$A$5:$A$204<>"")*(B_Drainage!$A$5:$A$204<=$B14)*(B_Drainage!$B$5:$B$204>$B14)*(B_Drainage!$D$5:$D$204<>"")),IF(B_Drainage!$D$5:$D$204="-","",UPPER(B_Drainage!$D$5:$D$204))),"") | R14: =IFERROR(LOOKUP(2,1/((D_Points!$A$5:$A$204<>"")*(D_Points!$A$5:$A$204>=$B14)*(D_Points!$A$5:$A$204<$B14+P_Interval)*(RIGHT(UPPER(TRIM(D_Points!$B$5:$B$204)),8)="_CULVERT")),IF(LEFT(UPPER(TRIM(D_Points!$B$5:$B$204)),2)="EX",1,IF(LEFT(UPPER(TRIM(D_Points!$B$5:$B$204)),2)="PR",2,3))),"") | S14: =IFERROR(LOOKUP(2,1/((D_Points!$A$5:$A$204<>"")*(D_Points!$A$5:$A$204>=$B14)*(D_Points!$A$5:$A$204<$B14+P_Interval)*(RIGHT(UPPER(TRIM(D_Points!$B$5:$B$204)),7)="_BRIDGE")),IF(LEFT(UPPER(TRIM(D_Points!$B$5:$B$204)),2)="EX",1,IF(LEFT(UPPER(TRIM(D_Points!$B$5:$B$204)),2)="PR",2,2))),"") | T14: =IFERROR(LOOKUP(2,1/((B_Drainage!$A$5:$A$204<>"")*(B_Drainage!$A$5:$A$204<=$B14)*(B_Drainage!$B$5:$B$204>$B14)*(B_Drainage!$E$5:$E$204<>"")),IF(B_Drainage!$E$5:$E$204="-","",1)),"") | U14: =IFERROR(LOOKUP(2,1/((B_Drainage!$A$5:$A$204<>"")*(B_Drainage!$A$5:$A$204<=$B14)*(B_Drainage!$B$5:$B$204>$B14)*(B_Drainage!$E$5:$E$204<>"")),IF(B_Drainage!$E$5:$E$204="-","",B_Drainage!$E$5:$E$204)),"") | V14: =IFERROR(LOOKUP(2,1/((B_Drainage!$A$5:$A$204<>"")*(B_Drainage!$A$5:$A$204<=$B14)*(B_Drainage!$B$5:$B$204>$B14)*(B_Drainage!$F$5:$F$204<>"")),IF(B_Drainage!$F$5:$F$204="-","",1)),"") | W14: =IFERROR(LOOKUP(2,1/((B_Drainage!$A$5:$A$204<>"")*(B_Drainage!$A$5:$A$204<=$B14)*(B_Drainage!$B$5:$B$204>$B14)*(B_Drainage!$F$5:$F$204<>"")),IF(B_Drainage!$F$5:$F$204="-","",B_Drainage!$F$5:$F$204)),"") | X14: =IFERROR(LOOKUP(2,1/((B_Drainage!$A$5:$A$204<>"")*(B_Drainage!$A$5:$A$204<=$B14)*(B_Drainage!$B$5:$B$204>$B14)*(B_Drainage!$G$5:$G$204<>"")),IF(UPPER(B_Drainage!$G$5:$G$204)="Y",1,"")),"") | Y14: =IFERROR(LOOKUP(2,1/((B_Drainage!$A$5:$A$204<>"")*(B_Drainage!$A$5:$A$204<=$B14)*(B_Drainage!$B$5:$B$204>$B14)*(B_Drainage!$H$5:$H$204<>"")),IF(UPPER(B_Drainage!$H$5:$H$204)="Y",1,"")),"") | Z14: =IFERROR(LOOKUP(2,1/((B_Drainage!$A$5:$A$204<>"")*(B_Drainage!$A$5:$A$204<=$B14)*(B_Drainage!$B$5:$B$204>$B14)*(B_Drainage!$I$5:$I$204<>"")),IF(UPPER(B_Drainage!$I$5:$I$204)="Y",1,"")),"") | AA14: =IFERROR(LOOKUP(2,1/((B_Drainage!$A$5:$A$204<>"")*(B_Drainage!$A$5:$A$204<=$B14)*(B_Drainage!$B$5:$B$204>$B14)*(B_Drainage!$J$5:$J$204<>"")),IF(UPPER(B_Drainage!$J$5:$J$204)="Y",1,"")),"") | AB14: =IFERROR(LOOKUP(2,1/((B_Drainage!$A$5:$A$204<>"")*(B_Drainage!$A$5:$A$204<=$B14)*(B_Drainage!$B$5:$B$204>$B14)*(B_Drainage!$K$5:$K$204<>"")),IF(B_Drainage!$K$5:$K$204="-","",B_Drainage!$K$5:$K$204)),"") | AC14: =IFERROR(LOOKUP(2,1/((B_Drainage!$A$5:$A$204<>"")*(B_Drainage!$A$5:$A$204<=$B14)*(B_Drainage!$B$5:$B$204>$B14)*(B_Drainage!$L$5:$L$204<>"")),IF(B_Drainage!$L$5:$L$204="-","",B_Drainage!$L$5:$L$204)),"") | AD14: =IFERROR(LOOKUP(2,1/((D_Points!$A$5:$A$204<>"")*(D_Points!$A$5:$A$204>=$B14)*(D_Points!$A$5:$A$204<$B14+P_Interval)*(UPPER(TRIM(D_Points!$B$5:$B$204))="TURNOUT_L")*(D_Points!$H$5:$H$204<>"")),D_Points!$H$5:$H$204),"") | AE14: =IFERROR(LOOKUP(2,1/((D_Points!$A$5:$A$204<>"")*(D_Points!$A$5:$A$204>=$B14)*(D_Points!$A$5:$A$204<$B14+P_Interval)*(UPPER(TRIM(D_Points!$B$5:$B$204))="TURNOUT_R")*(D_Points!$H$5:$H$204<>"")),D_Points!$H$5:$H$204),"") | AF14: =IFERROR(LOOKUP(2,1/((B_Drainage!$A$5:$A$204<>"")*(B_Drainage!$A$5:$A$204<=$B14)*(B_Drainage!$B$5:$B$204>$B14)*(B_Drainage!$M$5:$M$204<>"")),IF(UPPER(B_Drainage!$M$5:$M$204)="Y",1,"")),"") | AG14: =IFERROR(LOOKUP(2,1/((B_Drainage!$A$5:$A$204<>"")*(B_Drainage!$A$5:$A$204<=$B14)*(B_Drainage!$B$5:$B$204>$B14)*(B_Drainage!$N$5:$N$204<>"")),IF(UPPER(B_Drainage!$N$5:$N$204)="Y",1,"")),"") | AH14: =IF($AT14="BLADE",1,"") | AI14: =IF($AT14="RESHAPE",1,"") | AJ14: =IF($AT14="SCARIFY",1,"") | AK14: =$AU14 | AL14: =$AV14 | AM14: =IF(OR(UPPER($AW14)="Y",$AW14=1),1,"") | AN14: =IF(OR(UPPER($AX14)="Y",$AX14=1),1,"") | AO14: =IF(OR(UPPER($AY14)="Y",$AY14=1),1,"") | AQ14: =IFERROR(LOOKUP(2,1/((C_Pavement!$A$5:$A$204<>"")*(C_Pavement!$A$5:$A$204<=$B14)*(C_Pavement!$B$5:$B$204>$B14)*(C_Pavement!$C$5:$C$204<>"")),ROW(C_Pavement!$C$5:$C$204)-4),"") | AR14: =IF($AQ14="","",UPPER(TRIM(INDEX(C_Pavement!$C$5:$C$204,$AQ14)))) | AS14: =IF($AR14="","",IFERROR(MATCH($AR14,E_Rules!$A$5:$A$9,0),"")) | AT14: =IF($AQ14="","",IF(INDEX(C_Pavement!$D$5:$D$204,$AQ14)<>"",UPPER(TRIM(INDEX(C_Pavement!$D$5:$D$204,$AQ14))),IF($AS14="","",INDEX(E_Rules!$C$5:$C$9,$AS14)))) | AU14: =IF($AQ14="","",IF(INDEX(C_Pavement!$E$5:$E$204,$AQ14)<>"",IF(INDEX(C_Pavement!$E$5:$E$204,$AQ14)="-","",INDEX(C_Pavement!$E$5:$E$204,$AQ14)),IF($AS14="","",INDEX(E_Rules!$D$5:$D$9,$AS14)))) | AV14: =IF($AQ14="","",IF(INDEX(C_Pavement!$F$5:$F$204,$AQ14)<>"",IF(INDEX(C_Pavement!$F$5:$F$204,$AQ14)="-","",INDEX(C_Pavement!$F$5:$F$204,$AQ14)),IF($AS14="","",INDEX(E_Rules!$E$5:$E$9,$AS14)))) | AW14: =IF($AQ14="","",IF(INDEX(C_Pavement!$G$5:$G$204,$AQ14)<>"",IF(INDEX(C_Pavement!$G$5:$G$204,$AQ14)="-","",INDEX(C_Pavement!$G$5:$G$204,$AQ14)),IF($AS14="","",INDEX(E_Rules!$F$5:$F$9,$AS14)))) | AX14: =IF($AQ14="","",IF(INDEX(C_Pavement!$H$5:$H$204,$AQ14)<>"",IF(INDEX(C_Pavement!$H$5:$H$204,$AQ14)="-","",INDEX(C_Pavement!$H$5:$H$204,$AQ14)),IF($AS14="","",INDEX(E_Rules!$G$5:$G$9,$AS14)))) | AY14: =IF($AQ14="","",IF(INDEX(C_Pavement!$I$5:$I$204,$AQ14)<>"",IF(INDEX(C_Pavement!$I$5:$I$204,$AQ14)="-","",INDEX(C_Pavement!$I$5:$I$204,$AQ14)),IF($AS14="","",INDEX(E_Rules!$H$5:$H$9,$AS14))))
A15: 10 | B15: 450 | C15: 0+450 | D15: =IFERROR(LOOKUP(2,1/((A_Corridor!$A$5:$A$204<>"")*(A_Corridor!$A$5:$A$204<=$B15)*(A_Corridor!$B$5:$B$204>$B15)*(A_Corridor!$C$5:$C$204<>"")),IF(UPPER(A_Corridor!$C$5:$C$204)="Y",1,"")),"") | E15: =IFERROR(LOOKUP(2,1/((A_Corridor!$A$5:$A$204<>"")*(A_Corridor!$A$5:$A$204<=$B15)*(A_Corridor!$B$5:$B$204>$B15)*(A_Corridor!$D$5:$D$204<>"")),IF(A_Corridor!$D$5:$D$204="-","",UPPER(A_Corridor!$D$5:$D$204))),"") | F15: =IFERROR(LOOKUP(2,1/((A_Corridor!$A$5:$A$204<>"")*(A_Corridor!$A$5:$A$204<=$B15)*(A_Corridor!$B$5:$B$204>$B15)*(A_Corridor!$E$5:$E$204<>"")),IF(A_Corridor!$E$5:$E$204="-","",1)),"") | G15: =IFERROR(LOOKUP(2,1/((A_Corridor!$A$5:$A$204<>"")*(A_Corridor!$A$5:$A$204<=$B15)*(A_Corridor!$B$5:$B$204>$B15)*(A_Corridor!$E$5:$E$204<>"")),IF(A_Corridor!$E$5:$E$204="-","",A_Corridor!$E$5:$E$204)),"") | H15: =IFERROR(LOOKUP(2,1/((D_Points!$A$5:$A$204<>"")*(D_Points!$A$5:$A$204>=$B15)*(D_Points!$A$5:$A$204<$B15+P_Interval)*(UPPER(TRIM(D_Points!$B$5:$B$204))="GULLY")*(D_Points!$H$5:$H$204<>"")),D_Points!$H$5:$H$204),"") | I15: =IFERROR(LOOKUP(2,1/((A_Corridor!$A$5:$A$204<>"")*(A_Corridor!$A$5:$A$204<=$B15)*(A_Corridor!$B$5:$B$204>$B15)*(A_Corridor!$F$5:$F$204<>"")),IF(A_Corridor!$F$5:$F$204="-","",1)),"") | J15: =IFERROR(LOOKUP(2,1/((A_Corridor!$A$5:$A$204<>"")*(A_Corridor!$A$5:$A$204<=$B15)*(A_Corridor!$B$5:$B$204>$B15)*(A_Corridor!$F$5:$F$204<>"")),IF(A_Corridor!$F$5:$F$204="-","",A_Corridor!$F$5:$F$204)),"") | K15: =IFERROR(LOOKUP(2,1/((A_Corridor!$A$5:$A$204<>"")*(A_Corridor!$A$5:$A$204<=$B15)*(A_Corridor!$B$5:$B$204>$B15)*(A_Corridor!$G$5:$G$204<>"")),IF(A_Corridor!$G$5:$G$204="-","",A_Corridor!$G$5:$G$204)),"") | L15: =IFERROR(LOOKUP(2,1/((A_Corridor!$A$5:$A$204<>"")*(A_Corridor!$A$5:$A$204<=$B15)*(A_Corridor!$B$5:$B$204>$B15)*(A_Corridor!$H$5:$H$204<>"")),IF(A_Corridor!$H$5:$H$204="-","",1)),"") | M15: =IFERROR(LOOKUP(2,1/((A_Corridor!$A$5:$A$204<>"")*(A_Corridor!$A$5:$A$204<=$B15)*(A_Corridor!$B$5:$B$204>$B15)*(A_Corridor!$H$5:$H$204<>"")),IF(A_Corridor!$H$5:$H$204="-","",A_Corridor!$H$5:$H$204)),"") | N15: =IFERROR(LOOKUP(2,1/((A_Corridor!$A$5:$A$204<>"")*(A_Corridor!$A$5:$A$204<=$B15)*(A_Corridor!$B$5:$B$204>$B15)*(A_Corridor!$I$5:$I$204<>"")),IF(A_Corridor!$I$5:$I$204="-","",A_Corridor!$I$5:$I$204)),"") | O15: =IFERROR(LOOKUP(2,1/((D_Points!$A$5:$A$204<>"")*(D_Points!$A$5:$A$204>=$B15)*(D_Points!$A$5:$A$204<$B15+P_Interval)*(UPPER(TRIM(D_Points!$B$5:$B$204))="PITCHING")*(D_Points!$H$5:$H$204<>"")),D_Points!$H$5:$H$204),"") | P15: =IFERROR(LOOKUP(2,1/((B_Drainage!$A$5:$A$204<>"")*(B_Drainage!$A$5:$A$204<=$B15)*(B_Drainage!$B$5:$B$204>$B15)*(B_Drainage!$C$5:$C$204<>"")),IF(B_Drainage!$C$5:$C$204="-","",UPPER(B_Drainage!$C$5:$C$204))),"") | Q15: =IFERROR(LOOKUP(2,1/((B_Drainage!$A$5:$A$204<>"")*(B_Drainage!$A$5:$A$204<=$B15)*(B_Drainage!$B$5:$B$204>$B15)*(B_Drainage!$D$5:$D$204<>"")),IF(B_Drainage!$D$5:$D$204="-","",UPPER(B_Drainage!$D$5:$D$204))),"") | R15: =IFERROR(LOOKUP(2,1/((D_Points!$A$5:$A$204<>"")*(D_Points!$A$5:$A$204>=$B15)*(D_Points!$A$5:$A$204<$B15+P_Interval)*(RIGHT(UPPER(TRIM(D_Points!$B$5:$B$204)),8)="_CULVERT")),IF(LEFT(UPPER(TRIM(D_Points!$B$5:$B$204)),2)="EX",1,IF(LEFT(UPPER(TRIM(D_Points!$B$5:$B$204)),2)="PR",2,3))),"") | S15: =IFERROR(LOOKUP(2,1/((D_Points!$A$5:$A$204<>"")*(D_Points!$A$5:$A$204>=$B15)*(D_Points!$A$5:$A$204<$B15+P_Interval)*(RIGHT(UPPER(TRIM(D_Points!$B$5:$B$204)),7)="_BRIDGE")),IF(LEFT(UPPER(TRIM(D_Points!$B$5:$B$204)),2)="EX",1,IF(LEFT(UPPER(TRIM(D_Points!$B$5:$B$204)),2)="PR",2,2))),"") | T15: =IFERROR(LOOKUP(2,1/((B_Drainage!$A$5:$A$204<>"")*(B_Drainage!$A$5:$A$204<=$B15)*(B_Drainage!$B$5:$B$204>$B15)*(B_Drainage!$E$5:$E$204<>"")),IF(B_Drainage!$E$5:$E$204="-","",1)),"") | U15: =IFERROR(LOOKUP(2,1/((B_Drainage!$A$5:$A$204<>"")*(B_Drainage!$A$5:$A$204<=$B15)*(B_Drainage!$B$5:$B$204>$B15)*(B_Drainage!$E$5:$E$204<>"")),IF(B_Drainage!$E$5:$E$204="-","",B_Drainage!$E$5:$E$204)),"") | V15: =IFERROR(LOOKUP(2,1/((B_Drainage!$A$5:$A$204<>"")*(B_Drainage!$A$5:$A$204<=$B15)*(B_Drainage!$B$5:$B$204>$B15)*(B_Drainage!$F$5:$F$204<>"")),IF(B_Drainage!$F$5:$F$204="-","",1)),"") | W15: =IFERROR(LOOKUP(2,1/((B_Drainage!$A$5:$A$204<>"")*(B_Drainage!$A$5:$A$204<=$B15)*(B_Drainage!$B$5:$B$204>$B15)*(B_Drainage!$F$5:$F$204<>"")),IF(B_Drainage!$F$5:$F$204="-","",B_Drainage!$F$5:$F$204)),"") | X15: =IFERROR(LOOKUP(2,1/((B_Drainage!$A$5:$A$204<>"")*(B_Drainage!$A$5:$A$204<=$B15)*(B_Drainage!$B$5:$B$204>$B15)*(B_Drainage!$G$5:$G$204<>"")),IF(UPPER(B_Drainage!$G$5:$G$204)="Y",1,"")),"") | Y15: =IFERROR(LOOKUP(2,1/((B_Drainage!$A$5:$A$204<>"")*(B_Drainage!$A$5:$A$204<=$B15)*(B_Drainage!$B$5:$B$204>$B15)*(B_Drainage!$H$5:$H$204<>"")),IF(UPPER(B_Drainage!$H$5:$H$204)="Y",1,"")),"") | Z15: =IFERROR(LOOKUP(2,1/((B_Drainage!$A$5:$A$204<>"")*(B_Drainage!$A$5:$A$204<=$B15)*(B_Drainage!$B$5:$B$204>$B15)*(B_Drainage!$I$5:$I$204<>"")),IF(UPPER(B_Drainage!$I$5:$I$204)="Y",1,"")),"") | AA15: =IFERROR(LOOKUP(2,1/((B_Drainage!$A$5:$A$204<>"")*(B_Drainage!$A$5:$A$204<=$B15)*(B_Drainage!$B$5:$B$204>$B15)*(B_Drainage!$J$5:$J$204<>"")),IF(UPPER(B_Drainage!$J$5:$J$204)="Y",1,"")),"") | AB15: =IFERROR(LOOKUP(2,1/((B_Drainage!$A$5:$A$204<>"")*(B_Drainage!$A$5:$A$204<=$B15)*(B_Drainage!$B$5:$B$204>$B15)*(B_Drainage!$K$5:$K$204<>"")),IF(B_Drainage!$K$5:$K$204="-","",B_Drainage!$K$5:$K$204)),"") | AC15: =IFERROR(LOOKUP(2,1/((B_Drainage!$A$5:$A$204<>"")*(B_Drainage!$A$5:$A$204<=$B15)*(B_Drainage!$B$5:$B$204>$B15)*(B_Drainage!$L$5:$L$204<>"")),IF(B_Drainage!$L$5:$L$204="-","",B_Drainage!$L$5:$L$204)),"") | AD15: =IFERROR(LOOKUP(2,1/((D_Points!$A$5:$A$204<>"")*(D_Points!$A$5:$A$204>=$B15)*(D_Points!$A$5:$A$204<$B15+P_Interval)*(UPPER(TRIM(D_Points!$B$5:$B$204))="TURNOUT_L")*(D_Points!$H$5:$H$204<>"")),D_Points!$H$5:$H$204),"") | AE15: =IFERROR(LOOKUP(2,1/((D_Points!$A$5:$A$204<>"")*(D_Points!$A$5:$A$204>=$B15)*(D_Points!$A$5:$A$204<$B15+P_Interval)*(UPPER(TRIM(D_Points!$B$5:$B$204))="TURNOUT_R")*(D_Points!$H$5:$H$204<>"")),D_Points!$H$5:$H$204),"") | AF15: =IFERROR(LOOKUP(2,1/((B_Drainage!$A$5:$A$204<>"")*(B_Drainage!$A$5:$A$204<=$B15)*(B_Drainage!$B$5:$B$204>$B15)*(B_Drainage!$M$5:$M$204<>"")),IF(UPPER(B_Drainage!$M$5:$M$204)="Y",1,"")),"") | AG15: =IFERROR(LOOKUP(2,1/((B_Drainage!$A$5:$A$204<>"")*(B_Drainage!$A$5:$A$204<=$B15)*(B_Drainage!$B$5:$B$204>$B15)*(B_Drainage!$N$5:$N$204<>"")),IF(UPPER(B_Drainage!$N$5:$N$204)="Y",1,"")),"") | AH15: =IF($AT15="BLADE",1,"") | AI15: =IF($AT15="RESHAPE",1,"") | AJ15: =IF($AT15="SCARIFY",1,"") | AK15: =$AU15 | AL15: =$AV15 | AM15: =IF(OR(UPPER($AW15)="Y",$AW15=1),1,"") | AN15: =IF(OR(UPPER($AX15)="Y",$AX15=1),1,"") | AO15: =IF(OR(UPPER($AY15)="Y",$AY15=1),1,"") | AQ15: =IFERROR(LOOKUP(2,1/((C_Pavement!$A$5:$A$204<>"")*(C_Pavement!$A$5:$A$204<=$B15)*(C_Pavement!$B$5:$B$204>$B15)*(C_Pavement!$C$5:$C$204<>"")),ROW(C_Pavement!$C$5:$C$204)-4),"") | AR15: =IF($AQ15="","",UPPER(TRIM(INDEX(C_Pavement!$C$5:$C$204,$AQ15)))) | AS15: =IF($AR15="","",IFERROR(MATCH($AR15,E_Rules!$A$5:$A$9,0),"")) | AT15: =IF($AQ15="","",IF(INDEX(C_Pavement!$D$5:$D$204,$AQ15)<>"",UPPER(TRIM(INDEX(C_Pavement!$D$5:$D$204,$AQ15))),IF($AS15="","",INDEX(E_Rules!$C$5:$C$9,$AS15)))) | AU15: =IF($AQ15="","",IF(INDEX(C_Pavement!$E$5:$E$204,$AQ15)<>"",IF(INDEX(C_Pavement!$E$5:$E$204,$AQ15)="-","",INDEX(C_Pavement!$E$5:$E$204,$AQ15)),IF($AS15="","",INDEX(E_Rules!$D$5:$D$9,$AS15)))) | AV15: =IF($AQ15="","",IF(INDEX(C_Pavement!$F$5:$F$204,$AQ15)<>"",IF(INDEX(C_Pavement!$F$5:$F$204,$AQ15)="-","",INDEX(C_Pavement!$F$5:$F$204,$AQ15)),IF($AS15="","",INDEX(E_Rules!$E$5:$E$9,$AS15)))) | AW15: =IF($AQ15="","",IF(INDEX(C_Pavement!$G$5:$G$204,$AQ15)<>"",IF(INDEX(C_Pavement!$G$5:$G$204,$AQ15)="-","",INDEX(C_Pavement!$G$5:$G$204,$AQ15)),IF($AS15="","",INDEX(E_Rules!$F$5:$F$9,$AS15)))) | AX15: =IF($AQ15="","",IF(INDEX(C_Pavement!$H$5:$H$204,$AQ15)<>"",IF(INDEX(C_Pavement!$H$5:$H$204,$AQ15)="-","",INDEX(C_Pavement!$H$5:$H$204,$AQ15)),IF($AS15="","",INDEX(E_Rules!$G$5:$G$9,$AS15)))) | AY15: =IF($AQ15="","",IF(INDEX(C_Pavement!$I$5:$I$204,$AQ15)<>"",IF(INDEX(C_Pavement!$I$5:$I$204,$AQ15)="-","",INDEX(C_Pavement!$I$5:$I$204,$AQ15)),IF($AS15="","",INDEX(E_Rules!$H$5:$H$9,$AS15))))
A16: 11 | B16: 500 | C16: 0+500 | D16: =IFERROR(LOOKUP(2,1/((A_Corridor!$A$5:$A$204<>"")*(A_Corridor!$A$5:$A$204<=$B16)*(A_Corridor!$B$5:$B$204>$B16)*(A_Corridor!$C$5:$C$204<>"")),IF(UPPER(A_Corridor!$C$5:$C$204)="Y",1,"")),"") | E16: =IFERROR(LOOKUP(2,1/((A_Corridor!$A$5:$A$204<>"")*(A_Corridor!$A$5:$A$204<=$B16)*(A_Corridor!$B$5:$B$204>$B16)*(A_Corridor!$D$5:$D$204<>"")),IF(A_Corridor!$D$5:$D$204="-","",UPPER(A_Corridor!$D$5:$D$204))),"") | F16: =IFERROR(LOOKUP(2,1/((A_Corridor!$A$5:$A$204<>"")*(A_Corridor!$A$5:$A$204<=$B16)*(A_Corridor!$B$5:$B$204>$B16)*(A_Corridor!$E$5:$E$204<>"")),IF(A_Corridor!$E$5:$E$204="-","",1)),"") | G16: =IFERROR(LOOKUP(2,1/((A_Corridor!$A$5:$A$204<>"")*(A_Corridor!$A$5:$A$204<=$B16)*(A_Corridor!$B$5:$B$204>$B16)*(A_Corridor!$E$5:$E$204<>"")),IF(A_Corridor!$E$5:$E$204="-","",A_Corridor!$E$5:$E$204)),"") | H16: =IFERROR(LOOKUP(2,1/((D_Points!$A$5:$A$204<>"")*(D_Points!$A$5:$A$204>=$B16)*(D_Points!$A$5:$A$204<$B16+P_Interval)*(UPPER(TRIM(D_Points!$B$5:$B$204))="GULLY")*(D_Points!$H$5:$H$204<>"")),D_Points!$H$5:$H$204),"") | I16: =IFERROR(LOOKUP(2,1/((A_Corridor!$A$5:$A$204<>"")*(A_Corridor!$A$5:$A$204<=$B16)*(A_Corridor!$B$5:$B$204>$B16)*(A_Corridor!$F$5:$F$204<>"")),IF(A_Corridor!$F$5:$F$204="-","",1)),"") | J16: =IFERROR(LOOKUP(2,1/((A_Corridor!$A$5:$A$204<>"")*(A_Corridor!$A$5:$A$204<=$B16)*(A_Corridor!$B$5:$B$204>$B16)*(A_Corridor!$F$5:$F$204<>"")),IF(A_Corridor!$F$5:$F$204="-","",A_Corridor!$F$5:$F$204)),"") | K16: =IFERROR(LOOKUP(2,1/((A_Corridor!$A$5:$A$204<>"")*(A_Corridor!$A$5:$A$204<=$B16)*(A_Corridor!$B$5:$B$204>$B16)*(A_Corridor!$G$5:$G$204<>"")),IF(A_Corridor!$G$5:$G$204="-","",A_Corridor!$G$5:$G$204)),"") | L16: =IFERROR(LOOKUP(2,1/((A_Corridor!$A$5:$A$204<>"")*(A_Corridor!$A$5:$A$204<=$B16)*(A_Corridor!$B$5:$B$204>$B16)*(A_Corridor!$H$5:$H$204<>"")),IF(A_Corridor!$H$5:$H$204="-","",1)),"") | M16: =IFERROR(LOOKUP(2,1/((A_Corridor!$A$5:$A$204<>"")*(A_Corridor!$A$5:$A$204<=$B16)*(A_Corridor!$B$5:$B$204>$B16)*(A_Corridor!$H$5:$H$204<>"")),IF(A_Corridor!$H$5:$H$204="-","",A_Corridor!$H$5:$H$204)),"") | N16: =IFERROR(LOOKUP(2,1/((A_Corridor!$A$5:$A$204<>"")*(A_Corridor!$A$5:$A$204<=$B16)*(A_Corridor!$B$5:$B$204>$B16)*(A_Corridor!$I$5:$I$204<>"")),IF(A_Corridor!$I$5:$I$204="-","",A_Corridor!$I$5:$I$204)),"") | O16: =IFERROR(LOOKUP(2,1/((D_Points!$A$5:$A$204<>"")*(D_Points!$A$5:$A$204>=$B16)*(D_Points!$A$5:$A$204<$B16+P_Interval)*(UPPER(TRIM(D_Points!$B$5:$B$204))="PITCHING")*(D_Points!$H$5:$H$204<>"")),D_Points!$H$5:$H$204),"") | P16: =IFERROR(LOOKUP(2,1/((B_Drainage!$A$5:$A$204<>"")*(B_Drainage!$A$5:$A$204<=$B16)*(B_Drainage!$B$5:$B$204>$B16)*(B_Drainage!$C$5:$C$204<>"")),IF(B_Drainage!$C$5:$C$204="-","",UPPER(B_Drainage!$C$5:$C$204))),"") | Q16: =IFERROR(LOOKUP(2,1/((B_Drainage!$A$5:$A$204<>"")*(B_Drainage!$A$5:$A$204<=$B16)*(B_Drainage!$B$5:$B$204>$B16)*(B_Drainage!$D$5:$D$204<>"")),IF(B_Drainage!$D$5:$D$204="-","",UPPER(B_Drainage!$D$5:$D$204))),"") | R16: =IFERROR(LOOKUP(2,1/((D_Points!$A$5:$A$204<>"")*(D_Points!$A$5:$A$204>=$B16)*(D_Points!$A$5:$A$204<$B16+P_Interval)*(RIGHT(UPPER(TRIM(D_Points!$B$5:$B$204)),8)="_CULVERT")),IF(LEFT(UPPER(TRIM(D_Points!$B$5:$B$204)),2)="EX",1,IF(LEFT(UPPER(TRIM(D_Points!$B$5:$B$204)),2)="PR",2,3))),"") | S16: =IFERROR(LOOKUP(2,1/((D_Points!$A$5:$A$204<>"")*(D_Points!$A$5:$A$204>=$B16)*(D_Points!$A$5:$A$204<$B16+P_Interval)*(RIGHT(UPPER(TRIM(D_Points!$B$5:$B$204)),7)="_BRIDGE")),IF(LEFT(UPPER(TRIM(D_Points!$B$5:$B$204)),2)="EX",1,IF(LEFT(UPPER(TRIM(D_Points!$B$5:$B$204)),2)="PR",2,2))),"") | T16: =IFERROR(LOOKUP(2,1/((B_Drainage!$A$5:$A$204<>"")*(B_Drainage!$A$5:$A$204<=$B16)*(B_Drainage!$B$5:$B$204>$B16)*(B_Drainage!$E$5:$E$204<>"")),IF(B_Drainage!$E$5:$E$204="-","",1)),"") | U16: =IFERROR(LOOKUP(2,1/((B_Drainage!$A$5:$A$204<>"")*(B_Drainage!$A$5:$A$204<=$B16)*(B_Drainage!$B$5:$B$204>$B16)*(B_Drainage!$E$5:$E$204<>"")),IF(B_Drainage!$E$5:$E$204="-","",B_Drainage!$E$5:$E$204)),"") | V16: =IFERROR(LOOKUP(2,1/((B_Drainage!$A$5:$A$204<>"")*(B_Drainage!$A$5:$A$204<=$B16)*(B_Drainage!$B$5:$B$204>$B16)*(B_Drainage!$F$5:$F$204<>"")),IF(B_Drainage!$F$5:$F$204="-","",1)),"") | W16: =IFERROR(LOOKUP(2,1/((B_Drainage!$A$5:$A$204<>"")*(B_Drainage!$A$5:$A$204<=$B16)*(B_Drainage!$B$5:$B$204>$B16)*(B_Drainage!$F$5:$F$204<>"")),IF(B_Drainage!$F$5:$F$204="-","",B_Drainage!$F$5:$F$204)),"") | X16: =IFERROR(LOOKUP(2,1/((B_Drainage!$A$5:$A$204<>"")*(B_Drainage!$A$5:$A$204<=$B16)*(B_Drainage!$B$5:$B$204>$B16)*(B_Drainage!$G$5:$G$204<>"")),IF(UPPER(B_Drainage!$G$5:$G$204)="Y",1,"")),"") | Y16: =IFERROR(LOOKUP(2,1/((B_Drainage!$A$5:$A$204<>"")*(B_Drainage!$A$5:$A$204<=$B16)*(B_Drainage!$B$5:$B$204>$B16)*(B_Drainage!$H$5:$H$204<>"")),IF(UPPER(B_Drainage!$H$5:$H$204)="Y",1,"")),"") | Z16: =IFERROR(LOOKUP(2,1/((B_Drainage!$A$5:$A$204<>"")*(B_Drainage!$A$5:$A$204<=$B16)*(B_Drainage!$B$5:$B$204>$B16)*(B_Drainage!$I$5:$I$204<>"")),IF(UPPER(B_Drainage!$I$5:$I$204)="Y",1,"")),"") | AA16: =IFERROR(LOOKUP(2,1/((B_Drainage!$A$5:$A$204<>"")*(B_Drainage!$A$5:$A$204<=$B16)*(B_Drainage!$B$5:$B$204>$B16)*(B_Drainage!$J$5:$J$204<>"")),IF(UPPER(B_Drainage!$J$5:$J$204)="Y",1,"")),"") | AB16: =IFERROR(LOOKUP(2,1/((B_Drainage!$A$5:$A$204<>"")*(B_Drainage!$A$5:$A$204<=$B16)*(B_Drainage!$B$5:$B$204>$B16)*(B_Drainage!$K$5:$K$204<>"")),IF(B_Drainage!$K$5:$K$204="-","",B_Drainage!$K$5:$K$204)),"") | AC16: =IFERROR(LOOKUP(2,1/((B_Drainage!$A$5:$A$204<>"")*(B_Drainage!$A$5:$A$204<=$B16)*(B_Drainage!$B$5:$B$204>$B16)*(B_Drainage!$L$5:$L$204<>"")),IF(B_Drainage!$L$5:$L$204="-","",B_Drainage!$L$5:$L$204)),"") | AD16: =IFERROR(LOOKUP(2,1/((D_Points!$A$5:$A$204<>"")*(D_Points!$A$5:$A$204>=$B16)*(D_Points!$A$5:$A$204<$B16+P_Interval)*(UPPER(TRIM(D_Points!$B$5:$B$204))="TURNOUT_L")*(D_Points!$H$5:$H$204<>"")),D_Points!$H$5:$H$204),"") | AE16: =IFERROR(LOOKUP(2,1/((D_Points!$A$5:$A$204<>"")*(D_Points!$A$5:$A$204>=$B16)*(D_Points!$A$5:$A$204<$B16+P_Interval)*(UPPER(TRIM(D_Points!$B$5:$B$204))="TURNOUT_R")*(D_Points!$H$5:$H$204<>"")),D_Points!$H$5:$H$204),"") | AF16: =IFERROR(LOOKUP(2,1/((B_Drainage!$A$5:$A$204<>"")*(B_Drainage!$A$5:$A$204<=$B16)*(B_Drainage!$B$5:$B$204>$B16)*(B_Drainage!$M$5:$M$204<>"")),IF(UPPER(B_Drainage!$M$5:$M$204)="Y",1,"")),"") | AG16: =IFERROR(LOOKUP(2,1/((B_Drainage!$A$5:$A$204<>"")*(B_Drainage!$A$5:$A$204<=$B16)*(B_Drainage!$B$5:$B$204>$B16)*(B_Drainage!$N$5:$N$204<>"")),IF(UPPER(B_Drainage!$N$5:$N$204)="Y",1,"")),"") | AH16: =IF($AT16="BLADE",1,"") | AI16: =IF($AT16="RESHAPE",1,"") | AJ16: =IF($AT16="SCARIFY",1,"") | AK16: =$AU16 | AL16: =$AV16 | AM16: =IF(OR(UPPER($AW16)="Y",$AW16=1),1,"") | AN16: =IF(OR(UPPER($AX16)="Y",$AX16=1),1,"") | AO16: =IF(OR(UPPER($AY16)="Y",$AY16=1),1,"") | AQ16: =IFERROR(LOOKUP(2,1/((C_Pavement!$A$5:$A$204<>"")*(C_Pavement!$A$5:$A$204<=$B16)*(C_Pavement!$B$5:$B$204>$B16)*(C_Pavement!$C$5:$C$204<>"")),ROW(C_Pavement!$C$5:$C$204)-4),"") | AR16: =IF($AQ16="","",UPPER(TRIM(INDEX(C_Pavement!$C$5:$C$204,$AQ16)))) | AS16: =IF($AR16="","",IFERROR(MATCH($AR16,E_Rules!$A$5:$A$9,0),"")) | AT16: =IF($AQ16="","",IF(INDEX(C_Pavement!$D$5:$D$204,$AQ16)<>"",UPPER(TRIM(INDEX(C_Pavement!$D$5:$D$204,$AQ16))),IF($AS16="","",INDEX(E_Rules!$C$5:$C$9,$AS16)))) | AU16: =IF($AQ16="","",IF(INDEX(C_Pavement!$E$5:$E$204,$AQ16)<>"",IF(INDEX(C_Pavement!$E$5:$E$204,$AQ16)="-","",INDEX(C_Pavement!$E$5:$E$204,$AQ16)),IF($AS16="","",INDEX(E_Rules!$D$5:$D$9,$AS16)))) | AV16: =IF($AQ16="","",IF(INDEX(C_Pavement!$F$5:$F$204,$AQ16)<>"",IF(INDEX(C_Pavement!$F$5:$F$204,$AQ16)="-","",INDEX(C_Pavement!$F$5:$F$204,$AQ16)),IF($AS16="","",INDEX(E_Rules!$E$5:$E$9,$AS16)))) | AW16: =IF($AQ16="","",IF(INDEX(C_Pavement!$G$5:$G$204,$AQ16)<>"",IF(INDEX(C_Pavement!$G$5:$G$204,$AQ16)="-","",INDEX(C_Pavement!$G$5:$G$204,$AQ16)),IF($AS16="","",INDEX(E_Rules!$F$5:$F$9,$AS16)))) | AX16: =IF($AQ16="","",IF(INDEX(C_Pavement!$H$5:$H$204,$AQ16)<>"",IF(INDEX(C_Pavement!$H$5:$H$204,$AQ16)="-","",INDEX(C_Pavement!$H$5:$H$204,$AQ16)),IF($AS16="","",INDEX(E_Rules!$G$5:$G$9,$AS16)))) | AY16: =IF($AQ16="","",IF(INDEX(C_Pavement!$I$5:$I$204,$AQ16)<>"",IF(INDEX(C_Pavement!$I$5:$I$204,$AQ16)="-","",INDEX(C_Pavement!$I$5:$I$204,$AQ16)),IF($AS16="","",INDEX(E_Rules!$H$5:$H$9,$AS16))))
A17: 12 | B17: 550 | C17: 0+550 | D17: =IFERROR(LOOKUP(2,1/((A_Corridor!$A$5:$A$204<>"")*(A_Corridor!$A$5:$A$204<=$B17)*(A_Corridor!$B$5:$B$204>$B17)*(A_Corridor!$C$5:$C$204<>"")),IF(UPPER(A_Corridor!$C$5:$C$204)="Y",1,"")),"") | E17: =IFERROR(LOOKUP(2,1/((A_Corridor!$A$5:$A$204<>"")*(A_Corridor!$A$5:$A$204<=$B17)*(A_Corridor!$B$5:$B$204>$B17)*(A_Corridor!$D$5:$D$204<>"")),IF(A_Corridor!$D$5:$D$204="-","",UPPER(A_Corridor!$D$5:$D$204))),"") | F17: =IFERROR(LOOKUP(2,1/((A_Corridor!$A$5:$A$204<>"")*(A_Corridor!$A$5:$A$204<=$B17)*(A_Corridor!$B$5:$B$204>$B17)*(A_Corridor!$E$5:$E$204<>"")),IF(A_Corridor!$E$5:$E$204="-","",1)),"") | G17: =IFERROR(LOOKUP(2,1/((A_Corridor!$A$5:$A$204<>"")*(A_Corridor!$A$5:$A$204<=$B17)*(A_Corridor!$B$5:$B$204>$B17)*(A_Corridor!$E$5:$E$204<>"")),IF(A_Corridor!$E$5:$E$204="-","",A_Corridor!$E$5:$E$204)),"") | H17: =IFERROR(LOOKUP(2,1/((D_Points!$A$5:$A$204<>"")*(D_Points!$A$5:$A$204>=$B17)*(D_Points!$A$5:$A$204<$B17+P_Interval)*(UPPER(TRIM(D_Points!$B$5:$B$204))="GULLY")*(D_Points!$H$5:$H$204<>"")),D_Points!$H$5:$H$204),"") | I17: =IFERROR(LOOKUP(2,1/((A_Corridor!$A$5:$A$204<>"")*(A_Corridor!$A$5:$A$204<=$B17)*(A_Corridor!$B$5:$B$204>$B17)*(A_Corridor!$F$5:$F$204<>"")),IF(A_Corridor!$F$5:$F$204="-","",1)),"") | J17: =IFERROR(LOOKUP(2,1/((A_Corridor!$A$5:$A$204<>"")*(A_Corridor!$A$5:$A$204<=$B17)*(A_Corridor!$B$5:$B$204>$B17)*(A_Corridor!$F$5:$F$204<>"")),IF(A_Corridor!$F$5:$F$204="-","",A_Corridor!$F$5:$F$204)),"") | K17: =IFERROR(LOOKUP(2,1/((A_Corridor!$A$5:$A$204<>"")*(A_Corridor!$A$5:$A$204<=$B17)*(A_Corridor!$B$5:$B$204>$B17)*(A_Corridor!$G$5:$G$204<>"")),IF(A_Corridor!$G$5:$G$204="-","",A_Corridor!$G$5:$G$204)),"") | L17: =IFERROR(LOOKUP(2,1/((A_Corridor!$A$5:$A$204<>"")*(A_Corridor!$A$5:$A$204<=$B17)*(A_Corridor!$B$5:$B$204>$B17)*(A_Corridor!$H$5:$H$204<>"")),IF(A_Corridor!$H$5:$H$204="-","",1)),"") | M17: =IFERROR(LOOKUP(2,1/((A_Corridor!$A$5:$A$204<>"")*(A_Corridor!$A$5:$A$204<=$B17)*(A_Corridor!$B$5:$B$204>$B17)*(A_Corridor!$H$5:$H$204<>"")),IF(A_Corridor!$H$5:$H$204="-","",A_Corridor!$H$5:$H$204)),"") | N17: =IFERROR(LOOKUP(2,1/((A_Corridor!$A$5:$A$204<>"")*(A_Corridor!$A$5:$A$204<=$B17)*(A_Corridor!$B$5:$B$204>$B17)*(A_Corridor!$I$5:$I$204<>"")),IF(A_Corridor!$I$5:$I$204="-","",A_Corridor!$I$5:$I$204)),"") | O17: =IFERROR(LOOKUP(2,1/((D_Points!$A$5:$A$204<>"")*(D_Points!$A$5:$A$204>=$B17)*(D_Points!$A$5:$A$204<$B17+P_Interval)*(UPPER(TRIM(D_Points!$B$5:$B$204))="PITCHING")*(D_Points!$H$5:$H$204<>"")),D_Points!$H$5:$H$204),"") | P17: =IFERROR(LOOKUP(2,1/((B_Drainage!$A$5:$A$204<>"")*(B_Drainage!$A$5:$A$204<=$B17)*(B_Drainage!$B$5:$B$204>$B17)*(B_Drainage!$C$5:$C$204<>"")),IF(B_Drainage!$C$5:$C$204="-","",UPPER(B_Drainage!$C$5:$C$204))),"") | Q17: =IFERROR(LOOKUP(2,1/((B_Drainage!$A$5:$A$204<>"")*(B_Drainage!$A$5:$A$204<=$B17)*(B_Drainage!$B$5:$B$204>$B17)*(B_Drainage!$D$5:$D$204<>"")),IF(B_Drainage!$D$5:$D$204="-","",UPPER(B_Drainage!$D$5:$D$204))),"") | R17: =IFERROR(LOOKUP(2,1/((D_Points!$A$5:$A$204<>"")*(D_Points!$A$5:$A$204>=$B17)*(D_Points!$A$5:$A$204<$B17+P_Interval)*(RIGHT(UPPER(TRIM(D_Points!$B$5:$B$204)),8)="_CULVERT")),IF(LEFT(UPPER(TRIM(D_Points!$B$5:$B$204)),2)="EX",1,IF(LEFT(UPPER(TRIM(D_Points!$B$5:$B$204)),2)="PR",2,3))),"") | S17: =IFERROR(LOOKUP(2,1/((D_Points!$A$5:$A$204<>"")*(D_Points!$A$5:$A$204>=$B17)*(D_Points!$A$5:$A$204<$B17+P_Interval)*(RIGHT(UPPER(TRIM(D_Points!$B$5:$B$204)),7)="_BRIDGE")),IF(LEFT(UPPER(TRIM(D_Points!$B$5:$B$204)),2)="EX",1,IF(LEFT(UPPER(TRIM(D_Points!$B$5:$B$204)),2)="PR",2,2))),"") | T17: =IFERROR(LOOKUP(2,1/((B_Drainage!$A$5:$A$204<>"")*(B_Drainage!$A$5:$A$204<=$B17)*(B_Drainage!$B$5:$B$204>$B17)*(B_Drainage!$E$5:$E$204<>"")),IF(B_Drainage!$E$5:$E$204="-","",1)),"") | U17: =IFERROR(LOOKUP(2,1/((B_Drainage!$A$5:$A$204<>"")*(B_Drainage!$A$5:$A$204<=$B17)*(B_Drainage!$B$5:$B$204>$B17)*(B_Drainage!$E$5:$E$204<>"")),IF(B_Drainage!$E$5:$E$204="-","",B_Drainage!$E$5:$E$204)),"") | V17: =IFERROR(LOOKUP(2,1/((B_Drainage!$A$5:$A$204<>"")*(B_Drainage!$A$5:$A$204<=$B17)*(B_Drainage!$B$5:$B$204>$B17)*(B_Drainage!$F$5:$F$204<>"")),IF(B_Drainage!$F$5:$F$204="-","",1)),"") | W17: =IFERROR(LOOKUP(2,1/((B_Drainage!$A$5:$A$204<>"")*(B_Drainage!$A$5:$A$204<=$B17)*(B_Drainage!$B$5:$B$204>$B17)*(B_Drainage!$F$5:$F$204<>"")),IF(B_Drainage!$F$5:$F$204="-","",B_Drainage!$F$5:$F$204)),"") | X17: =IFERROR(LOOKUP(2,1/((B_Drainage!$A$5:$A$204<>"")*(B_Drainage!$A$5:$A$204<=$B17)*(B_Drainage!$B$5:$B$204>$B17)*(B_Drainage!$G$5:$G$204<>"")),IF(UPPER(B_Drainage!$G$5:$G$204)="Y",1,"")),"") | Y17: =IFERROR(LOOKUP(2,1/((B_Drainage!$A$5:$A$204<>"")*(B_Drainage!$A$5:$A$204<=$B17)*(B_Drainage!$B$5:$B$204>$B17)*(B_Drainage!$H$5:$H$204<>"")),IF(UPPER(B_Drainage!$H$5:$H$204)="Y",1,"")),"") | Z17: =IFERROR(LOOKUP(2,1/((B_Drainage!$A$5:$A$204<>"")*(B_Drainage!$A$5:$A$204<=$B17)*(B_Drainage!$B$5:$B$204>$B17)*(B_Drainage!$I$5:$I$204<>"")),IF(UPPER(B_Drainage!$I$5:$I$204)="Y",1,"")),"") | AA17: =IFERROR(LOOKUP(2,1/((B_Drainage!$A$5:$A$204<>"")*(B_Drainage!$A$5:$A$204<=$B17)*(B_Drainage!$B$5:$B$204>$B17)*(B_Drainage!$J$5:$J$204<>"")),IF(UPPER(B_Drainage!$J$5:$J$204)="Y",1,"")),"") | AB17: =IFERROR(LOOKUP(2,1/((B_Drainage!$A$5:$A$204<>"")*(B_Drainage!$A$5:$A$204<=$B17)*(B_Drainage!$B$5:$B$204>$B17)*(B_Drainage!$K$5:$K$204<>"")),IF(B_Drainage!$K$5:$K$204="-","",B_Drainage!$K$5:$K$204)),"") | AC17: =IFERROR(LOOKUP(2,1/((B_Drainage!$A$5:$A$204<>"")*(B_Drainage!$A$5:$A$204<=$B17)*(B_Drainage!$B$5:$B$204>$B17)*(B_Drainage!$L$5:$L$204<>"")),IF(B_Drainage!$L$5:$L$204="-","",B_Drainage!$L$5:$L$204)),"") | AD17: =IFERROR(LOOKUP(2,1/((D_Points!$A$5:$A$204<>"")*(D_Points!$A$5:$A$204>=$B17)*(D_Points!$A$5:$A$204<$B17+P_Interval)*(UPPER(TRIM(D_Points!$B$5:$B$204))="TURNOUT_L")*(D_Points!$H$5:$H$204<>"")),D_Points!$H$5:$H$204),"") | AE17: =IFERROR(LOOKUP(2,1/((D_Points!$A$5:$A$204<>"")*(D_Points!$A$5:$A$204>=$B17)*(D_Points!$A$5:$A$204<$B17+P_Interval)*(UPPER(TRIM(D_Points!$B$5:$B$204))="TURNOUT_R")*(D_Points!$H$5:$H$204<>"")),D_Points!$H$5:$H$204),"") | AF17: =IFERROR(LOOKUP(2,1/((B_Drainage!$A$5:$A$204<>"")*(B_Drainage!$A$5:$A$204<=$B17)*(B_Drainage!$B$5:$B$204>$B17)*(B_Drainage!$M$5:$M$204<>"")),IF(UPPER(B_Drainage!$M$5:$M$204)="Y",1,"")),"") | AG17: =IFERROR(LOOKUP(2,1/((B_Drainage!$A$5:$A$204<>"")*(B_Drainage!$A$5:$A$204<=$B17)*(B_Drainage!$B$5:$B$204>$B17)*(B_Drainage!$N$5:$N$204<>"")),IF(UPPER(B_Drainage!$N$5:$N$204)="Y",1,"")),"") | AH17: =IF($AT17="BLADE",1,"") | AI17: =IF($AT17="RESHAPE",1,"") | AJ17: =IF($AT17="SCARIFY",1,"") | AK17: =$AU17 | AL17: =$AV17 | AM17: =IF(OR(UPPER($AW17)="Y",$AW17=1),1,"") | AN17: =IF(OR(UPPER($AX17)="Y",$AX17=1),1,"") | AO17: =IF(OR(UPPER($AY17)="Y",$AY17=1),1,"") | AQ17: =IFERROR(LOOKUP(2,1/((C_Pavement!$A$5:$A$204<>"")*(C_Pavement!$A$5:$A$204<=$B17)*(C_Pavement!$B$5:$B$204>$B17)*(C_Pavement!$C$5:$C$204<>"")),ROW(C_Pavement!$C$5:$C$204)-4),"") | AR17: =IF($AQ17="","",UPPER(TRIM(INDEX(C_Pavement!$C$5:$C$204,$AQ17)))) | AS17: =IF($AR17="","",IFERROR(MATCH($AR17,E_Rules!$A$5:$A$9,0),"")) | AT17: =IF($AQ17="","",IF(INDEX(C_Pavement!$D$5:$D$204,$AQ17)<>"",UPPER(TRIM(INDEX(C_Pavement!$D$5:$D$204,$AQ17))),IF($AS17="","",INDEX(E_Rules!$C$5:$C$9,$AS17)))) | AU17: =IF($AQ17="","",IF(INDEX(C_Pavement!$E$5:$E$204,$AQ17)<>"",IF(INDEX(C_Pavement!$E$5:$E$204,$AQ17)="-","",INDEX(C_Pavement!$E$5:$E$204,$AQ17)),IF($AS17="","",INDEX(E_Rules!$D$5:$D$9,$AS17)))) | AV17: =IF($AQ17="","",IF(INDEX(C_Pavement!$F$5:$F$204,$AQ17)<>"",IF(INDEX(C_Pavement!$F$5:$F$204,$AQ17)="-","",INDEX(C_Pavement!$F$5:$F$204,$AQ17)),IF($AS17="","",INDEX(E_Rules!$E$5:$E$9,$AS17)))) | AW17: =IF($AQ17="","",IF(INDEX(C_Pavement!$G$5:$G$204,$AQ17)<>"",IF(INDEX(C_Pavement!$G$5:$G$204,$AQ17)="-","",INDEX(C_Pavement!$G$5:$G$204,$AQ17)),IF($AS17="","",INDEX(E_Rules!$F$5:$F$9,$AS17)))) | AX17: =IF($AQ17="","",IF(INDEX(C_Pavement!$H$5:$H$204,$AQ17)<>"",IF(INDEX(C_Pavement!$H$5:$H$204,$AQ17)="-","",INDEX(C_Pavement!$H$5:$H$204,$AQ17)),IF($AS17="","",INDEX(E_Rules!$G$5:$G$9,$AS17)))) | AY17: =IF($AQ17="","",IF(INDEX(C_Pavement!$I$5:$I$204,$AQ17)<>"",IF(INDEX(C_Pavement!$I$5:$I$204,$AQ17)="-","",INDEX(C_Pavement!$I$5:$I$204,$AQ17)),IF($AS17="","",INDEX(E_Rules!$H$5:$H$9,$AS17))))
... A1005: 1000 | B1005: 49950 | C1005: 49+950 | D1005: =IFERROR(LOOKUP(2,1/((A_Corridor!$A$5:$A$204<>"")*(A_Corridor!$A$5:$A$204<=$B1005)*(A_Corridor!$B$5:$B$204>$B1005)*(A_Corridor!$C$5:$C$204<>"")),IF(UPPER(A_Corridor!$C$5:$C$204)="Y",1,"")),"") | E1005: =IFERROR(LOOKUP(2,1/((A_Corridor!$A$5:$A$204<>"")*(A_Corridor!$A$5:$A$204<=$B1005)*(A_Corridor!$B$5:$B$204>$B1005)*(A_Corridor!$D$5:$D$204<>"")),IF(A_Corridor!$D$5:$D$204="-","",UPPER(A_Corridor!$D$5:$D$204))),"") | F1005: =IFERROR(LOOKUP(2,1/((A_Corridor!$A$5:$A$204<>"")*(A_Corridor!$A$5:$A$204<=$B1005)*(A_Corridor!$B$5:$B$204>$B1005)*(A_Corridor!$E$5:$E$204<>"")),IF(A_Corridor!$E$5:$E$204="-","",1)),"") | G1005: =IFERROR(LOOKUP(2,1/((A_Corridor!$A$5:$A$204<>"")*(A_Corridor!$A$5:$A$204<=$B1005)*(A_Corridor!$B$5:$B$204>$B1005)*(A_Corridor!$E$5:$E$204<>"")),IF(A_Corridor!$E$5:$E$204="-","",A_Corridor!$E$5:$E$204)),"") | H1005: =IFERROR(LOOKUP(2,1/((D_Points!$A$5:$A$204<>"")*(D_Points!$A$5:$A$204>=$B1005)*(D_Points!$A$5:$A$204<$B1005+P_Interval)*(UPPER(TRIM(D_Points!$B$5:$B$204))="GULLY")*(D_Points!$H$5:$H$204<>"")),D_Points!$H$5:$H$204),"") | I1005: =IFERROR(LOOKUP(2,1/((A_Corridor!$A$5:$A$204<>"")*(A_Corridor!$A$5:$A$204<=$B1005)*(A_Corridor!$B$5:$B$204>$B1005)*(A_Corridor!$F$5:$F$204<>"")),IF(A_Corridor!$F$5:$F$204="-","",1)),"") | J1005: =IFERROR(LOOKUP(2,1/((A_Corridor!$A$5:$A$204<>"")*(A_Corridor!$A$5:$A$204<=$B1005)*(A_Corridor!$B$5:$B$204>$B1005)*(A_Corridor!$F$5:$F$204<>"")),IF(A_Corridor!$F$5:$F$204="-","",A_Corridor!$F$5:$F$204)),"") | K1005: =IFERROR(LOOKUP(2,1/((A_Corridor!$A$5:$A$204<>"")*(A_Corridor!$A$5:$A$204<=$B1005)*(A_Corridor!$B$5:$B$204>$B1005)*(A_Corridor!$G$5:$G$204<>"")),IF(A_Corridor!$G$5:$G$204="-","",A_Corridor!$G$5:$G$204)),"") | L1005: =IFERROR(LOOKUP(2,1/((A_Corridor!$A$5:$A$204<>"")*(A_Corridor!$A$5:$A$204<=$B1005)*(A_Corridor!$B$5:$B$204>$B1005)*(A_Corridor!$H$5:$H$204<>"")),IF(A_Corridor!$H$5:$H$204="-","",1)),"") | M1005: =IFERROR(LOOKUP(2,1/((A_Corridor!$A$5:$A$204<>"")*(A_Corridor!$A$5:$A$204<=$B1005)*(A_Corridor!$B$5:$B$204>$B1005)*(A_Corridor!$H$5:$H$204<>"")),IF(A_Corridor!$H$5:$H$204="-","",A_Corridor!$H$5:$H$204)),"") | N1005: =IFERROR(LOOKUP(2,1/((A_Corridor!$A$5:$A$204<>"")*(A_Corridor!$A$5:$A$204<=$B1005)*(A_Corridor!$B$5:$B$204>$B1005)*(A_Corridor!$I$5:$I$204<>"")),IF(A_Corridor!$I$5:$I$204="-","",A_Corridor!$I$5:$I$204)),"") | O1005: =IFERROR(LOOKUP(2,1/((D_Points!$A$5:$A$204<>"")*(D_Points!$A$5:$A$204>=$B1005)*(D_Points!$A$5:$A$204<$B1005+P_Interval)*(UPPER(TRIM(D_Points!$B$5:$B$204))="PITCHING")*(D_Points!$H$5:$H$204<>"")),D_Points!$H$5:$H$204),"") | P1005: =IFERROR(LOOKUP(2,1/((B_Drainage!$A$5:$A$204<>"")*(B_Drainage!$A$5:$A$204<=$B1005)*(B_Drainage!$B$5:$B$204>$B1005)*(B_Drainage!$C$5:$C$204<>"")),IF(B_Drainage!$C$5:$C$204="-","",UPPER(B_Drainage!$C$5:$C$204))),"") | Q1005: =IFERROR(LOOKUP(2,1/((B_Drainage!$A$5:$A$204<>"")*(B_Drainage!$A$5:$A$204<=$B1005)*(B_Drainage!$B$5:$B$204>$B1005)*(B_Drainage!$D$5:$D$204<>"")),IF(B_Drainage!$D$5:$D$204="-","",UPPER(B_Drainage!$D$5:$D$204))),"") | R1005: =IFERROR(LOOKUP(2,1/((D_Points!$A$5:$A$204<>"")*(D_Points!$A$5:$A$204>=$B1005)*(D_Points!$A$5:$A$204<$B1005+P_Interval)*(RIGHT(UPPER(TRIM(D_Points!$B$5:$B$204)),8)="_CULVERT")),IF(LEFT(UPPER(TRIM(D_Points!$B$5:$B$204)),2)="EX",1,IF(LEFT(UPPER(TRIM(D_Points!$B$5:$B$204)),2)="PR",2,3))),"") | S1005: =IFERROR(LOOKUP(2,1/((D_Points!$A$5:$A$204<>"")*(D_Points!$A$5:$A$204>=$B1005)*(D_Points!$A$5:$A$204<$B1005+P_Interval)*(RIGHT(UPPER(TRIM(D_Points!$B$5:$B$204)),7)="_BRIDGE")),IF(LEFT(UPPER(TRIM(D_Points!$B$5:$B$204)),2)="EX",1,IF(LEFT(UPPER(TRIM(D_Points!$B$5:$B$204)),2)="PR",2,2))),"") | T1005: =IFERROR(LOOKUP(2,1/((B_Drainage!$A$5:$A$204<>"")*(B_Drainage!$A$5:$A$204<=$B1005)*(B_Drainage!$B$5:$B$204>$B1005)*(B_Drainage!$E$5:$E$204<>"")),IF(B_Drainage!$E$5:$E$204="-","",1)),"") | U1005: =IFERROR(LOOKUP(2,1/((B_Drainage!$A$5:$A$204<>"")*(B_Drainage!$A$5:$A$204<=$B1005)*(B_Drainage!$B$5:$B$204>$B1005)*(B_Drainage!$E$5:$E$204<>"")),IF(B_Drainage!$E$5:$E$204="-","",B_Drainage!$E$5:$E$204)),"") | V1005: =IFERROR(LOOKUP(2,1/((B_Drainage!$A$5:$A$204<>"")*(B_Drainage!$A$5:$A$204<=$B1005)*(B_Drainage!$B$5:$B$204>$B1005)*(B_Drainage!$F$5:$F$204<>"")),IF(B_Drainage!$F$5:$F$204="-","",1)),"") | W1005: =IFERROR(LOOKUP(2,1/((B_Drainage!$A$5:$A$204<>"")*(B_Drainage!$A$5:$A$204<=$B1005)*(B_Drainage!$B$5:$B$204>$B1005)*(B_Drainage!$F$5:$F$204<>"")),IF(B_Drainage!$F$5:$F$204="-","",B_Drainage!$F$5:$F$204)),"") | X1005: =IFERROR(LOOKUP(2,1/((B_Drainage!$A$5:$A$204<>"")*(B_Drainage!$A$5:$A$204<=$B1005)*(B_Drainage!$B$5:$B$204>$B1005)*(B_Drainage!$G$5:$G$204<>"")),IF(UPPER(B_Drainage!$G$5:$G$204)="Y",1,"")),"") | Y1005: =IFERROR(LOOKUP(2,1/((B_Drainage!$A$5:$A$204<>"")*(B_Drainage!$A$5:$A$204<=$B1005)*(B_Drainage!$B$5:$B$204>$B1005)*(B_Drainage!$H$5:$H$204<>"")),IF(UPPER(B_Drainage!$H$5:$H$204)="Y",1,"")),"") | Z1005: =IFERROR(LOOKUP(2,1/((B_Drainage!$A$5:$A$204<>"")*(B_Drainage!$A$5:$A$204<=$B1005)*(B_Drainage!$B$5:$B$204>$B1005)*(B_Drainage!$I$5:$I$204<>"")),IF(UPPER(B_Drainage!$I$5:$I$204)="Y",1,"")),"") | AA1005: =IFERROR(LOOKUP(2,1/((B_Drainage!$A$5:$A$204<>"")*(B_Drainage!$A$5:$A$204<=$B1005)*(B_Drainage!$B$5:$B$204>$B1005)*(B_Drainage!$J$5:$J$204<>"")),IF(UPPER(B_Drainage!$J$5:$J$204)="Y",1,"")),"") | AB1005: =IFERROR(LOOKUP(2,1/((B_Drainage!$A$5:$A$204<>"")*(B_Drainage!$A$5:$A$204<=$B1005)*(B_Drainage!$B$5:$B$204>$B1005)*(B_Drainage!$K$5:$K$204<>"")),IF(B_Drainage!$K$5:$K$204="-","",B_Drainage!$K$5:$K$204)),"") | AC1005: =IFERROR(LOOKUP(2,1/((B_Drainage!$A$5:$A$204<>"")*(B_Drainage!$A$5:$A$204<=$B1005)*(B_Drainage!$B$5:$B$204>$B1005)*(B_Drainage!$L$5:$L$204<>"")),IF(B_Drainage!$L$5:$L$204="-","",B_Drainage!$L$5:$L$204)),"") | AD1005: =IFERROR(LOOKUP(2,1/((D_Points!$A$5:$A$204<>"")*(D_Points!$A$5:$A$204>=$B1005)*(D_Points!$A$5:$A$204<$B1005+P_Interval)*(UPPER(TRIM(D_Points!$B$5:$B$204))="TURNOUT_L")*(D_Points!$H$5:$H$204<>"")),D_Points!$H$5:$H$204),"") | AE1005: =IFERROR(LOOKUP(2,1/((D_Points!$A$5:$A$204<>"")*(D_Points!$A$5:$A$204>=$B1005)*(D_Points!$A$5:$A$204<$B1005+P_Interval)*(UPPER(TRIM(D_Points!$B$5:$B$204))="TURNOUT_R")*(D_Points!$H$5:$H$204<>"")),D_Points!$H$5:$H$204),"") | AF1005: =IFERROR(LOOKUP(2,1/((B_Drainage!$A$5:$A$204<>"")*(B_Drainage!$A$5:$A$204<=$B1005)*(B_Drainage!$B$5:$B$204>$B1005)*(B_Drainage!$M$5:$M$204<>"")),IF(UPPER(B_Drainage!$M$5:$M$204)="Y",1,"")),"") | AG1005: =IFERROR(LOOKUP(2,1/((B_Drainage!$A$5:$A$204<>"")*(B_Drainage!$A$5:$A$204<=$B1005)*(B_Drainage!$B$5:$B$204>$B1005)*(B_Drainage!$N$5:$N$204<>"")),IF(UPPER(B_Drainage!$N$5:$N$204)="Y",1,"")),"") | AH1005: =IF($AT1005="BLADE",1,"") | AI1005: =IF($AT1005="RESHAPE",1,"") | AJ1005: =IF($AT1005="SCARIFY",1,"") | AK1005: =$AU1005 | AL1005: =$AV1005 | AM1005: =IF(OR(UPPER($AW1005)="Y",$AW1005=1),1,"") | AN1005: =IF(OR(UPPER($AX1005)="Y",$AX1005=1),1,"") | AO1005: =IF(OR(UPPER($AY1005)="Y",$AY1005=1),1,"") | AQ1005: =IFERROR(LOOKUP(2,1/((C_Pavement!$A$5:$A$204<>"")*(C_Pavement!$A$5:$A$204<=$B1005)*(C_Pavement!$B$5:$B$204>$B1005)*(C_Pavement!$C$5:$C$204<>"")),ROW(C_Pavement!$C$5:$C$204)-4),"") | AR1005: =IF($AQ1005="","",UPPER(TRIM(INDEX(C_Pavement!$C$5:$C$204,$AQ1005)))) | AS1005: =IF($AR1005="","",IFERROR(MATCH($AR1005,E_Rules!$A$5:$A$9,0),"")) | AT1005: =IF($AQ1005="","",IF(INDEX(C_Pavement!$D$5:$D$204,$AQ1005)<>"",UPPER(TRIM(INDEX(C_Pavement!$D$5:$D$204,$AQ1005))),IF($AS1005="","",INDEX(E_Rules!$C$5:$C$9,$AS1005)))) | AU1005: =IF($AQ1005="","",IF(INDEX(C_Pavement!$E$5:$E$204,$AQ1005)<>"",IF(INDEX(C_Pavement!$E$5:$E$204,$AQ1005)="-","",INDEX(C_Pavement!$E$5:$E$204,$AQ1005)),IF($AS1005="","",INDEX(E_Rules!$D$5:$D$9,$AS1005)))) | AV1005: =IF($AQ1005="","",IF(INDEX(C_Pavement!$F$5:$F$204,$AQ1005)<>"",IF(INDEX(C_Pavement!$F$5:$F$204,$AQ1005)="-","",INDEX(C_Pavement!$F$5:$F$204,$AQ1005)),IF($AS1005="","",INDEX(E_Rules!$E$5:$E$9,$AS1005)))) | AW1005: =IF($AQ1005="","",IF(INDEX(C_Pavement!$G$5:$G$204,$AQ1005)<>"",IF(INDEX(C_Pavement!$G$5:$G$204,$AQ1005)="-","",INDEX(C_Pavement!$G$5:$G$204,$AQ1005)),IF($AS1005="","",INDEX(E_Rules!$F$5:$F$9,$AS1005)))) | AX1005: =IF($AQ1005="","",IF(INDEX(C_Pavement!$H$5:$H$204,$AQ1005)<>"",IF(INDEX(C_Pavement!$H$5:$H$204,$AQ1005)="-","",INDEX(C_Pavement!$H$5:$H$204,$AQ1005)),IF($AS1005="","",INDEX(E_Rules!$G$5:$G$9,$AS1005)))) | AY1005: =IF($AQ1005="","",IF(INDEX(C_Pavement!$I$5:$I$204,$AQ1005)<>"",IF(INDEX(C_Pavement!$I$5:$I$204,$AQ1005)="-","",INDEX(C_Pavement!$I$5:$I$204,$AQ1005)),IF($AS1005="","",INDEX(E_Rules!$H$5:$H$9,$AS1005))))

Sheet 02_Culverts
A1: CULVERT SCHEDULE
A2: One row per culvert, built automatically from the PR_CULVERT rows on Form D — do not type here. Family and Size together form the key the engines match on, so a U-culvert can never be picked up as a pipe culvert.
A4: ID | B4: Chainage | C4: Family | D4: Cells | E4: Size | F4: Length (m) | G4: Orientation | H4: Inlet structure | I4: Outlet structure | J4: Key | K4: Remarks | M4: (Form D row)
A5: =IF($C5="","",1) | B5: =IF($M5="","",TEXT(INT(INDEX(D_Points!$A$5:$A$204,$M5)/1000),"0")&"+"&TEXT(MOD(INDEX(D_Points!$A$5:$A$204,$M5),1000),"000")) | C5: =IF($M5="","",UPPER(TRIM(INDEX(D_Points!$C$5:$C$204,$M5)))) | D5: =IF($M5="","",INDEX(D_Points!$D$5:$D$204,$M5)) | E5: =IF($M5="","",UPPER(TRIM(INDEX(D_Points!$E$5:$E$204,$M5)))) | F5: =IF($M5="","",INDEX(D_Points!$F$5:$F$204,$M5)) | G5: =IF($M5="","",""&IF(INDEX(D_Points!$G$5:$G$204,$M5)="","Right Angle",TRIM(INDEX(D_Points!$G$5:$G$204,$M5)))) | H5: =IF($C5="","",IF($G5="Skew","Catchpit inlet","Normal endwalls")) | I5: =IF($C5="","","Normal outlet") | J5: =IF($C5="","",$C5&"|"&$D5&"/"&UPPER(TRIM($E5))) | K5: =IF($M5="","",INDEX(D_Points!$I$5:$I$204,$M5)) | M5: =IFERROR(MATCH(1,D_Points!$K$5:$K$204,0),"")
A6: =IF($C6="","",2) | B6: =IF($M6="","",TEXT(INT(INDEX(D_Points!$A$5:$A$204,$M6)/1000),"0")&"+"&TEXT(MOD(INDEX(D_Points!$A$5:$A$204,$M6),1000),"000")) | C6: =IF($M6="","",UPPER(TRIM(INDEX(D_Points!$C$5:$C$204,$M6)))) | D6: =IF($M6="","",INDEX(D_Points!$D$5:$D$204,$M6)) | E6: =IF($M6="","",UPPER(TRIM(INDEX(D_Points!$E$5:$E$204,$M6)))) | F6: =IF($M6="","",INDEX(D_Points!$F$5:$F$204,$M6)) | G6: =IF($M6="","",""&IF(INDEX(D_Points!$G$5:$G$204,$M6)="","Right Angle",TRIM(INDEX(D_Points!$G$5:$G$204,$M6)))) | H6: =IF($C6="","",IF($G6="Skew","Catchpit inlet","Normal endwalls")) | I6: =IF($C6="","","Normal outlet") | J6: =IF($C6="","",$C6&"|"&$D6&"/"&UPPER(TRIM($E6))) | K6: =IF($M6="","",INDEX(D_Points!$I$5:$I$204,$M6)) | M6: =IFERROR(MATCH(2,D_Points!$K$5:$K$204,0),"")
A7: =IF($C7="","",3) | B7: =IF($M7="","",TEXT(INT(INDEX(D_Points!$A$5:$A$204,$M7)/1000),"0")&"+"&TEXT(MOD(INDEX(D_Points!$A$5:$A$204,$M7),1000),"000")) | C7: =IF($M7="","",UPPER(TRIM(INDEX(D_Points!$C$5:$C$204,$M7)))) | D7: =IF($M7="","",INDEX(D_Points!$D$5:$D$204,$M7)) | E7: =IF($M7="","",UPPER(TRIM(INDEX(D_Points!$E$5:$E$204,$M7)))) | F7: =IF($M7="","",INDEX(D_Points!$F$5:$F$204,$M7)) | G7: =IF($M7="","",""&IF(INDEX(D_Points!$G$5:$G$204,$M7)="","Right Angle",TRIM(INDEX(D_Points!$G$5:$G$204,$M7)))) | H7: =IF($C7="","",IF($G7="Skew","Catchpit inlet","Normal endwalls")) | I7: =IF($C7="","","Normal outlet") | J7: =IF($C7="","",$C7&"|"&$D7&"/"&UPPER(TRIM($E7))) | K7: =IF($M7="","",INDEX(D_Points!$I$5:$I$204,$M7)) | M7: =IFERROR(MATCH(3,D_Points!$K$5:$K$204,0),"")
A8: =IF($C8="","",4) | B8: =IF($M8="","",TEXT(INT(INDEX(D_Points!$A$5:$A$204,$M8)/1000),"0")&"+"&TEXT(MOD(INDEX(D_Points!$A$5:$A$204,$M8),1000),"000")) | C8: =IF($M8="","",UPPER(TRIM(INDEX(D_Points!$C$5:$C$204,$M8)))) | D8: =IF($M8="","",INDEX(D_Points!$D$5:$D$204,$M8)) | E8: =IF($M8="","",UPPER(TRIM(INDEX(D_Points!$E$5:$E$204,$M8)))) | F8: =IF($M8="","",INDEX(D_Points!$F$5:$F$204,$M8)) | G8: =IF($M8="","",""&IF(INDEX(D_Points!$G$5:$G$204,$M8)="","Right Angle",TRIM(INDEX(D_Points!$G$5:$G$204,$M8)))) | H8: =IF($C8="","",IF($G8="Skew","Catchpit inlet","Normal endwalls")) | I8: =IF($C8="","","Normal outlet") | J8: =IF($C8="","",$C8&"|"&$D8&"/"&UPPER(TRIM($E8))) | K8: =IF($M8="","",INDEX(D_Points!$I$5:$I$204,$M8)) | M8: =IFERROR(MATCH(4,D_Points!$K$5:$K$204,0),"")
A9: =IF($C9="","",5) | B9: =IF($M9="","",TEXT(INT(INDEX(D_Points!$A$5:$A$204,$M9)/1000),"0")&"+"&TEXT(MOD(INDEX(D_Points!$A$5:$A$204,$M9),1000),"000")) | C9: =IF($M9="","",UPPER(TRIM(INDEX(D_Points!$C$5:$C$204,$M9)))) | D9: =IF($M9="","",INDEX(D_Points!$D$5:$D$204,$M9)) | E9: =IF($M9="","",UPPER(TRIM(INDEX(D_Points!$E$5:$E$204,$M9)))) | F9: =IF($M9="","",INDEX(D_Points!$F$5:$F$204,$M9)) | G9: =IF($M9="","",""&IF(INDEX(D_Points!$G$5:$G$204,$M9)="","Right Angle",TRIM(INDEX(D_Points!$G$5:$G$204,$M9)))) | H9: =IF($C9="","",IF($G9="Skew","Catchpit inlet","Normal endwalls")) | I9: =IF($C9="","","Normal outlet") | J9: =IF($C9="","",$C9&"|"&$D9&"/"&UPPER(TRIM($E9))) | K9: =IF($M9="","",INDEX(D_Points!$I$5:$I$204,$M9)) | M9: =IFERROR(MATCH(5,D_Points!$K$5:$K$204,0),"")
A10: =IF($C10="","",6) | B10: =IF($M10="","",TEXT(INT(INDEX(D_Points!$A$5:$A$204,$M10)/1000),"0")&"+"&TEXT(MOD(INDEX(D_Points!$A$5:$A$204,$M10),1000),"000")) | C10: =IF($M10="","",UPPER(TRIM(INDEX(D_Points!$C$5:$C$204,$M10)))) | D10: =IF($M10="","",INDEX(D_Points!$D$5:$D$204,$M10)) | E10: =IF($M10="","",UPPER(TRIM(INDEX(D_Points!$E$5:$E$204,$M10)))) | F10: =IF($M10="","",INDEX(D_Points!$F$5:$F$204,$M10)) | G10: =IF($M10="","",""&IF(INDEX(D_Points!$G$5:$G$204,$M10)="","Right Angle",TRIM(INDEX(D_Points!$G$5:$G$204,$M10)))) | H10: =IF($C10="","",IF($G10="Skew","Catchpit inlet","Normal endwalls")) | I10: =IF($C10="","","Normal outlet") | J10: =IF($C10="","",$C10&"|"&$D10&"/"&UPPER(TRIM($E10))) | K10: =IF($M10="","",INDEX(D_Points!$I$5:$I$204,$M10)) | M10: =IFERROR(MATCH(6,D_Points!$K$5:$K$204,0),"")
A11: =IF($C11="","",7) | B11: =IF($M11="","",TEXT(INT(INDEX(D_Points!$A$5:$A$204,$M11)/1000),"0")&"+"&TEXT(MOD(INDEX(D_Points!$A$5:$A$204,$M11),1000),"000")) | C11: =IF($M11="","",UPPER(TRIM(INDEX(D_Points!$C$5:$C$204,$M11)))) | D11: =IF($M11="","",INDEX(D_Points!$D$5:$D$204,$M11)) | E11: =IF($M11="","",UPPER(TRIM(INDEX(D_Points!$E$5:$E$204,$M11)))) | F11: =IF($M11="","",INDEX(D_Points!$F$5:$F$204,$M11)) | G11: =IF($M11="","",""&IF(INDEX(D_Points!$G$5:$G$204,$M11)="","Right Angle",TRIM(INDEX(D_Points!$G$5:$G$204,$M11)))) | H11: =IF($C11="","",IF($G11="Skew","Catchpit inlet","Normal endwalls")) | I11: =IF($C11="","","Normal outlet") | J11: =IF($C11="","",$C11&"|"&$D11&"/"&UPPER(TRIM($E11))) | K11: =IF($M11="","",INDEX(D_Points!$I$5:$I$204,$M11)) | M11: =IFERROR(MATCH(7,D_Points!$K$5:$K$204,0),"")
A12: =IF($C12="","",8) | B12: =IF($M12="","",TEXT(INT(INDEX(D_Points!$A$5:$A$204,$M12)/1000),"0")&"+"&TEXT(MOD(INDEX(D_Points!$A$5:$A$204,$M12),1000),"000")) | C12: =IF($M12="","",UPPER(TRIM(INDEX(D_Points!$C$5:$C$204,$M12)))) | D12: =IF($M12="","",INDEX(D_Points!$D$5:$D$204,$M12)) | E12: =IF($M12="","",UPPER(TRIM(INDEX(D_Points!$E$5:$E$204,$M12)))) | F12: =IF($M12="","",INDEX(D_Points!$F$5:$F$204,$M12)) | G12: =IF($M12="","",""&IF(INDEX(D_Points!$G$5:$G$204,$M12)="","Right Angle",TRIM(INDEX(D_Points!$G$5:$G$204,$M12)))) | H12: =IF($C12="","",IF($G12="Skew","Catchpit inlet","Normal endwalls")) | I12: =IF($C12="","","Normal outlet") | J12: =IF($C12="","",$C12&"|"&$D12&"/"&UPPER(TRIM($E12))) | K12: =IF($M12="","",INDEX(D_Points!$I$5:$I$204,$M12)) | M12: =IFERROR(MATCH(8,D_Points!$K$5:$K$204,0),"")
A13: =IF($C13="","",9) | B13: =IF($M13="","",TEXT(INT(INDEX(D_Points!$A$5:$A$204,$M13)/1000),"0")&"+"&TEXT(MOD(INDEX(D_Points!$A$5:$A$204,$M13),1000),"000")) | C13: =IF($M13="","",UPPER(TRIM(INDEX(D_Points!$C$5:$C$204,$M13)))) | D13: =IF($M13="","",INDEX(D_Points!$D$5:$D$204,$M13)) | E13: =IF($M13="","",UPPER(TRIM(INDEX(D_Points!$E$5:$E$204,$M13)))) | F13: =IF($M13="","",INDEX(D_Points!$F$5:$F$204,$M13)) | G13: =IF($M13="","",""&IF(INDEX(D_Points!$G$5:$G$204,$M13)="","Right Angle",TRIM(INDEX(D_Points!$G$5:$G$204,$M13)))) | H13: =IF($C13="","",IF($G13="Skew","Catchpit inlet","Normal endwalls")) | I13: =IF($C13="","","Normal outlet") | J13: =IF($C13="","",$C13&"|"&$D13&"/"&UPPER(TRIM($E13))) | K13: =IF($M13="","",INDEX(D_Points!$I$5:$I$204,$M13)) | M13: =IFERROR(MATCH(9,D_Points!$K$5:$K$204,0),"")
A14: =IF($C14="","",10) | B14: =IF($M14="","",TEXT(INT(INDEX(D_Points!$A$5:$A$204,$M14)/1000),"0")&"+"&TEXT(MOD(INDEX(D_Points!$A$5:$A$204,$M14),1000),"000")) | C14: =IF($M14="","",UPPER(TRIM(INDEX(D_Points!$C$5:$C$204,$M14)))) | D14: =IF($M14="","",INDEX(D_Points!$D$5:$D$204,$M14)) | E14: =IF($M14="","",UPPER(TRIM(INDEX(D_Points!$E$5:$E$204,$M14)))) | F14: =IF($M14="","",INDEX(D_Points!$F$5:$F$204,$M14)) | G14: =IF($M14="","",""&IF(INDEX(D_Points!$G$5:$G$204,$M14)="","Right Angle",TRIM(INDEX(D_Points!$G$5:$G$204,$M14)))) | H14: =IF($C14="","",IF($G14="Skew","Catchpit inlet","Normal endwalls")) | I14: =IF($C14="","","Normal outlet") | J14: =IF($C14="","",$C14&"|"&$D14&"/"&UPPER(TRIM($E14))) | K14: =IF($M14="","",INDEX(D_Points!$I$5:$I$204,$M14)) | M14: =IFERROR(MATCH(10,D_Points!$K$5:$K$204,0),"")
A15: =IF($C15="","",11) | B15: =IF($M15="","",TEXT(INT(INDEX(D_Points!$A$5:$A$204,$M15)/1000),"0")&"+"&TEXT(MOD(INDEX(D_Points!$A$5:$A$204,$M15),1000),"000")) | C15: =IF($M15="","",UPPER(TRIM(INDEX(D_Points!$C$5:$C$204,$M15)))) | D15: =IF($M15="","",INDEX(D_Points!$D$5:$D$204,$M15)) | E15: =IF($M15="","",UPPER(TRIM(INDEX(D_Points!$E$5:$E$204,$M15)))) | F15: =IF($M15="","",INDEX(D_Points!$F$5:$F$204,$M15)) | G15: =IF($M15="","",""&IF(INDEX(D_Points!$G$5:$G$204,$M15)="","Right Angle",TRIM(INDEX(D_Points!$G$5:$G$204,$M15)))) | H15: =IF($C15="","",IF($G15="Skew","Catchpit inlet","Normal endwalls")) | I15: =IF($C15="","","Normal outlet") | J15: =IF($C15="","",$C15&"|"&$D15&"/"&UPPER(TRIM($E15))) | K15: =IF($M15="","",INDEX(D_Points!$I$5:$I$204,$M15)) | M15: =IFERROR(MATCH(11,D_Points!$K$5:$K$204,0),"")
A16: =IF($C16="","",12) | B16: =IF($M16="","",TEXT(INT(INDEX(D_Points!$A$5:$A$204,$M16)/1000),"0")&"+"&TEXT(MOD(INDEX(D_Points!$A$5:$A$204,$M16),1000),"000")) | C16: =IF($M16="","",UPPER(TRIM(INDEX(D_Points!$C$5:$C$204,$M16)))) | D16: =IF($M16="","",INDEX(D_Points!$D$5:$D$204,$M16)) | E16: =IF($M16="","",UPPER(TRIM(INDEX(D_Points!$E$5:$E$204,$M16)))) | F16: =IF($M16="","",INDEX(D_Points!$F$5:$F$204,$M16)) | G16: =IF($M16="","",""&IF(INDEX(D_Points!$G$5:$G$204,$M16)="","Right Angle",TRIM(INDEX(D_Points!$G$5:$G$204,$M16)))) | H16: =IF($C16="","",IF($G16="Skew","Catchpit inlet","Normal endwalls")) | I16: =IF($C16="","","Normal outlet") | J16: =IF($C16="","",$C16&"|"&$D16&"/"&UPPER(TRIM($E16))) | K16: =IF($M16="","",INDEX(D_Points!$I$5:$I$204,$M16)) | M16: =IFERROR(MATCH(12,D_Points!$K$5:$K$204,0),"")
A17: =IF($C17="","",13) | B17: =IF($M17="","",TEXT(INT(INDEX(D_Points!$A$5:$A$204,$M17)/1000),"0")&"+"&TEXT(MOD(INDEX(D_Points!$A$5:$A$204,$M17),1000),"000")) | C17: =IF($M17="","",UPPER(TRIM(INDEX(D_Points!$C$5:$C$204,$M17)))) | D17: =IF($M17="","",INDEX(D_Points!$D$5:$D$204,$M17)) | E17: =IF($M17="","",UPPER(TRIM(INDEX(D_Points!$E$5:$E$204,$M17)))) | F17: =IF($M17="","",INDEX(D_Points!$F$5:$F$204,$M17)) | G17: =IF($M17="","",""&IF(INDEX(D_Points!$G$5:$G$204,$M17)="","Right Angle",TRIM(INDEX(D_Points!$G$5:$G$204,$M17)))) | H17: =IF($C17="","",IF($G17="Skew","Catchpit inlet","Normal endwalls")) | I17: =IF($C17="","","Normal outlet") | J17: =IF($C17="","",$C17&"|"&$D17&"/"&UPPER(TRIM($E17))) | K17: =IF($M17="","",INDEX(D_Points!$I$5:$I$204,$M17)) | M17: =IFERROR(MATCH(13,D_Points!$K$5:$K$204,0),"")
A18: =IF($C18="","",14) | B18: =IF($M18="","",TEXT(INT(INDEX(D_Points!$A$5:$A$204,$M18)/1000),"0")&"+"&TEXT(MOD(INDEX(D_Points!$A$5:$A$204,$M18),1000),"000")) | C18: =IF($M18="","",UPPER(TRIM(INDEX(D_Points!$C$5:$C$204,$M18)))) | D18: =IF($M18="","",INDEX(D_Points!$D$5:$D$204,$M18)) | E18: =IF($M18="","",UPPER(TRIM(INDEX(D_Points!$E$5:$E$204,$M18)))) | F18: =IF($M18="","",INDEX(D_Points!$F$5:$F$204,$M18)) | G18: =IF($M18="","",""&IF(INDEX(D_Points!$G$5:$G$204,$M18)="","Right Angle",TRIM(INDEX(D_Points!$G$5:$G$204,$M18)))) | H18: =IF($C18="","",IF($G18="Skew","Catchpit inlet","Normal endwalls")) | I18: =IF($C18="","","Normal outlet") | J18: =IF($C18="","",$C18&"|"&$D18&"/"&UPPER(TRIM($E18))) | K18: =IF($M18="","",INDEX(D_Points!$I$5:$I$204,$M18)) | M18: =IFERROR(MATCH(14,D_Points!$K$5:$K$204,0),"")
A19: =IF($C19="","",15) | B19: =IF($M19="","",TEXT(INT(INDEX(D_Points!$A$5:$A$204,$M19)/1000),"0")&"+"&TEXT(MOD(INDEX(D_Points!$A$5:$A$204,$M19),1000),"000")) | C19: =IF($M19="","",UPPER(TRIM(INDEX(D_Points!$C$5:$C$204,$M19)))) | D19: =IF($M19="","",INDEX(D_Points!$D$5:$D$204,$M19)) | E19: =IF($M19="","",UPPER(TRIM(INDEX(D_Points!$E$5:$E$204,$M19)))) | F19: =IF($M19="","",INDEX(D_Points!$F$5:$F$204,$M19)) | G19: =IF($M19="","",""&IF(INDEX(D_Points!$G$5:$G$204,$M19)="","Right Angle",TRIM(INDEX(D_Points!$G$5:$G$204,$M19)))) | H19: =IF($C19="","",IF($G19="Skew","Catchpit inlet","Normal endwalls")) | I19: =IF($C19="","","Normal outlet") | J19: =IF($C19="","",$C19&"|"&$D19&"/"&UPPER(TRIM($E19))) | K19: =IF($M19="","",INDEX(D_Points!$I$5:$I$204,$M19)) | M19: =IFERROR(MATCH(15,D_Points!$K$5:$K$204,0),"")
A20: =IF($C20="","",16) | B20: =IF($M20="","",TEXT(INT(INDEX(D_Points!$A$5:$A$204,$M20)/1000),"0")&"+"&TEXT(MOD(INDEX(D_Points!$A$5:$A$204,$M20),1000),"000")) | C20: =IF($M20="","",UPPER(TRIM(INDEX(D_Points!$C$5:$C$204,$M20)))) | D20: =IF($M20="","",INDEX(D_Points!$D$5:$D$204,$M20)) | E20: =IF($M20="","",UPPER(TRIM(INDEX(D_Points!$E$5:$E$204,$M20)))) | F20: =IF($M20="","",INDEX(D_Points!$F$5:$F$204,$M20)) | G20: =IF($M20="","",""&IF(INDEX(D_Points!$G$5:$G$204,$M20)="","Right Angle",TRIM(INDEX(D_Points!$G$5:$G$204,$M20)))) | H20: =IF($C20="","",IF($G20="Skew","Catchpit inlet","Normal endwalls")) | I20: =IF($C20="","","Normal outlet") | J20: =IF($C20="","",$C20&"|"&$D20&"/"&UPPER(TRIM($E20))) | K20: =IF($M20="","",INDEX(D_Points!$I$5:$I$204,$M20)) | M20: =IFERROR(MATCH(16,D_Points!$K$5:$K$204,0),"")
A21: =IF($C21="","",17) | B21: =IF($M21="","",TEXT(INT(INDEX(D_Points!$A$5:$A$204,$M21)/1000),"0")&"+"&TEXT(MOD(INDEX(D_Points!$A$5:$A$204,$M21),1000),"000")) | C21: =IF($M21="","",UPPER(TRIM(INDEX(D_Points!$C$5:$C$204,$M21)))) | D21: =IF($M21="","",INDEX(D_Points!$D$5:$D$204,$M21)) | E21: =IF($M21="","",UPPER(TRIM(INDEX(D_Points!$E$5:$E$204,$M21)))) | F21: =IF($M21="","",INDEX(D_Points!$F$5:$F$204,$M21)) | G21: =IF($M21="","",""&IF(INDEX(D_Points!$G$5:$G$204,$M21)="","Right Angle",TRIM(INDEX(D_Points!$G$5:$G$204,$M21)))) | H21: =IF($C21="","",IF($G21="Skew","Catchpit inlet","Normal endwalls")) | I21: =IF($C21="","","Normal outlet") | J21: =IF($C21="","",$C21&"|"&$D21&"/"&UPPER(TRIM($E21))) | K21: =IF($M21="","",INDEX(D_Points!$I$5:$I$204,$M21)) | M21: =IFERROR(MATCH(17,D_Points!$K$5:$K$204,0),"")
A22: =IF($C22="","",18) | B22: =IF($M22="","",TEXT(INT(INDEX(D_Points!$A$5:$A$204,$M22)/1000),"0")&"+"&TEXT(MOD(INDEX(D_Points!$A$5:$A$204,$M22),1000),"000")) | C22: =IF($M22="","",UPPER(TRIM(INDEX(D_Points!$C$5:$C$204,$M22)))) | D22: =IF($M22="","",INDEX(D_Points!$D$5:$D$204,$M22)) | E22: =IF($M22="","",UPPER(TRIM(INDEX(D_Points!$E$5:$E$204,$M22)))) | F22: =IF($M22="","",INDEX(D_Points!$F$5:$F$204,$M22)) | G22: =IF($M22="","",""&IF(INDEX(D_Points!$G$5:$G$204,$M22)="","Right Angle",TRIM(INDEX(D_Points!$G$5:$G$204,$M22)))) | H22: =IF($C22="","",IF($G22="Skew","Catchpit inlet","Normal endwalls")) | I22: =IF($C22="","","Normal outlet") | J22: =IF($C22="","",$C22&"|"&$D22&"/"&UPPER(TRIM($E22))) | K22: =IF($M22="","",INDEX(D_Points!$I$5:$I$204,$M22)) | M22: =IFERROR(MATCH(18,D_Points!$K$5:$K$204,0),"")
A23: =IF($C23="","",19) | B23: =IF($M23="","",TEXT(INT(INDEX(D_Points!$A$5:$A$204,$M23)/1000),"0")&"+"&TEXT(MOD(INDEX(D_Points!$A$5:$A$204,$M23),1000),"000")) | C23: =IF($M23="","",UPPER(TRIM(INDEX(D_Points!$C$5:$C$204,$M23)))) | D23: =IF($M23="","",INDEX(D_Points!$D$5:$D$204,$M23)) | E23: =IF($M23="","",UPPER(TRIM(INDEX(D_Points!$E$5:$E$204,$M23)))) | F23: =IF($M23="","",INDEX(D_Points!$F$5:$F$204,$M23)) | G23: =IF($M23="","",""&IF(INDEX(D_Points!$G$5:$G$204,$M23)="","Right Angle",TRIM(INDEX(D_Points!$G$5:$G$204,$M23)))) | H23: =IF($C23="","",IF($G23="Skew","Catchpit inlet","Normal endwalls")) | I23: =IF($C23="","","Normal outlet") | J23: =IF($C23="","",$C23&"|"&$D23&"/"&UPPER(TRIM($E23))) | K23: =IF($M23="","",INDEX(D_Points!$I$5:$I$204,$M23)) | M23: =IFERROR(MATCH(19,D_Points!$K$5:$K$204,0),"")
A24: =IF($C24="","",20) | B24: =IF($M24="","",TEXT(INT(INDEX(D_Points!$A$5:$A$204,$M24)/1000),"0")&"+"&TEXT(MOD(INDEX(D_Points!$A$5:$A$204,$M24),1000),"000")) | C24: =IF($M24="","",UPPER(TRIM(INDEX(D_Points!$C$5:$C$204,$M24)))) | D24: =IF($M24="","",INDEX(D_Points!$D$5:$D$204,$M24)) | E24: =IF($M24="","",UPPER(TRIM(INDEX(D_Points!$E$5:$E$204,$M24)))) | F24: =IF($M24="","",INDEX(D_Points!$F$5:$F$204,$M24)) | G24: =IF($M24="","",""&IF(INDEX(D_Points!$G$5:$G$204,$M24)="","Right Angle",TRIM(INDEX(D_Points!$G$5:$G$204,$M24)))) | H24: =IF($C24="","",IF($G24="Skew","Catchpit inlet","Normal endwalls")) | I24: =IF($C24="","","Normal outlet") | J24: =IF($C24="","",$C24&"|"&$D24&"/"&UPPER(TRIM($E24))) | K24: =IF($M24="","",INDEX(D_Points!$I$5:$I$204,$M24)) | M24: =IFERROR(MATCH(20,D_Points!$K$5:$K$204,0),"")
A25: =IF($C25="","",21) | B25: =IF($M25="","",TEXT(INT(INDEX(D_Points!$A$5:$A$204,$M25)/1000),"0")&"+"&TEXT(MOD(INDEX(D_Points!$A$5:$A$204,$M25),1000),"000")) | C25: =IF($M25="","",UPPER(TRIM(INDEX(D_Points!$C$5:$C$204,$M25)))) | D25: =IF($M25="","",INDEX(D_Points!$D$5:$D$204,$M25)) | E25: =IF($M25="","",UPPER(TRIM(INDEX(D_Points!$E$5:$E$204,$M25)))) | F25: =IF($M25="","",INDEX(D_Points!$F$5:$F$204,$M25)) | G25: =IF($M25="","",""&IF(INDEX(D_Points!$G$5:$G$204,$M25)="","Right Angle",TRIM(INDEX(D_Points!$G$5:$G$204,$M25)))) | H25: =IF($C25="","",IF($G25="Skew","Catchpit inlet","Normal endwalls")) | I25: =IF($C25="","","Normal outlet") | J25: =IF($C25="","",$C25&"|"&$D25&"/"&UPPER(TRIM($E25))) | K25: =IF($M25="","",INDEX(D_Points!$I$5:$I$204,$M25)) | M25: =IFERROR(MATCH(21,D_Points!$K$5:$K$204,0),"")
A26: =IF($C26="","",22) | B26: =IF($M26="","",TEXT(INT(INDEX(D_Points!$A$5:$A$204,$M26)/1000),"0")&"+"&TEXT(MOD(INDEX(D_Points!$A$5:$A$204,$M26),1000),"000")) | C26: =IF($M26="","",UPPER(TRIM(INDEX(D_Points!$C$5:$C$204,$M26)))) | D26: =IF($M26="","",INDEX(D_Points!$D$5:$D$204,$M26)) | E26: =IF($M26="","",UPPER(TRIM(INDEX(D_Points!$E$5:$E$204,$M26)))) | F26: =IF($M26="","",INDEX(D_Points!$F$5:$F$204,$M26)) | G26: =IF($M26="","",""&IF(INDEX(D_Points!$G$5:$G$204,$M26)="","Right Angle",TRIM(INDEX(D_Points!$G$5:$G$204,$M26)))) | H26: =IF($C26="","",IF($G26="Skew","Catchpit inlet","Normal endwalls")) | I26: =IF($C26="","","Normal outlet") | J26: =IF($C26="","",$C26&"|"&$D26&"/"&UPPER(TRIM($E26))) | K26: =IF($M26="","",INDEX(D_Points!$I$5:$I$204,$M26)) | M26: =IFERROR(MATCH(22,D_Points!$K$5:$K$204,0),"")
A27: =IF($C27="","",23) | B27: =IF($M27="","",TEXT(INT(INDEX(D_Points!$A$5:$A$204,$M27)/1000),"0")&"+"&TEXT(MOD(INDEX(D_Points!$A$5:$A$204,$M27),1000),"000")) | C27: =IF($M27="","",UPPER(TRIM(INDEX(D_Points!$C$5:$C$204,$M27)))) | D27: =IF($M27="","",INDEX(D_Points!$D$5:$D$204,$M27)) | E27: =IF($M27="","",UPPER(TRIM(INDEX(D_Points!$E$5:$E$204,$M27)))) | F27: =IF($M27="","",INDEX(D_Points!$F$5:$F$204,$M27)) | G27: =IF($M27="","",""&IF(INDEX(D_Points!$G$5:$G$204,$M27)="","Right Angle",TRIM(INDEX(D_Points!$G$5:$G$204,$M27)))) | H27: =IF($C27="","",IF($G27="Skew","Catchpit inlet","Normal endwalls")) | I27: =IF($C27="","","Normal outlet") | J27: =IF($C27="","",$C27&"|"&$D27&"/"&UPPER(TRIM($E27))) | K27: =IF($M27="","",INDEX(D_Points!$I$5:$I$204,$M27)) | M27: =IFERROR(MATCH(23,D_Points!$K$5:$K$204,0),"")
A28: =IF($C28="","",24) | B28: =IF($M28="","",TEXT(INT(INDEX(D_Points!$A$5:$A$204,$M28)/1000),"0")&"+"&TEXT(MOD(INDEX(D_Points!$A$5:$A$204,$M28),1000),"000")) | C28: =IF($M28="","",UPPER(TRIM(INDEX(D_Points!$C$5:$C$204,$M28)))) | D28: =IF($M28="","",INDEX(D_Points!$D$5:$D$204,$M28)) | E28: =IF($M28="","",UPPER(TRIM(INDEX(D_Points!$E$5:$E$204,$M28)))) | F28: =IF($M28="","",INDEX(D_Points!$F$5:$F$204,$M28)) | G28: =IF($M28="","",""&IF(INDEX(D_Points!$G$5:$G$204,$M28)="","Right Angle",TRIM(INDEX(D_Points!$G$5:$G$204,$M28)))) | H28: =IF($C28="","",IF($G28="Skew","Catchpit inlet","Normal endwalls")) | I28: =IF($C28="","","Normal outlet") | J28: =IF($C28="","",$C28&"|"&$D28&"/"&UPPER(TRIM($E28))) | K28: =IF($M28="","",INDEX(D_Points!$I$5:$I$204,$M28)) | M28: =IFERROR(MATCH(24,D_Points!$K$5:$K$204,0),"")
A29: =IF($C29="","",25) | B29: =IF($M29="","",TEXT(INT(INDEX(D_Points!$A$5:$A$204,$M29)/1000),"0")&"+"&TEXT(MOD(INDEX(D_Points!$A$5:$A$204,$M29),1000),"000")) | C29: =IF($M29="","",UPPER(TRIM(INDEX(D_Points!$C$5:$C$204,$M29)))) | D29: =IF($M29="","",INDEX(D_Points!$D$5:$D$204,$M29)) | E29: =IF($M29="","",UPPER(TRIM(INDEX(D_Points!$E$5:$E$204,$M29)))) | F29: =IF($M29="","",INDEX(D_Points!$F$5:$F$204,$M29)) | G29: =IF($M29="","",""&IF(INDEX(D_Points!$G$5:$G$204,$M29)="","Right Angle",TRIM(INDEX(D_Points!$G$5:$G$204,$M29)))) | H29: =IF($C29="","",IF($G29="Skew","Catchpit inlet","Normal endwalls")) | I29: =IF($C29="","","Normal outlet") | J29: =IF($C29="","",$C29&"|"&$D29&"/"&UPPER(TRIM($E29))) | K29: =IF($M29="","",INDEX(D_Points!$I$5:$I$204,$M29)) | M29: =IFERROR(MATCH(25,D_Points!$K$5:$K$204,0),"")
A30: =IF($C30="","",26) | B30: =IF($M30="","",TEXT(INT(INDEX(D_Points!$A$5:$A$204,$M30)/1000),"0")&"+"&TEXT(MOD(INDEX(D_Points!$A$5:$A$204,$M30),1000),"000")) | C30: =IF($M30="","",UPPER(TRIM(INDEX(D_Points!$C$5:$C$204,$M30)))) | D30: =IF($M30="","",INDEX(D_Points!$D$5:$D$204,$M30)) | E30: =IF($M30="","",UPPER(TRIM(INDEX(D_Points!$E$5:$E$204,$M30)))) | F30: =IF($M30="","",INDEX(D_Points!$F$5:$F$204,$M30)) | G30: =IF($M30="","",""&IF(INDEX(D_Points!$G$5:$G$204,$M30)="","Right Angle",TRIM(INDEX(D_Points!$G$5:$G$204,$M30)))) | H30: =IF($C30="","",IF($G30="Skew","Catchpit inlet","Normal endwalls")) | I30: =IF($C30="","","Normal outlet") | J30: =IF($C30="","",$C30&"|"&$D30&"/"&UPPER(TRIM($E30))) | K30: =IF($M30="","",INDEX(D_Points!$I$5:$I$204,$M30)) | M30: =IFERROR(MATCH(26,D_Points!$K$5:$K$204,0),"")
A31: =IF($C31="","",27) | B31: =IF($M31="","",TEXT(INT(INDEX(D_Points!$A$5:$A$204,$M31)/1000),"0")&"+"&TEXT(MOD(INDEX(D_Points!$A$5:$A$204,$M31),1000),"000")) | C31: =IF($M31="","",UPPER(TRIM(INDEX(D_Points!$C$5:$C$204,$M31)))) | D31: =IF($M31="","",INDEX(D_Points!$D$5:$D$204,$M31)) | E31: =IF($M31="","",UPPER(TRIM(INDEX(D_Points!$E$5:$E$204,$M31)))) | F31: =IF($M31="","",INDEX(D_Points!$F$5:$F$204,$M31)) | G31: =IF($M31="","",""&IF(INDEX(D_Points!$G$5:$G$204,$M31)="","Right Angle",TRIM(INDEX(D_Points!$G$5:$G$204,$M31)))) | H31: =IF($C31="","",IF($G31="Skew","Catchpit inlet","Normal endwalls")) | I31: =IF($C31="","","Normal outlet") | J31: =IF($C31="","",$C31&"|"&$D31&"/"&UPPER(TRIM($E31))) | K31: =IF($M31="","",INDEX(D_Points!$I$5:$I$204,$M31)) | M31: =IFERROR(MATCH(27,D_Points!$K$5:$K$204,0),"")
A32: =IF($C32="","",28) | B32: =IF($M32="","",TEXT(INT(INDEX(D_Points!$A$5:$A$204,$M32)/1000),"0")&"+"&TEXT(MOD(INDEX(D_Points!$A$5:$A$204,$M32),1000),"000")) | C32: =IF($M32="","",UPPER(TRIM(INDEX(D_Points!$C$5:$C$204,$M32)))) | D32: =IF($M32="","",INDEX(D_Points!$D$5:$D$204,$M32)) | E32: =IF($M32="","",UPPER(TRIM(INDEX(D_Points!$E$5:$E$204,$M32)))) | F32: =IF($M32="","",INDEX(D_Points!$F$5:$F$204,$M32)) | G32: =IF($M32="","",""&IF(INDEX(D_Points!$G$5:$G$204,$M32)="","Right Angle",TRIM(INDEX(D_Points!$G$5:$G$204,$M32)))) | H32: =IF($C32="","",IF($G32="Skew","Catchpit inlet","Normal endwalls")) | I32: =IF($C32="","","Normal outlet") | J32: =IF($C32="","",$C32&"|"&$D32&"/"&UPPER(TRIM($E32))) | K32: =IF($M32="","",INDEX(D_Points!$I$5:$I$204,$M32)) | M32: =IFERROR(MATCH(28,D_Points!$K$5:$K$204,0),"")
A33: =IF($C33="","",29) | B33: =IF($M33="","",TEXT(INT(INDEX(D_Points!$A$5:$A$204,$M33)/1000),"0")&"+"&TEXT(MOD(INDEX(D_Points!$A$5:$A$204,$M33),1000),"000")) | C33: =IF($M33="","",UPPER(TRIM(INDEX(D_Points!$C$5:$C$204,$M33)))) | D33: =IF($M33="","",INDEX(D_Points!$D$5:$D$204,$M33)) | E33: =IF($M33="","",UPPER(TRIM(INDEX(D_Points!$E$5:$E$204,$M33)))) | F33: =IF($M33="","",INDEX(D_Points!$F$5:$F$204,$M33)) | G33: =IF($M33="","",""&IF(INDEX(D_Points!$G$5:$G$204,$M33)="","Right Angle",TRIM(INDEX(D_Points!$G$5:$G$204,$M33)))) | H33: =IF($C33="","",IF($G33="Skew","Catchpit inlet","Normal endwalls")) | I33: =IF($C33="","","Normal outlet") | J33: =IF($C33="","",$C33&"|"&$D33&"/"&UPPER(TRIM($E33))) | K33: =IF($M33="","",INDEX(D_Points!$I$5:$I$204,$M33)) | M33: =IFERROR(MATCH(29,D_Points!$K$5:$K$204,0),"")
A34: =IF($C34="","",30) | B34: =IF($M34="","",TEXT(INT(INDEX(D_Points!$A$5:$A$204,$M34)/1000),"0")&"+"&TEXT(MOD(INDEX(D_Points!$A$5:$A$204,$M34),1000),"000")) | C34: =IF($M34="","",UPPER(TRIM(INDEX(D_Points!$C$5:$C$204,$M34)))) | D34: =IF($M34="","",INDEX(D_Points!$D$5:$D$204,$M34)) | E34: =IF($M34="","",UPPER(TRIM(INDEX(D_Points!$E$5:$E$204,$M34)))) | F34: =IF($M34="","",INDEX(D_Points!$F$5:$F$204,$M34)) | G34: =IF($M34="","",""&IF(INDEX(D_Points!$G$5:$G$204,$M34)="","Right Angle",TRIM(INDEX(D_Points!$G$5:$G$204,$M34)))) | H34: =IF($C34="","",IF($G34="Skew","Catchpit inlet","Normal endwalls")) | I34: =IF($C34="","","Normal outlet") | J34: =IF($C34="","",$C34&"|"&$D34&"/"&UPPER(TRIM($E34))) | K34: =IF($M34="","",INDEX(D_Points!$I$5:$I$204,$M34)) | M34: =IFERROR(MATCH(30,D_Points!$K$5:$K$204,0),"")
A35: =IF($C35="","",31) | B35: =IF($M35="","",TEXT(INT(INDEX(D_Points!$A$5:$A$204,$M35)/1000),"0")&"+"&TEXT(MOD(INDEX(D_Points!$A$5:$A$204,$M35),1000),"000")) | C35: =IF($M35="","",UPPER(TRIM(INDEX(D_Points!$C$5:$C$204,$M35)))) | D35: =IF($M35="","",INDEX(D_Points!$D$5:$D$204,$M35)) | E35: =IF($M35="","",UPPER(TRIM(INDEX(D_Points!$E$5:$E$204,$M35)))) | F35: =IF($M35="","",INDEX(D_Points!$F$5:$F$204,$M35)) | G35: =IF($M35="","",""&IF(INDEX(D_Points!$G$5:$G$204,$M35)="","Right Angle",TRIM(INDEX(D_Points!$G$5:$G$204,$M35)))) | H35: =IF($C35="","",IF($G35="Skew","Catchpit inlet","Normal endwalls")) | I35: =IF($C35="","","Normal outlet") | J35: =IF($C35="","",$C35&"|"&$D35&"/"&UPPER(TRIM($E35))) | K35: =IF($M35="","",INDEX(D_Points!$I$5:$I$204,$M35)) | M35: =IFERROR(MATCH(31,D_Points!$K$5:$K$204,0),"")
A36: =IF($C36="","",32) | B36: =IF($M36="","",TEXT(INT(INDEX(D_Points!$A$5:$A$204,$M36)/1000),"0")&"+"&TEXT(MOD(INDEX(D_Points!$A$5:$A$204,$M36),1000),"000")) | C36: =IF($M36="","",UPPER(TRIM(INDEX(D_Points!$C$5:$C$204,$M36)))) | D36: =IF($M36="","",INDEX(D_Points!$D$5:$D$204,$M36)) | E36: =IF($M36="","",UPPER(TRIM(INDEX(D_Points!$E$5:$E$204,$M36)))) | F36: =IF($M36="","",INDEX(D_Points!$F$5:$F$204,$M36)) | G36: =IF($M36="","",""&IF(INDEX(D_Points!$G$5:$G$204,$M36)="","Right Angle",TRIM(INDEX(D_Points!$G$5:$G$204,$M36)))) | H36: =IF($C36="","",IF($G36="Skew","Catchpit inlet","Normal endwalls")) | I36: =IF($C36="","","Normal outlet") | J36: =IF($C36="","",$C36&"|"&$D36&"/"&UPPER(TRIM($E36))) | K36: =IF($M36="","",INDEX(D_Points!$I$5:$I$204,$M36)) | M36: =IFERROR(MATCH(32,D_Points!$K$5:$K$204,0),"")
A37: =IF($C37="","",33) | B37: =IF($M37="","",TEXT(INT(INDEX(D_Points!$A$5:$A$204,$M37)/1000),"0")&"+"&TEXT(MOD(INDEX(D_Points!$A$5:$A$204,$M37),1000),"000")) | C37: =IF($M37="","",UPPER(TRIM(INDEX(D_Points!$C$5:$C$204,$M37)))) | D37: =IF($M37="","",INDEX(D_Points!$D$5:$D$204,$M37)) | E37: =IF($M37="","",UPPER(TRIM(INDEX(D_Points!$E$5:$E$204,$M37)))) | F37: =IF($M37="","",INDEX(D_Points!$F$5:$F$204,$M37)) | G37: =IF($M37="","",""&IF(INDEX(D_Points!$G$5:$G$204,$M37)="","Right Angle",TRIM(INDEX(D_Points!$G$5:$G$204,$M37)))) | H37: =IF($C37="","",IF($G37="Skew","Catchpit inlet","Normal endwalls")) | I37: =IF($C37="","","Normal outlet") | J37: =IF($C37="","",$C37&"|"&$D37&"/"&UPPER(TRIM($E37))) | K37: =IF($M37="","",INDEX(D_Points!$I$5:$I$204,$M37)) | M37: =IFERROR(MATCH(33,D_Points!$K$5:$K$204,0),"")
A38: =IF($C38="","",34) | B38: =IF($M38="","",TEXT(INT(INDEX(D_Points!$A$5:$A$204,$M38)/1000),"0")&"+"&TEXT(MOD(INDEX(D_Points!$A$5:$A$204,$M38),1000),"000")) | C38: =IF($M38="","",UPPER(TRIM(INDEX(D_Points!$C$5:$C$204,$M38)))) | D38: =IF($M38="","",INDEX(D_Points!$D$5:$D$204,$M38)) | E38: =IF($M38="","",UPPER(TRIM(INDEX(D_Points!$E$5:$E$204,$M38)))) | F38: =IF($M38="","",INDEX(D_Points!$F$5:$F$204,$M38)) | G38: =IF($M38="","",""&IF(INDEX(D_Points!$G$5:$G$204,$M38)="","Right Angle",TRIM(INDEX(D_Points!$G$5:$G$204,$M38)))) | H38: =IF($C38="","",IF($G38="Skew","Catchpit inlet","Normal endwalls")) | I38: =IF($C38="","","Normal outlet") | J38: =IF($C38="","",$C38&"|"&$D38&"/"&UPPER(TRIM($E38))) | K38: =IF($M38="","",INDEX(D_Points!$I$5:$I$204,$M38)) | M38: =IFERROR(MATCH(34,D_Points!$K$5:$K$204,0),"")
A39: =IF($C39="","",35) | B39: =IF($M39="","",TEXT(INT(INDEX(D_Points!$A$5:$A$204,$M39)/1000),"0")&"+"&TEXT(MOD(INDEX(D_Points!$A$5:$A$204,$M39),1000),"000")) | C39: =IF($M39="","",UPPER(TRIM(INDEX(D_Points!$C$5:$C$204,$M39)))) | D39: =IF($M39="","",INDEX(D_Points!$D$5:$D$204,$M39)) | E39: =IF($M39="","",UPPER(TRIM(INDEX(D_Points!$E$5:$E$204,$M39)))) | F39: =IF($M39="","",INDEX(D_Points!$F$5:$F$204,$M39)) | G39: =IF($M39="","",""&IF(INDEX(D_Points!$G$5:$G$204,$M39)="","Right Angle",TRIM(INDEX(D_Points!$G$5:$G$204,$M39)))) | H39: =IF($C39="","",IF($G39="Skew","Catchpit inlet","Normal endwalls")) | I39: =IF($C39="","","Normal outlet") | J39: =IF($C39="","",$C39&"|"&$D39&"/"&UPPER(TRIM($E39))) | K39: =IF($M39="","",INDEX(D_Points!$I$5:$I$204,$M39)) | M39: =IFERROR(MATCH(35,D_Points!$K$5:$K$204,0),"")
A40: =IF($C40="","",36) | B40: =IF($M40="","",TEXT(INT(INDEX(D_Points!$A$5:$A$204,$M40)/1000),"0")&"+"&TEXT(MOD(INDEX(D_Points!$A$5:$A$204,$M40),1000),"000")) | C40: =IF($M40="","",UPPER(TRIM(INDEX(D_Points!$C$5:$C$204,$M40)))) | D40: =IF($M40="","",INDEX(D_Points!$D$5:$D$204,$M40)) | E40: =IF($M40="","",UPPER(TRIM(INDEX(D_Points!$E$5:$E$204,$M40)))) | F40: =IF($M40="","",INDEX(D_Points!$F$5:$F$204,$M40)) | G40: =IF($M40="","",""&IF(INDEX(D_Points!$G$5:$G$204,$M40)="","Right Angle",TRIM(INDEX(D_Points!$G$5:$G$204,$M40)))) | H40: =IF($C40="","",IF($G40="Skew","Catchpit inlet","Normal endwalls")) | I40: =IF($C40="","","Normal outlet") | J40: =IF($C40="","",$C40&"|"&$D40&"/"&UPPER(TRIM($E40))) | K40: =IF($M40="","",INDEX(D_Points!$I$5:$I$204,$M40)) | M40: =IFERROR(MATCH(36,D_Points!$K$5:$K$204,0),"")
A41: =IF($C41="","",37) | B41: =IF($M41="","",TEXT(INT(INDEX(D_Points!$A$5:$A$204,$M41)/1000),"0")&"+"&TEXT(MOD(INDEX(D_Points!$A$5:$A$204,$M41),1000),"000")) | C41: =IF($M41="","",UPPER(TRIM(INDEX(D_Points!$C$5:$C$204,$M41)))) | D41: =IF($M41="","",INDEX(D_Points!$D$5:$D$204,$M41)) | E41: =IF($M41="","",UPPER(TRIM(INDEX(D_Points!$E$5:$E$204,$M41)))) | F41: =IF($M41="","",INDEX(D_Points!$F$5:$F$204,$M41)) | G41: =IF($M41="","",""&IF(INDEX(D_Points!$G$5:$G$204,$M41)="","Right Angle",TRIM(INDEX(D_Points!$G$5:$G$204,$M41)))) | H41: =IF($C41="","",IF($G41="Skew","Catchpit inlet","Normal endwalls")) | I41: =IF($C41="","","Normal outlet") | J41: =IF($C41="","",$C41&"|"&$D41&"/"&UPPER(TRIM($E41))) | K41: =IF($M41="","",INDEX(D_Points!$I$5:$I$204,$M41)) | M41: =IFERROR(MATCH(37,D_Points!$K$5:$K$204,0),"")
A42: =IF($C42="","",38) | B42: =IF($M42="","",TEXT(INT(INDEX(D_Points!$A$5:$A$204,$M42)/1000),"0")&"+"&TEXT(MOD(INDEX(D_Points!$A$5:$A$204,$M42),1000),"000")) | C42: =IF($M42="","",UPPER(TRIM(INDEX(D_Points!$C$5:$C$204,$M42)))) | D42: =IF($M42="","",INDEX(D_Points!$D$5:$D$204,$M42)) | E42: =IF($M42="","",UPPER(TRIM(INDEX(D_Points!$E$5:$E$204,$M42)))) | F42: =IF($M42="","",INDEX(D_Points!$F$5:$F$204,$M42)) | G42: =IF($M42="","",""&IF(INDEX(D_Points!$G$5:$G$204,$M42)="","Right Angle",TRIM(INDEX(D_Points!$G$5:$G$204,$M42)))) | H42: =IF($C42="","",IF($G42="Skew","Catchpit inlet","Normal endwalls")) | I42: =IF($C42="","","Normal outlet") | J42: =IF($C42="","",$C42&"|"&$D42&"/"&UPPER(TRIM($E42))) | K42: =IF($M42="","",INDEX(D_Points!$I$5:$I$204,$M42)) | M42: =IFERROR(MATCH(38,D_Points!$K$5:$K$204,0),"")
A43: =IF($C43="","",39) | B43: =IF($M43="","",TEXT(INT(INDEX(D_Points!$A$5:$A$204,$M43)/1000),"0")&"+"&TEXT(MOD(INDEX(D_Points!$A$5:$A$204,$M43),1000),"000")) | C43: =IF($M43="","",UPPER(TRIM(INDEX(D_Points!$C$5:$C$204,$M43)))) | D43: =IF($M43="","",INDEX(D_Points!$D$5:$D$204,$M43)) | E43: =IF($M43="","",UPPER(TRIM(INDEX(D_Points!$E$5:$E$204,$M43)))) | F43: =IF($M43="","",INDEX(D_Points!$F$5:$F$204,$M43)) | G43: =IF($M43="","",""&IF(INDEX(D_Points!$G$5:$G$204,$M43)="","Right Angle",TRIM(INDEX(D_Points!$G$5:$G$204,$M43)))) | H43: =IF($C43="","",IF($G43="Skew","Catchpit inlet","Normal endwalls")) | I43: =IF($C43="","","Normal outlet") | J43: =IF($C43="","",$C43&"|"&$D43&"/"&UPPER(TRIM($E43))) | K43: =IF($M43="","",INDEX(D_Points!$I$5:$I$204,$M43)) | M43: =IFERROR(MATCH(39,D_Points!$K$5:$K$204,0),"")
A44: =IF($C44="","",40) | B44: =IF($M44="","",TEXT(INT(INDEX(D_Points!$A$5:$A$204,$M44)/1000),"0")&"+"&TEXT(MOD(INDEX(D_Points!$A$5:$A$204,$M44),1000),"000")) | C44: =IF($M44="","",UPPER(TRIM(INDEX(D_Points!$C$5:$C$204,$M44)))) | D44: =IF($M44="","",INDEX(D_Points!$D$5:$D$204,$M44)) | E44: =IF($M44="","",UPPER(TRIM(INDEX(D_Points!$E$5:$E$204,$M44)))) | F44: =IF($M44="","",INDEX(D_Points!$F$5:$F$204,$M44)) | G44: =IF($M44="","",""&IF(INDEX(D_Points!$G$5:$G$204,$M44)="","Right Angle",TRIM(INDEX(D_Points!$G$5:$G$204,$M44)))) | H44: =IF($C44="","",IF($G44="Skew","Catchpit inlet","Normal endwalls")) | I44: =IF($C44="","","Normal outlet") | J44: =IF($C44="","",$C44&"|"&$D44&"/"&UPPER(TRIM($E44))) | K44: =IF($M44="","",INDEX(D_Points!$I$5:$I$204,$M44)) | M44: =IFERROR(MATCH(40,D_Points!$K$5:$K$204,0),"")
A45: =IF($C45="","",41) | B45: =IF($M45="","",TEXT(INT(INDEX(D_Points!$A$5:$A$204,$M45)/1000),"0")&"+"&TEXT(MOD(INDEX(D_Points!$A$5:$A$204,$M45),1000),"000")) | C45: =IF($M45="","",UPPER(TRIM(INDEX(D_Points!$C$5:$C$204,$M45)))) | D45: =IF($M45="","",INDEX(D_Points!$D$5:$D$204,$M45)) | E45: =IF($M45="","",UPPER(TRIM(INDEX(D_Points!$E$5:$E$204,$M45)))) | F45: =IF($M45="","",INDEX(D_Points!$F$5:$F$204,$M45)) | G45: =IF($M45="","",""&IF(INDEX(D_Points!$G$5:$G$204,$M45)="","Right Angle",TRIM(INDEX(D_Points!$G$5:$G$204,$M45)))) | H45: =IF($C45="","",IF($G45="Skew","Catchpit inlet","Normal endwalls")) | I45: =IF($C45="","","Normal outlet") | J45: =IF($C45="","",$C45&"|"&$D45&"/"&UPPER(TRIM($E45))) | K45: =IF($M45="","",INDEX(D_Points!$I$5:$I$204,$M45)) | M45: =IFERROR(MATCH(41,D_Points!$K$5:$K$204,0),"")
A46: =IF($C46="","",42) | B46: =IF($M46="","",TEXT(INT(INDEX(D_Points!$A$5:$A$204,$M46)/1000),"0")&"+"&TEXT(MOD(INDEX(D_Points!$A$5:$A$204,$M46),1000),"000")) | C46: =IF($M46="","",UPPER(TRIM(INDEX(D_Points!$C$5:$C$204,$M46)))) | D46: =IF($M46="","",INDEX(D_Points!$D$5:$D$204,$M46)) | E46: =IF($M46="","",UPPER(TRIM(INDEX(D_Points!$E$5:$E$204,$M46)))) | F46: =IF($M46="","",INDEX(D_Points!$F$5:$F$204,$M46)) | G46: =IF($M46="","",""&IF(INDEX(D_Points!$G$5:$G$204,$M46)="","Right Angle",TRIM(INDEX(D_Points!$G$5:$G$204,$M46)))) | H46: =IF($C46="","",IF($G46="Skew","Catchpit inlet","Normal endwalls")) | I46: =IF($C46="","","Normal outlet") | J46: =IF($C46="","",$C46&"|"&$D46&"/"&UPPER(TRIM($E46))) | K46: =IF($M46="","",INDEX(D_Points!$I$5:$I$204,$M46)) | M46: =IFERROR(MATCH(42,D_Points!$K$5:$K$204,0),"")
A47: =IF($C47="","",43) | B47: =IF($M47="","",TEXT(INT(INDEX(D_Points!$A$5:$A$204,$M47)/1000),"0")&"+"&TEXT(MOD(INDEX(D_Points!$A$5:$A$204,$M47),1000),"000")) | C47: =IF($M47="","",UPPER(TRIM(INDEX(D_Points!$C$5:$C$204,$M47)))) | D47: =IF($M47="","",INDEX(D_Points!$D$5:$D$204,$M47)) | E47: =IF($M47="","",UPPER(TRIM(INDEX(D_Points!$E$5:$E$204,$M47)))) | F47: =IF($M47="","",INDEX(D_Points!$F$5:$F$204,$M47)) | G47: =IF($M47="","",""&IF(INDEX(D_Points!$G$5:$G$204,$M47)="","Right Angle",TRIM(INDEX(D_Points!$G$5:$G$204,$M47)))) | H47: =IF($C47="","",IF($G47="Skew","Catchpit inlet","Normal endwalls")) | I47: =IF($C47="","","Normal outlet") | J47: =IF($C47="","",$C47&"|"&$D47&"/"&UPPER(TRIM($E47))) | K47: =IF($M47="","",INDEX(D_Points!$I$5:$I$204,$M47)) | M47: =IFERROR(MATCH(43,D_Points!$K$5:$K$204,0),"")
A48: =IF($C48="","",44) | B48: =IF($M48="","",TEXT(INT(INDEX(D_Points!$A$5:$A$204,$M48)/1000),"0")&"+"&TEXT(MOD(INDEX(D_Points!$A$5:$A$204,$M48),1000),"000")) | C48: =IF($M48="","",UPPER(TRIM(INDEX(D_Points!$C$5:$C$204,$M48)))) | D48: =IF($M48="","",INDEX(D_Points!$D$5:$D$204,$M48)) | E48: =IF($M48="","",UPPER(TRIM(INDEX(D_Points!$E$5:$E$204,$M48)))) | F48: =IF($M48="","",INDEX(D_Points!$F$5:$F$204,$M48)) | G48: =IF($M48="","",""&IF(INDEX(D_Points!$G$5:$G$204,$M48)="","Right Angle",TRIM(INDEX(D_Points!$G$5:$G$204,$M48)))) | H48: =IF($C48="","",IF($G48="Skew","Catchpit inlet","Normal endwalls")) | I48: =IF($C48="","","Normal outlet") | J48: =IF($C48="","",$C48&"|"&$D48&"/"&UPPER(TRIM($E48))) | K48: =IF($M48="","",INDEX(D_Points!$I$5:$I$204,$M48)) | M48: =IFERROR(MATCH(44,D_Points!$K$5:$K$204,0),"")
A49: =IF($C49="","",45) | B49: =IF($M49="","",TEXT(INT(INDEX(D_Points!$A$5:$A$204,$M49)/1000),"0")&"+"&TEXT(MOD(INDEX(D_Points!$A$5:$A$204,$M49),1000),"000")) | C49: =IF($M49="","",UPPER(TRIM(INDEX(D_Points!$C$5:$C$204,$M49)))) | D49: =IF($M49="","",INDEX(D_Points!$D$5:$D$204,$M49)) | E49: =IF($M49="","",UPPER(TRIM(INDEX(D_Points!$E$5:$E$204,$M49)))) | F49: =IF($M49="","",INDEX(D_Points!$F$5:$F$204,$M49)) | G49: =IF($M49="","",""&IF(INDEX(D_Points!$G$5:$G$204,$M49)="","Right Angle",TRIM(INDEX(D_Points!$G$5:$G$204,$M49)))) | H49: =IF($C49="","",IF($G49="Skew","Catchpit inlet","Normal endwalls")) | I49: =IF($C49="","","Normal outlet") | J49: =IF($C49="","",$C49&"|"&$D49&"/"&UPPER(TRIM($E49))) | K49: =IF($M49="","",INDEX(D_Points!$I$5:$I$204,$M49)) | M49: =IFERROR(MATCH(45,D_Points!$K$5:$K$204,0),"")
A50: =IF($C50="","",46) | B50: =IF($M50="","",TEXT(INT(INDEX(D_Points!$A$5:$A$204,$M50)/1000),"0")&"+"&TEXT(MOD(INDEX(D_Points!$A$5:$A$204,$M50),1000),"000")) | C50: =IF($M50="","",UPPER(TRIM(INDEX(D_Points!$C$5:$C$204,$M50)))) | D50: =IF($M50="","",INDEX(D_Points!$D$5:$D$204,$M50)) | E50: =IF($M50="","",UPPER(TRIM(INDEX(D_Points!$E$5:$E$204,$M50)))) | F50: =IF($M50="","",INDEX(D_Points!$F$5:$F$204,$M50)) | G50: =IF($M50="","",""&IF(INDEX(D_Points!$G$5:$G$204,$M50)="","Right Angle",TRIM(INDEX(D_Points!$G$5:$G$204,$M50)))) | H50: =IF($C50="","",IF($G50="Skew","Catchpit inlet","Normal endwalls")) | I50: =IF($C50="","","Normal outlet") | J50: =IF($C50="","",$C50&"|"&$D50&"/"&UPPER(TRIM($E50))) | K50: =IF($M50="","",INDEX(D_Points!$I$5:$I$204,$M50)) | M50: =IFERROR(MATCH(46,D_Points!$K$5:$K$204,0),"")
A51: =IF($C51="","",47) | B51: =IF($M51="","",TEXT(INT(INDEX(D_Points!$A$5:$A$204,$M51)/1000),"0")&"+"&TEXT(MOD(INDEX(D_Points!$A$5:$A$204,$M51),1000),"000")) | C51: =IF($M51="","",UPPER(TRIM(INDEX(D_Points!$C$5:$C$204,$M51)))) | D51: =IF($M51="","",INDEX(D_Points!$D$5:$D$204,$M51)) | E51: =IF($M51="","",UPPER(TRIM(INDEX(D_Points!$E$5:$E$204,$M51)))) | F51: =IF($M51="","",INDEX(D_Points!$F$5:$F$204,$M51)) | G51: =IF($M51="","",""&IF(INDEX(D_Points!$G$5:$G$204,$M51)="","Right Angle",TRIM(INDEX(D_Points!$G$5:$G$204,$M51)))) | H51: =IF($C51="","",IF($G51="Skew","Catchpit inlet","Normal endwalls")) | I51: =IF($C51="","","Normal outlet") | J51: =IF($C51="","",$C51&"|"&$D51&"/"&UPPER(TRIM($E51))) | K51: =IF($M51="","",INDEX(D_Points!$I$5:$I$204,$M51)) | M51: =IFERROR(MATCH(47,D_Points!$K$5:$K$204,0),"")
A52: =IF($C52="","",48) | B52: =IF($M52="","",TEXT(INT(INDEX(D_Points!$A$5:$A$204,$M52)/1000),"0")&"+"&TEXT(MOD(INDEX(D_Points!$A$5:$A$204,$M52),1000),"000")) | C52: =IF($M52="","",UPPER(TRIM(INDEX(D_Points!$C$5:$C$204,$M52)))) | D52: =IF($M52="","",INDEX(D_Points!$D$5:$D$204,$M52)) | E52: =IF($M52="","",UPPER(TRIM(INDEX(D_Points!$E$5:$E$204,$M52)))) | F52: =IF($M52="","",INDEX(D_Points!$F$5:$F$204,$M52)) | G52: =IF($M52="","",""&IF(INDEX(D_Points!$G$5:$G$204,$M52)="","Right Angle",TRIM(INDEX(D_Points!$G$5:$G$204,$M52)))) | H52: =IF($C52="","",IF($G52="Skew","Catchpit inlet","Normal endwalls")) | I52: =IF($C52="","","Normal outlet") | J52: =IF($C52="","",$C52&"|"&$D52&"/"&UPPER(TRIM($E52))) | K52: =IF($M52="","",INDEX(D_Points!$I$5:$I$204,$M52)) | M52: =IFERROR(MATCH(48,D_Points!$K$5:$K$204,0),"")
A53: =IF($C53="","",49) | B53: =IF($M53="","",TEXT(INT(INDEX(D_Points!$A$5:$A$204,$M53)/1000),"0")&"+"&TEXT(MOD(INDEX(D_Points!$A$5:$A$204,$M53),1000),"000")) | C53: =IF($M53="","",UPPER(TRIM(INDEX(D_Points!$C$5:$C$204,$M53)))) | D53: =IF($M53="","",INDEX(D_Points!$D$5:$D$204,$M53)) | E53: =IF($M53="","",UPPER(TRIM(INDEX(D_Points!$E$5:$E$204,$M53)))) | F53: =IF($M53="","",INDEX(D_Points!$F$5:$F$204,$M53)) | G53: =IF($M53="","",""&IF(INDEX(D_Points!$G$5:$G$204,$M53)="","Right Angle",TRIM(INDEX(D_Points!$G$5:$G$204,$M53)))) | H53: =IF($C53="","",IF($G53="Skew","Catchpit inlet","Normal endwalls")) | I53: =IF($C53="","","Normal outlet") | J53: =IF($C53="","",$C53&"|"&$D53&"/"&UPPER(TRIM($E53))) | K53: =IF($M53="","",INDEX(D_Points!$I$5:$I$204,$M53)) | M53: =IFERROR(MATCH(49,D_Points!$K$5:$K$204,0),"")
A54: =IF($C54="","",50) | B54: =IF($M54="","",TEXT(INT(INDEX(D_Points!$A$5:$A$204,$M54)/1000),"0")&"+"&TEXT(MOD(INDEX(D_Points!$A$5:$A$204,$M54),1000),"000")) | C54: =IF($M54="","",UPPER(TRIM(INDEX(D_Points!$C$5:$C$204,$M54)))) | D54: =IF($M54="","",INDEX(D_Points!$D$5:$D$204,$M54)) | E54: =IF($M54="","",UPPER(TRIM(INDEX(D_Points!$E$5:$E$204,$M54)))) | F54: =IF($M54="","",INDEX(D_Points!$F$5:$F$204,$M54)) | G54: =IF($M54="","",""&IF(INDEX(D_Points!$G$5:$G$204,$M54)="","Right Angle",TRIM(INDEX(D_Points!$G$5:$G$204,$M54)))) | H54: =IF($C54="","",IF($G54="Skew","Catchpit inlet","Normal endwalls")) | I54: =IF($C54="","","Normal outlet") | J54: =IF($C54="","",$C54&"|"&$D54&"/"&UPPER(TRIM($E54))) | K54: =IF($M54="","",INDEX(D_Points!$I$5:$I$204,$M54)) | M54: =IFERROR(MATCH(50,D_Points!$K$5:$K$204,0),"")
A55: =IF($C55="","",51) | B55: =IF($M55="","",TEXT(INT(INDEX(D_Points!$A$5:$A$204,$M55)/1000),"0")&"+"&TEXT(MOD(INDEX(D_Points!$A$5:$A$204,$M55),1000),"000")) | C55: =IF($M55="","",UPPER(TRIM(INDEX(D_Points!$C$5:$C$204,$M55)))) | D55: =IF($M55="","",INDEX(D_Points!$D$5:$D$204,$M55)) | E55: =IF($M55="","",UPPER(TRIM(INDEX(D_Points!$E$5:$E$204,$M55)))) | F55: =IF($M55="","",INDEX(D_Points!$F$5:$F$204,$M55)) | G55: =IF($M55="","",""&IF(INDEX(D_Points!$G$5:$G$204,$M55)="","Right Angle",TRIM(INDEX(D_Points!$G$5:$G$204,$M55)))) | H55: =IF($C55="","",IF($G55="Skew","Catchpit inlet","Normal endwalls")) | I55: =IF($C55="","","Normal outlet") | J55: =IF($C55="","",$C55&"|"&$D55&"/"&UPPER(TRIM($E55))) | K55: =IF($M55="","",INDEX(D_Points!$I$5:$I$204,$M55)) | M55: =IFERROR(MATCH(51,D_Points!$K$5:$K$204,0),"")
A56: =IF($C56="","",52) | B56: =IF($M56="","",TEXT(INT(INDEX(D_Points!$A$5:$A$204,$M56)/1000),"0")&"+"&TEXT(MOD(INDEX(D_Points!$A$5:$A$204,$M56),1000),"000")) | C56: =IF($M56="","",UPPER(TRIM(INDEX(D_Points!$C$5:$C$204,$M56)))) | D56: =IF($M56="","",INDEX(D_Points!$D$5:$D$204,$M56)) | E56: =IF($M56="","",UPPER(TRIM(INDEX(D_Points!$E$5:$E$204,$M56)))) | F56: =IF($M56="","",INDEX(D_Points!$F$5:$F$204,$M56)) | G56: =IF($M56="","",""&IF(INDEX(D_Points!$G$5:$G$204,$M56)="","Right Angle",TRIM(INDEX(D_Points!$G$5:$G$204,$M56)))) | H56: =IF($C56="","",IF($G56="Skew","Catchpit inlet","Normal endwalls")) | I56: =IF($C56="","","Normal outlet") | J56: =IF($C56="","",$C56&"|"&$D56&"/"&UPPER(TRIM($E56))) | K56: =IF($M56="","",INDEX(D_Points!$I$5:$I$204,$M56)) | M56: =IFERROR(MATCH(52,D_Points!$K$5:$K$204,0),"")
A57: =IF($C57="","",53) | B57: =IF($M57="","",TEXT(INT(INDEX(D_Points!$A$5:$A$204,$M57)/1000),"0")&"+"&TEXT(MOD(INDEX(D_Points!$A$5:$A$204,$M57),1000),"000")) | C57: =IF($M57="","",UPPER(TRIM(INDEX(D_Points!$C$5:$C$204,$M57)))) | D57: =IF($M57="","",INDEX(D_Points!$D$5:$D$204,$M57)) | E57: =IF($M57="","",UPPER(TRIM(INDEX(D_Points!$E$5:$E$204,$M57)))) | F57: =IF($M57="","",INDEX(D_Points!$F$5:$F$204,$M57)) | G57: =IF($M57="","",""&IF(INDEX(D_Points!$G$5:$G$204,$M57)="","Right Angle",TRIM(INDEX(D_Points!$G$5:$G$204,$M57)))) | H57: =IF($C57="","",IF($G57="Skew","Catchpit inlet","Normal endwalls")) | I57: =IF($C57="","","Normal outlet") | J57: =IF($C57="","",$C57&"|"&$D57&"/"&UPPER(TRIM($E57))) | K57: =IF($M57="","",INDEX(D_Points!$I$5:$I$204,$M57)) | M57: =IFERROR(MATCH(53,D_Points!$K$5:$K$204,0),"")
A58: =IF($C58="","",54) | B58: =IF($M58="","",TEXT(INT(INDEX(D_Points!$A$5:$A$204,$M58)/1000),"0")&"+"&TEXT(MOD(INDEX(D_Points!$A$5:$A$204,$M58),1000),"000")) | C58: =IF($M58="","",UPPER(TRIM(INDEX(D_Points!$C$5:$C$204,$M58)))) | D58: =IF($M58="","",INDEX(D_Points!$D$5:$D$204,$M58)) | E58: =IF($M58="","",UPPER(TRIM(INDEX(D_Points!$E$5:$E$204,$M58)))) | F58: =IF($M58="","",INDEX(D_Points!$F$5:$F$204,$M58)) | G58: =IF($M58="","",""&IF(INDEX(D_Points!$G$5:$G$204,$M58)="","Right Angle",TRIM(INDEX(D_Points!$G$5:$G$204,$M58)))) | H58: =IF($C58="","",IF($G58="Skew","Catchpit inlet","Normal endwalls")) | I58: =IF($C58="","","Normal outlet") | J58: =IF($C58="","",$C58&"|"&$D58&"/"&UPPER(TRIM($E58))) | K58: =IF($M58="","",INDEX(D_Points!$I$5:$I$204,$M58)) | M58: =IFERROR(MATCH(54,D_Points!$K$5:$K$204,0),"")
A59: =IF($C59="","",55) | B59: =IF($M59="","",TEXT(INT(INDEX(D_Points!$A$5:$A$204,$M59)/1000),"0")&"+"&TEXT(MOD(INDEX(D_Points!$A$5:$A$204,$M59),1000),"000")) | C59: =IF($M59="","",UPPER(TRIM(INDEX(D_Points!$C$5:$C$204,$M59)))) | D59: =IF($M59="","",INDEX(D_Points!$D$5:$D$204,$M59)) | E59: =IF($M59="","",UPPER(TRIM(INDEX(D_Points!$E$5:$E$204,$M59)))) | F59: =IF($M59="","",INDEX(D_Points!$F$5:$F$204,$M59)) | G59: =IF($M59="","",""&IF(INDEX(D_Points!$G$5:$G$204,$M59)="","Right Angle",TRIM(INDEX(D_Points!$G$5:$G$204,$M59)))) | H59: =IF($C59="","",IF($G59="Skew","Catchpit inlet","Normal endwalls")) | I59: =IF($C59="","","Normal outlet") | J59: =IF($C59="","",$C59&"|"&$D59&"/"&UPPER(TRIM($E59))) | K59: =IF($M59="","",INDEX(D_Points!$I$5:$I$204,$M59)) | M59: =IFERROR(MATCH(55,D_Points!$K$5:$K$204,0),"")
A60: =IF($C60="","",56) | B60: =IF($M60="","",TEXT(INT(INDEX(D_Points!$A$5:$A$204,$M60)/1000),"0")&"+"&TEXT(MOD(INDEX(D_Points!$A$5:$A$204,$M60),1000),"000")) | C60: =IF($M60="","",UPPER(TRIM(INDEX(D_Points!$C$5:$C$204,$M60)))) | D60: =IF($M60="","",INDEX(D_Points!$D$5:$D$204,$M60)) | E60: =IF($M60="","",UPPER(TRIM(INDEX(D_Points!$E$5:$E$204,$M60)))) | F60: =IF($M60="","",INDEX(D_Points!$F$5:$F$204,$M60)) | G60: =IF($M60="","",""&IF(INDEX(D_Points!$G$5:$G$204,$M60)="","Right Angle",TRIM(INDEX(D_Points!$G$5:$G$204,$M60)))) | H60: =IF($C60="","",IF($G60="Skew","Catchpit inlet","Normal endwalls")) | I60: =IF($C60="","","Normal outlet") | J60: =IF($C60="","",$C60&"|"&$D60&"/"&UPPER(TRIM($E60))) | K60: =IF($M60="","",INDEX(D_Points!$I$5:$I$204,$M60)) | M60: =IFERROR(MATCH(56,D_Points!$K$5:$K$204,0),"")
A61: =IF($C61="","",57) | B61: =IF($M61="","",TEXT(INT(INDEX(D_Points!$A$5:$A$204,$M61)/1000),"0")&"+"&TEXT(MOD(INDEX(D_Points!$A$5:$A$204,$M61),1000),"000")) | C61: =IF($M61="","",UPPER(TRIM(INDEX(D_Points!$C$5:$C$204,$M61)))) | D61: =IF($M61="","",INDEX(D_Points!$D$5:$D$204,$M61)) | E61: =IF($M61="","",UPPER(TRIM(INDEX(D_Points!$E$5:$E$204,$M61)))) | F61: =IF($M61="","",INDEX(D_Points!$F$5:$F$204,$M61)) | G61: =IF($M61="","",""&IF(INDEX(D_Points!$G$5:$G$204,$M61)="","Right Angle",TRIM(INDEX(D_Points!$G$5:$G$204,$M61)))) | H61: =IF($C61="","",IF($G61="Skew","Catchpit inlet","Normal endwalls")) | I61: =IF($C61="","","Normal outlet") | J61: =IF($C61="","",$C61&"|"&$D61&"/"&UPPER(TRIM($E61))) | K61: =IF($M61="","",INDEX(D_Points!$I$5:$I$204,$M61)) | M61: =IFERROR(MATCH(57,D_Points!$K$5:$K$204,0),"")
A62: =IF($C62="","",58) | B62: =IF($M62="","",TEXT(INT(INDEX(D_Points!$A$5:$A$204,$M62)/1000),"0")&"+"&TEXT(MOD(INDEX(D_Points!$A$5:$A$204,$M62),1000),"000")) | C62: =IF($M62="","",UPPER(TRIM(INDEX(D_Points!$C$5:$C$204,$M62)))) | D62: =IF($M62="","",INDEX(D_Points!$D$5:$D$204,$M62)) | E62: =IF($M62="","",UPPER(TRIM(INDEX(D_Points!$E$5:$E$204,$M62)))) | F62: =IF($M62="","",INDEX(D_Points!$F$5:$F$204,$M62)) | G62: =IF($M62="","",""&IF(INDEX(D_Points!$G$5:$G$204,$M62)="","Right Angle",TRIM(INDEX(D_Points!$G$5:$G$204,$M62)))) | H62: =IF($C62="","",IF($G62="Skew","Catchpit inlet","Normal endwalls")) | I62: =IF($C62="","","Normal outlet") | J62: =IF($C62="","",$C62&"|"&$D62&"/"&UPPER(TRIM($E62))) | K62: =IF($M62="","",INDEX(D_Points!$I$5:$I$204,$M62)) | M62: =IFERROR(MATCH(58,D_Points!$K$5:$K$204,0),"")
A63: =IF($C63="","",59) | B63: =IF($M63="","",TEXT(INT(INDEX(D_Points!$A$5:$A$204,$M63)/1000),"0")&"+"&TEXT(MOD(INDEX(D_Points!$A$5:$A$204,$M63),1000),"000")) | C63: =IF($M63="","",UPPER(TRIM(INDEX(D_Points!$C$5:$C$204,$M63)))) | D63: =IF($M63="","",INDEX(D_Points!$D$5:$D$204,$M63)) | E63: =IF($M63="","",UPPER(TRIM(INDEX(D_Points!$E$5:$E$204,$M63)))) | F63: =IF($M63="","",INDEX(D_Points!$F$5:$F$204,$M63)) | G63: =IF($M63="","",""&IF(INDEX(D_Points!$G$5:$G$204,$M63)="","Right Angle",TRIM(INDEX(D_Points!$G$5:$G$204,$M63)))) | H63: =IF($C63="","",IF($G63="Skew","Catchpit inlet","Normal endwalls")) | I63: =IF($C63="","","Normal outlet") | J63: =IF($C63="","",$C63&"|"&$D63&"/"&UPPER(TRIM($E63))) | K63: =IF($M63="","",INDEX(D_Points!$I$5:$I$204,$M63)) | M63: =IFERROR(MATCH(59,D_Points!$K$5:$K$204,0),"")
A64: =IF($C64="","",60) | B64: =IF($M64="","",TEXT(INT(INDEX(D_Points!$A$5:$A$204,$M64)/1000),"0")&"+"&TEXT(MOD(INDEX(D_Points!$A$5:$A$204,$M64),1000),"000")) | C64: =IF($M64="","",UPPER(TRIM(INDEX(D_Points!$C$5:$C$204,$M64)))) | D64: =IF($M64="","",INDEX(D_Points!$D$5:$D$204,$M64)) | E64: =IF($M64="","",UPPER(TRIM(INDEX(D_Points!$E$5:$E$204,$M64)))) | F64: =IF($M64="","",INDEX(D_Points!$F$5:$F$204,$M64)) | G64: =IF($M64="","",""&IF(INDEX(D_Points!$G$5:$G$204,$M64)="","Right Angle",TRIM(INDEX(D_Points!$G$5:$G$204,$M64)))) | H64: =IF($C64="","",IF($G64="Skew","Catchpit inlet","Normal endwalls")) | I64: =IF($C64="","","Normal outlet") | J64: =IF($C64="","",$C64&"|"&$D64&"/"&UPPER(TRIM($E64))) | K64: =IF($M64="","",INDEX(D_Points!$I$5:$I$204,$M64)) | M64: =IFERROR(MATCH(60,D_Points!$K$5:$K$204,0),"")
A65: =IF($C65="","",61) | B65: =IF($M65="","",TEXT(INT(INDEX(D_Points!$A$5:$A$204,$M65)/1000),"0")&"+"&TEXT(MOD(INDEX(D_Points!$A$5:$A$204,$M65),1000),"000")) | C65: =IF($M65="","",UPPER(TRIM(INDEX(D_Points!$C$5:$C$204,$M65)))) | D65: =IF($M65="","",INDEX(D_Points!$D$5:$D$204,$M65)) | E65: =IF($M65="","",UPPER(TRIM(INDEX(D_Points!$E$5:$E$204,$M65)))) | F65: =IF($M65="","",INDEX(D_Points!$F$5:$F$204,$M65)) | G65: =IF($M65="","",""&IF(INDEX(D_Points!$G$5:$G$204,$M65)="","Right Angle",TRIM(INDEX(D_Points!$G$5:$G$204,$M65)))) | H65: =IF($C65="","",IF($G65="Skew","Catchpit inlet","Normal endwalls")) | I65: =IF($C65="","","Normal outlet") | J65: =IF($C65="","",$C65&"|"&$D65&"/"&UPPER(TRIM($E65))) | K65: =IF($M65="","",INDEX(D_Points!$I$5:$I$204,$M65)) | M65: =IFERROR(MATCH(61,D_Points!$K$5:$K$204,0),"")
A66: =IF($C66="","",62) | B66: =IF($M66="","",TEXT(INT(INDEX(D_Points!$A$5:$A$204,$M66)/1000),"0")&"+"&TEXT(MOD(INDEX(D_Points!$A$5:$A$204,$M66),1000),"000")) | C66: =IF($M66="","",UPPER(TRIM(INDEX(D_Points!$C$5:$C$204,$M66)))) | D66: =IF($M66="","",INDEX(D_Points!$D$5:$D$204,$M66)) | E66: =IF($M66="","",UPPER(TRIM(INDEX(D_Points!$E$5:$E$204,$M66)))) | F66: =IF($M66="","",INDEX(D_Points!$F$5:$F$204,$M66)) | G66: =IF($M66="","",""&IF(INDEX(D_Points!$G$5:$G$204,$M66)="","Right Angle",TRIM(INDEX(D_Points!$G$5:$G$204,$M66)))) | H66: =IF($C66="","",IF($G66="Skew","Catchpit inlet","Normal endwalls")) | I66: =IF($C66="","","Normal outlet") | J66: =IF($C66="","",$C66&"|"&$D66&"/"&UPPER(TRIM($E66))) | K66: =IF($M66="","",INDEX(D_Points!$I$5:$I$204,$M66)) | M66: =IFERROR(MATCH(62,D_Points!$K$5:$K$204,0),"")
A67: =IF($C67="","",63) | B67: =IF($M67="","",TEXT(INT(INDEX(D_Points!$A$5:$A$204,$M67)/1000),"0")&"+"&TEXT(MOD(INDEX(D_Points!$A$5:$A$204,$M67),1000),"000")) | C67: =IF($M67="","",UPPER(TRIM(INDEX(D_Points!$C$5:$C$204,$M67)))) | D67: =IF($M67="","",INDEX(D_Points!$D$5:$D$204,$M67)) | E67: =IF($M67="","",UPPER(TRIM(INDEX(D_Points!$E$5:$E$204,$M67)))) | F67: =IF($M67="","",INDEX(D_Points!$F$5:$F$204,$M67)) | G67: =IF($M67="","",""&IF(INDEX(D_Points!$G$5:$G$204,$M67)="","Right Angle",TRIM(INDEX(D_Points!$G$5:$G$204,$M67)))) | H67: =IF($C67="","",IF($G67="Skew","Catchpit inlet","Normal endwalls")) | I67: =IF($C67="","","Normal outlet") | J67: =IF($C67="","",$C67&"|"&$D67&"/"&UPPER(TRIM($E67))) | K67: =IF($M67="","",INDEX(D_Points!$I$5:$I$204,$M67)) | M67: =IFERROR(MATCH(63,D_Points!$K$5:$K$204,0),"")
A68: =IF($C68="","",64) | B68: =IF($M68="","",TEXT(INT(INDEX(D_Points!$A$5:$A$204,$M68)/1000),"0")&"+"&TEXT(MOD(INDEX(D_Points!$A$5:$A$204,$M68),1000),"000")) | C68: =IF($M68="","",UPPER(TRIM(INDEX(D_Points!$C$5:$C$204,$M68)))) | D68: =IF($M68="","",INDEX(D_Points!$D$5:$D$204,$M68)) | E68: =IF($M68="","",UPPER(TRIM(INDEX(D_Points!$E$5:$E$204,$M68)))) | F68: =IF($M68="","",INDEX(D_Points!$F$5:$F$204,$M68)) | G68: =IF($M68="","",""&IF(INDEX(D_Points!$G$5:$G$204,$M68)="","Right Angle",TRIM(INDEX(D_Points!$G$5:$G$204,$M68)))) | H68: =IF($C68="","",IF($G68="Skew","Catchpit inlet","Normal endwalls")) | I68: =IF($C68="","","Normal outlet") | J68: =IF($C68="","",$C68&"|"&$D68&"/"&UPPER(TRIM($E68))) | K68: =IF($M68="","",INDEX(D_Points!$I$5:$I$204,$M68)) | M68: =IFERROR(MATCH(64,D_Points!$K$5:$K$204,0),"")
A69: =IF($C69="","",65) | B69: =IF($M69="","",TEXT(INT(INDEX(D_Points!$A$5:$A$204,$M69)/1000),"0")&"+"&TEXT(MOD(INDEX(D_Points!$A$5:$A$204,$M69),1000),"000")) | C69: =IF($M69="","",UPPER(TRIM(INDEX(D_Points!$C$5:$C$204,$M69)))) | D69: =IF($M69="","",INDEX(D_Points!$D$5:$D$204,$M69)) | E69: =IF($M69="","",UPPER(TRIM(INDEX(D_Points!$E$5:$E$204,$M69)))) | F69: =IF($M69="","",INDEX(D_Points!$F$5:$F$204,$M69)) | G69: =IF($M69="","",""&IF(INDEX(D_Points!$G$5:$G$204,$M69)="","Right Angle",TRIM(INDEX(D_Points!$G$5:$G$204,$M69)))) | H69: =IF($C69="","",IF($G69="Skew","Catchpit inlet","Normal endwalls")) | I69: =IF($C69="","","Normal outlet") | J69: =IF($C69="","",$C69&"|"&$D69&"/"&UPPER(TRIM($E69))) | K69: =IF($M69="","",INDEX(D_Points!$I$5:$I$204,$M69)) | M69: =IFERROR(MATCH(65,D_Points!$K$5:$K$204,0),"")
A70: =IF($C70="","",66) | B70: =IF($M70="","",TEXT(INT(INDEX(D_Points!$A$5:$A$204,$M70)/1000),"0")&"+"&TEXT(MOD(INDEX(D_Points!$A$5:$A$204,$M70),1000),"000")) | C70: =IF($M70="","",UPPER(TRIM(INDEX(D_Points!$C$5:$C$204,$M70)))) | D70: =IF($M70="","",INDEX(D_Points!$D$5:$D$204,$M70)) | E70: =IF($M70="","",UPPER(TRIM(INDEX(D_Points!$E$5:$E$204,$M70)))) | F70: =IF($M70="","",INDEX(D_Points!$F$5:$F$204,$M70)) | G70: =IF($M70="","",""&IF(INDEX(D_Points!$G$5:$G$204,$M70)="","Right Angle",TRIM(INDEX(D_Points!$G$5:$G$204,$M70)))) | H70: =IF($C70="","",IF($G70="Skew","Catchpit inlet","Normal endwalls")) | I70: =IF($C70="","","Normal outlet") | J70: =IF($C70="","",$C70&"|"&$D70&"/"&UPPER(TRIM($E70))) | K70: =IF($M70="","",INDEX(D_Points!$I$5:$I$204,$M70)) | M70: =IFERROR(MATCH(66,D_Points!$K$5:$K$204,0),"")
A71: =IF($C71="","",67) | B71: =IF($M71="","",TEXT(INT(INDEX(D_Points!$A$5:$A$204,$M71)/1000),"0")&"+"&TEXT(MOD(INDEX(D_Points!$A$5:$A$204,$M71),1000),"000")) | C71: =IF($M71="","",UPPER(TRIM(INDEX(D_Points!$C$5:$C$204,$M71)))) | D71: =IF($M71="","",INDEX(D_Points!$D$5:$D$204,$M71)) | E71: =IF($M71="","",UPPER(TRIM(INDEX(D_Points!$E$5:$E$204,$M71)))) | F71: =IF($M71="","",INDEX(D_Points!$F$5:$F$204,$M71)) | G71: =IF($M71="","",""&IF(INDEX(D_Points!$G$5:$G$204,$M71)="","Right Angle",TRIM(INDEX(D_Points!$G$5:$G$204,$M71)))) | H71: =IF($C71="","",IF($G71="Skew","Catchpit inlet","Normal endwalls")) | I71: =IF($C71="","","Normal outlet") | J71: =IF($C71="","",$C71&"|"&$D71&"/"&UPPER(TRIM($E71))) | K71: =IF($M71="","",INDEX(D_Points!$I$5:$I$204,$M71)) | M71: =IFERROR(MATCH(67,D_Points!$K$5:$K$204,0),"")
A72: =IF($C72="","",68) | B72: =IF($M72="","",TEXT(INT(INDEX(D_Points!$A$5:$A$204,$M72)/1000),"0")&"+"&TEXT(MOD(INDEX(D_Points!$A$5:$A$204,$M72),1000),"000")) | C72: =IF($M72="","",UPPER(TRIM(INDEX(D_Points!$C$5:$C$204,$M72)))) | D72: =IF($M72="","",INDEX(D_Points!$D$5:$D$204,$M72)) | E72: =IF($M72="","",UPPER(TRIM(INDEX(D_Points!$E$5:$E$204,$M72)))) | F72: =IF($M72="","",INDEX(D_Points!$F$5:$F$204,$M72)) | G72: =IF($M72="","",""&IF(INDEX(D_Points!$G$5:$G$204,$M72)="","Right Angle",TRIM(INDEX(D_Points!$G$5:$G$204,$M72)))) | H72: =IF($C72="","",IF($G72="Skew","Catchpit inlet","Normal endwalls")) | I72: =IF($C72="","","Normal outlet") | J72: =IF($C72="","",$C72&"|"&$D72&"/"&UPPER(TRIM($E72))) | K72: =IF($M72="","",INDEX(D_Points!$I$5:$I$204,$M72)) | M72: =IFERROR(MATCH(68,D_Points!$K$5:$K$204,0),"")
A73: =IF($C73="","",69) | B73: =IF($M73="","",TEXT(INT(INDEX(D_Points!$A$5:$A$204,$M73)/1000),"0")&"+"&TEXT(MOD(INDEX(D_Points!$A$5:$A$204,$M73),1000),"000")) | C73: =IF($M73="","",UPPER(TRIM(INDEX(D_Points!$C$5:$C$204,$M73)))) | D73: =IF($M73="","",INDEX(D_Points!$D$5:$D$204,$M73)) | E73: =IF($M73="","",UPPER(TRIM(INDEX(D_Points!$E$5:$E$204,$M73)))) | F73: =IF($M73="","",INDEX(D_Points!$F$5:$F$204,$M73)) | G73: =IF($M73="","",""&IF(INDEX(D_Points!$G$5:$G$204,$M73)="","Right Angle",TRIM(INDEX(D_Points!$G$5:$G$204,$M73)))) | H73: =IF($C73="","",IF($G73="Skew","Catchpit inlet","Normal endwalls")) | I73: =IF($C73="","","Normal outlet") | J73: =IF($C73="","",$C73&"|"&$D73&"/"&UPPER(TRIM($E73))) | K73: =IF($M73="","",INDEX(D_Points!$I$5:$I$204,$M73)) | M73: =IFERROR(MATCH(69,D_Points!$K$5:$K$204,0),"")
A74: =IF($C74="","",70) | B74: =IF($M74="","",TEXT(INT(INDEX(D_Points!$A$5:$A$204,$M74)/1000),"0")&"+"&TEXT(MOD(INDEX(D_Points!$A$5:$A$204,$M74),1000),"000")) | C74: =IF($M74="","",UPPER(TRIM(INDEX(D_Points!$C$5:$C$204,$M74)))) | D74: =IF($M74="","",INDEX(D_Points!$D$5:$D$204,$M74)) | E74: =IF($M74="","",UPPER(TRIM(INDEX(D_Points!$E$5:$E$204,$M74)))) | F74: =IF($M74="","",INDEX(D_Points!$F$5:$F$204,$M74)) | G74: =IF($M74="","",""&IF(INDEX(D_Points!$G$5:$G$204,$M74)="","Right Angle",TRIM(INDEX(D_Points!$G$5:$G$204,$M74)))) | H74: =IF($C74="","",IF($G74="Skew","Catchpit inlet","Normal endwalls")) | I74: =IF($C74="","","Normal outlet") | J74: =IF($C74="","",$C74&"|"&$D74&"/"&UPPER(TRIM($E74))) | K74: =IF($M74="","",INDEX(D_Points!$I$5:$I$204,$M74)) | M74: =IFERROR(MATCH(70,D_Points!$K$5:$K$204,0),"")
A75: =IF($C75="","",71) | B75: =IF($M75="","",TEXT(INT(INDEX(D_Points!$A$5:$A$204,$M75)/1000),"0")&"+"&TEXT(MOD(INDEX(D_Points!$A$5:$A$204,$M75),1000),"000")) | C75: =IF($M75="","",UPPER(TRIM(INDEX(D_Points!$C$5:$C$204,$M75)))) | D75: =IF($M75="","",INDEX(D_Points!$D$5:$D$204,$M75)) | E75: =IF($M75="","",UPPER(TRIM(INDEX(D_Points!$E$5:$E$204,$M75)))) | F75: =IF($M75="","",INDEX(D_Points!$F$5:$F$204,$M75)) | G75: =IF($M75="","",""&IF(INDEX(D_Points!$G$5:$G$204,$M75)="","Right Angle",TRIM(INDEX(D_Points!$G$5:$G$204,$M75)))) | H75: =IF($C75="","",IF($G75="Skew","Catchpit inlet","Normal endwalls")) | I75: =IF($C75="","","Normal outlet") | J75: =IF($C75="","",$C75&"|"&$D75&"/"&UPPER(TRIM($E75))) | K75: =IF($M75="","",INDEX(D_Points!$I$5:$I$204,$M75)) | M75: =IFERROR(MATCH(71,D_Points!$K$5:$K$204,0),"")
A76: =IF($C76="","",72) | B76: =IF($M76="","",TEXT(INT(INDEX(D_Points!$A$5:$A$204,$M76)/1000),"0")&"+"&TEXT(MOD(INDEX(D_Points!$A$5:$A$204,$M76),1000),"000")) | C76: =IF($M76="","",UPPER(TRIM(INDEX(D_Points!$C$5:$C$204,$M76)))) | D76: =IF($M76="","",INDEX(D_Points!$D$5:$D$204,$M76)) | E76: =IF($M76="","",UPPER(TRIM(INDEX(D_Points!$E$5:$E$204,$M76)))) | F76: =IF($M76="","",INDEX(D_Points!$F$5:$F$204,$M76)) | G76: =IF($M76="","",""&IF(INDEX(D_Points!$G$5:$G$204,$M76)="","Right Angle",TRIM(INDEX(D_Points!$G$5:$G$204,$M76)))) | H76: =IF($C76="","",IF($G76="Skew","Catchpit inlet","Normal endwalls")) | I76: =IF($C76="","","Normal outlet") | J76: =IF($C76="","",$C76&"|"&$D76&"/"&UPPER(TRIM($E76))) | K76: =IF($M76="","",INDEX(D_Points!$I$5:$I$204,$M76)) | M76: =IFERROR(MATCH(72,D_Points!$K$5:$K$204,0),"")
A77: =IF($C77="","",73) | B77: =IF($M77="","",TEXT(INT(INDEX(D_Points!$A$5:$A$204,$M77)/1000),"0")&"+"&TEXT(MOD(INDEX(D_Points!$A$5:$A$204,$M77),1000),"000")) | C77: =IF($M77="","",UPPER(TRIM(INDEX(D_Points!$C$5:$C$204,$M77)))) | D77: =IF($M77="","",INDEX(D_Points!$D$5:$D$204,$M77)) | E77: =IF($M77="","",UPPER(TRIM(INDEX(D_Points!$E$5:$E$204,$M77)))) | F77: =IF($M77="","",INDEX(D_Points!$F$5:$F$204,$M77)) | G77: =IF($M77="","",""&IF(INDEX(D_Points!$G$5:$G$204,$M77)="","Right Angle",TRIM(INDEX(D_Points!$G$5:$G$204,$M77)))) | H77: =IF($C77="","",IF($G77="Skew","Catchpit inlet","Normal endwalls")) | I77: =IF($C77="","","Normal outlet") | J77: =IF($C77="","",$C77&"|"&$D77&"/"&UPPER(TRIM($E77))) | K77: =IF($M77="","",INDEX(D_Points!$I$5:$I$204,$M77)) | M77: =IFERROR(MATCH(73,D_Points!$K$5:$K$204,0),"")
A78: =IF($C78="","",74) | B78: =IF($M78="","",TEXT(INT(INDEX(D_Points!$A$5:$A$204,$M78)/1000),"0")&"+"&TEXT(MOD(INDEX(D_Points!$A$5:$A$204,$M78),1000),"000")) | C78: =IF($M78="","",UPPER(TRIM(INDEX(D_Points!$C$5:$C$204,$M78)))) | D78: =IF($M78="","",INDEX(D_Points!$D$5:$D$204,$M78)) | E78: =IF($M78="","",UPPER(TRIM(INDEX(D_Points!$E$5:$E$204,$M78)))) | F78: =IF($M78="","",INDEX(D_Points!$F$5:$F$204,$M78)) | G78: =IF($M78="","",""&IF(INDEX(D_Points!$G$5:$G$204,$M78)="","Right Angle",TRIM(INDEX(D_Points!$G$5:$G$204,$M78)))) | H78: =IF($C78="","",IF($G78="Skew","Catchpit inlet","Normal endwalls")) | I78: =IF($C78="","","Normal outlet") | J78: =IF($C78="","",$C78&"|"&$D78&"/"&UPPER(TRIM($E78))) | K78: =IF($M78="","",INDEX(D_Points!$I$5:$I$204,$M78)) | M78: =IFERROR(MATCH(74,D_Points!$K$5:$K$204,0),"")
A79: =IF($C79="","",75) | B79: =IF($M79="","",TEXT(INT(INDEX(D_Points!$A$5:$A$204,$M79)/1000),"0")&"+"&TEXT(MOD(INDEX(D_Points!$A$5:$A$204,$M79),1000),"000")) | C79: =IF($M79="","",UPPER(TRIM(INDEX(D_Points!$C$5:$C$204,$M79)))) | D79: =IF($M79="","",INDEX(D_Points!$D$5:$D$204,$M79)) | E79: =IF($M79="","",UPPER(TRIM(INDEX(D_Points!$E$5:$E$204,$M79)))) | F79: =IF($M79="","",INDEX(D_Points!$F$5:$F$204,$M79)) | G79: =IF($M79="","",""&IF(INDEX(D_Points!$G$5:$G$204,$M79)="","Right Angle",TRIM(INDEX(D_Points!$G$5:$G$204,$M79)))) | H79: =IF($C79="","",IF($G79="Skew","Catchpit inlet","Normal endwalls")) | I79: =IF($C79="","","Normal outlet") | J79: =IF($C79="","",$C79&"|"&$D79&"/"&UPPER(TRIM($E79))) | K79: =IF($M79="","",INDEX(D_Points!$I$5:$I$204,$M79)) | M79: =IFERROR(MATCH(75,D_Points!$K$5:$K$204,0),"")
A80: =IF($C80="","",76) | B80: =IF($M80="","",TEXT(INT(INDEX(D_Points!$A$5:$A$204,$M80)/1000),"0")&"+"&TEXT(MOD(INDEX(D_Points!$A$5:$A$204,$M80),1000),"000")) | C80: =IF($M80="","",UPPER(TRIM(INDEX(D_Points!$C$5:$C$204,$M80)))) | D80: =IF($M80="","",INDEX(D_Points!$D$5:$D$204,$M80)) | E80: =IF($M80="","",UPPER(TRIM(INDEX(D_Points!$E$5:$E$204,$M80)))) | F80: =IF($M80="","",INDEX(D_Points!$F$5:$F$204,$M80)) | G80: =IF($M80="","",""&IF(INDEX(D_Points!$G$5:$G$204,$M80)="","Right Angle",TRIM(INDEX(D_Points!$G$5:$G$204,$M80)))) | H80: =IF($C80="","",IF($G80="Skew","Catchpit inlet","Normal endwalls")) | I80: =IF($C80="","","Normal outlet") | J80: =IF($C80="","",$C80&"|"&$D80&"/"&UPPER(TRIM($E80))) | K80: =IF($M80="","",INDEX(D_Points!$I$5:$I$204,$M80)) | M80: =IFERROR(MATCH(76,D_Points!$K$5:$K$204,0),"")
A81: =IF($C81="","",77) | B81: =IF($M81="","",TEXT(INT(INDEX(D_Points!$A$5:$A$204,$M81)/1000),"0")&"+"&TEXT(MOD(INDEX(D_Points!$A$5:$A$204,$M81),1000),"000")) | C81: =IF($M81="","",UPPER(TRIM(INDEX(D_Points!$C$5:$C$204,$M81)))) | D81: =IF($M81="","",INDEX(D_Points!$D$5:$D$204,$M81)) | E81: =IF($M81="","",UPPER(TRIM(INDEX(D_Points!$E$5:$E$204,$M81)))) | F81: =IF($M81="","",INDEX(D_Points!$F$5:$F$204,$M81)) | G81: =IF($M81="","",""&IF(INDEX(D_Points!$G$5:$G$204,$M81)="","Right Angle",TRIM(INDEX(D_Points!$G$5:$G$204,$M81)))) | H81: =IF($C81="","",IF($G81="Skew","Catchpit inlet","Normal endwalls")) | I81: =IF($C81="","","Normal outlet") | J81: =IF($C81="","",$C81&"|"&$D81&"/"&UPPER(TRIM($E81))) | K81: =IF($M81="","",INDEX(D_Points!$I$5:$I$204,$M81)) | M81: =IFERROR(MATCH(77,D_Points!$K$5:$K$204,0),"")
A82: =IF($C82="","",78) | B82: =IF($M82="","",TEXT(INT(INDEX(D_Points!$A$5:$A$204,$M82)/1000),"0")&"+"&TEXT(MOD(INDEX(D_Points!$A$5:$A$204,$M82),1000),"000")) | C82: =IF($M82="","",UPPER(TRIM(INDEX(D_Points!$C$5:$C$204,$M82)))) | D82: =IF($M82="","",INDEX(D_Points!$D$5:$D$204,$M82)) | E82: =IF($M82="","",UPPER(TRIM(INDEX(D_Points!$E$5:$E$204,$M82)))) | F82: =IF($M82="","",INDEX(D_Points!$F$5:$F$204,$M82)) | G82: =IF($M82="","",""&IF(INDEX(D_Points!$G$5:$G$204,$M82)="","Right Angle",TRIM(INDEX(D_Points!$G$5:$G$204,$M82)))) | H82: =IF($C82="","",IF($G82="Skew","Catchpit inlet","Normal endwalls")) | I82: =IF($C82="","","Normal outlet") | J82: =IF($C82="","",$C82&"|"&$D82&"/"&UPPER(TRIM($E82))) | K82: =IF($M82="","",INDEX(D_Points!$I$5:$I$204,$M82)) | M82: =IFERROR(MATCH(78,D_Points!$K$5:$K$204,0),"")
A83: =IF($C83="","",79) | B83: =IF($M83="","",TEXT(INT(INDEX(D_Points!$A$5:$A$204,$M83)/1000),"0")&"+"&TEXT(MOD(INDEX(D_Points!$A$5:$A$204,$M83),1000),"000")) | C83: =IF($M83="","",UPPER(TRIM(INDEX(D_Points!$C$5:$C$204,$M83)))) | D83: =IF($M83="","",INDEX(D_Points!$D$5:$D$204,$M83)) | E83: =IF($M83="","",UPPER(TRIM(INDEX(D_Points!$E$5:$E$204,$M83)))) | F83: =IF($M83="","",INDEX(D_Points!$F$5:$F$204,$M83)) | G83: =IF($M83="","",""&IF(INDEX(D_Points!$G$5:$G$204,$M83)="","Right Angle",TRIM(INDEX(D_Points!$G$5:$G$204,$M83)))) | H83: =IF($C83="","",IF($G83="Skew","Catchpit inlet","Normal endwalls")) | I83: =IF($C83="","","Normal outlet") | J83: =IF($C83="","",$C83&"|"&$D83&"/"&UPPER(TRIM($E83))) | K83: =IF($M83="","",INDEX(D_Points!$I$5:$I$204,$M83)) | M83: =IFERROR(MATCH(79,D_Points!$K$5:$K$204,0),"")
A84: =IF($C84="","",80) | B84: =IF($M84="","",TEXT(INT(INDEX(D_Points!$A$5:$A$204,$M84)/1000),"0")&"+"&TEXT(MOD(INDEX(D_Points!$A$5:$A$204,$M84),1000),"000")) | C84: =IF($M84="","",UPPER(TRIM(INDEX(D_Points!$C$5:$C$204,$M84)))) | D84: =IF($M84="","",INDEX(D_Points!$D$5:$D$204,$M84)) | E84: =IF($M84="","",UPPER(TRIM(INDEX(D_Points!$E$5:$E$204,$M84)))) | F84: =IF($M84="","",INDEX(D_Points!$F$5:$F$204,$M84)) | G84: =IF($M84="","",""&IF(INDEX(D_Points!$G$5:$G$204,$M84)="","Right Angle",TRIM(INDEX(D_Points!$G$5:$G$204,$M84)))) | H84: =IF($C84="","",IF($G84="Skew","Catchpit inlet","Normal endwalls")) | I84: =IF($C84="","","Normal outlet") | J84: =IF($C84="","",$C84&"|"&$D84&"/"&UPPER(TRIM($E84))) | K84: =IF($M84="","",INDEX(D_Points!$I$5:$I$204,$M84)) | M84: =IFERROR(MATCH(80,D_Points!$K$5:$K$204,0),"")
A85: =IF($C85="","",81) | B85: =IF($M85="","",TEXT(INT(INDEX(D_Points!$A$5:$A$204,$M85)/1000),"0")&"+"&TEXT(MOD(INDEX(D_Points!$A$5:$A$204,$M85),1000),"000")) | C85: =IF($M85="","",UPPER(TRIM(INDEX(D_Points!$C$5:$C$204,$M85)))) | D85: =IF($M85="","",INDEX(D_Points!$D$5:$D$204,$M85)) | E85: =IF($M85="","",UPPER(TRIM(INDEX(D_Points!$E$5:$E$204,$M85)))) | F85: =IF($M85="","",INDEX(D_Points!$F$5:$F$204,$M85)) | G85: =IF($M85="","",""&IF(INDEX(D_Points!$G$5:$G$204,$M85)="","Right Angle",TRIM(INDEX(D_Points!$G$5:$G$204,$M85)))) | H85: =IF($C85="","",IF($G85="Skew","Catchpit inlet","Normal endwalls")) | I85: =IF($C85="","","Normal outlet") | J85: =IF($C85="","",$C85&"|"&$D85&"/"&UPPER(TRIM($E85))) | K85: =IF($M85="","",INDEX(D_Points!$I$5:$I$204,$M85)) | M85: =IFERROR(MATCH(81,D_Points!$K$5:$K$204,0),"")
A86: =IF($C86="","",82) | B86: =IF($M86="","",TEXT(INT(INDEX(D_Points!$A$5:$A$204,$M86)/1000),"0")&"+"&TEXT(MOD(INDEX(D_Points!$A$5:$A$204,$M86),1000),"000")) | C86: =IF($M86="","",UPPER(TRIM(INDEX(D_Points!$C$5:$C$204,$M86)))) | D86: =IF($M86="","",INDEX(D_Points!$D$5:$D$204,$M86)) | E86: =IF($M86="","",UPPER(TRIM(INDEX(D_Points!$E$5:$E$204,$M86)))) | F86: =IF($M86="","",INDEX(D_Points!$F$5:$F$204,$M86)) | G86: =IF($M86="","",""&IF(INDEX(D_Points!$G$5:$G$204,$M86)="","Right Angle",TRIM(INDEX(D_Points!$G$5:$G$204,$M86)))) | H86: =IF($C86="","",IF($G86="Skew","Catchpit inlet","Normal endwalls")) | I86: =IF($C86="","","Normal outlet") | J86: =IF($C86="","",$C86&"|"&$D86&"/"&UPPER(TRIM($E86))) | K86: =IF($M86="","",INDEX(D_Points!$I$5:$I$204,$M86)) | M86: =IFERROR(MATCH(82,D_Points!$K$5:$K$204,0),"")
A87: =IF($C87="","",83) | B87: =IF($M87="","",TEXT(INT(INDEX(D_Points!$A$5:$A$204,$M87)/1000),"0")&"+"&TEXT(MOD(INDEX(D_Points!$A$5:$A$204,$M87),1000),"000")) | C87: =IF($M87="","",UPPER(TRIM(INDEX(D_Points!$C$5:$C$204,$M87)))) | D87: =IF($M87="","",INDEX(D_Points!$D$5:$D$204,$M87)) | E87: =IF($M87="","",UPPER(TRIM(INDEX(D_Points!$E$5:$E$204,$M87)))) | F87: =IF($M87="","",INDEX(D_Points!$F$5:$F$204,$M87)) | G87: =IF($M87="","",""&IF(INDEX(D_Points!$G$5:$G$204,$M87)="","Right Angle",TRIM(INDEX(D_Points!$G$5:$G$204,$M87)))) | H87: =IF($C87="","",IF($G87="Skew","Catchpit inlet","Normal endwalls")) | I87: =IF($C87="","","Normal outlet") | J87: =IF($C87="","",$C87&"|"&$D87&"/"&UPPER(TRIM($E87))) | K87: =IF($M87="","",INDEX(D_Points!$I$5:$I$204,$M87)) | M87: =IFERROR(MATCH(83,D_Points!$K$5:$K$204,0),"")
A88: =IF($C88="","",84) | B88: =IF($M88="","",TEXT(INT(INDEX(D_Points!$A$5:$A$204,$M88)/1000),"0")&"+"&TEXT(MOD(INDEX(D_Points!$A$5:$A$204,$M88),1000),"000")) | C88: =IF($M88="","",UPPER(TRIM(INDEX(D_Points!$C$5:$C$204,$M88)))) | D88: =IF($M88="","",INDEX(D_Points!$D$5:$D$204,$M88)) | E88: =IF($M88="","",UPPER(TRIM(INDEX(D_Points!$E$5:$E$204,$M88)))) | F88: =IF($M88="","",INDEX(D_Points!$F$5:$F$204,$M88)) | G88: =IF($M88="","",""&IF(INDEX(D_Points!$G$5:$G$204,$M88)="","Right Angle",TRIM(INDEX(D_Points!$G$5:$G$204,$M88)))) | H88: =IF($C88="","",IF($G88="Skew","Catchpit inlet","Normal endwalls")) | I88: =IF($C88="","","Normal outlet") | J88: =IF($C88="","",$C88&"|"&$D88&"/"&UPPER(TRIM($E88))) | K88: =IF($M88="","",INDEX(D_Points!$I$5:$I$204,$M88)) | M88: =IFERROR(MATCH(84,D_Points!$K$5:$K$204,0),"")
A89: =IF($C89="","",85) | B89: =IF($M89="","",TEXT(INT(INDEX(D_Points!$A$5:$A$204,$M89)/1000),"0")&"+"&TEXT(MOD(INDEX(D_Points!$A$5:$A$204,$M89),1000),"000")) | C89: =IF($M89="","",UPPER(TRIM(INDEX(D_Points!$C$5:$C$204,$M89)))) | D89: =IF($M89="","",INDEX(D_Points!$D$5:$D$204,$M89)) | E89: =IF($M89="","",UPPER(TRIM(INDEX(D_Points!$E$5:$E$204,$M89)))) | F89: =IF($M89="","",INDEX(D_Points!$F$5:$F$204,$M89)) | G89: =IF($M89="","",""&IF(INDEX(D_Points!$G$5:$G$204,$M89)="","Right Angle",TRIM(INDEX(D_Points!$G$5:$G$204,$M89)))) | H89: =IF($C89="","",IF($G89="Skew","Catchpit inlet","Normal endwalls")) | I89: =IF($C89="","","Normal outlet") | J89: =IF($C89="","",$C89&"|"&$D89&"/"&UPPER(TRIM($E89))) | K89: =IF($M89="","",INDEX(D_Points!$I$5:$I$204,$M89)) | M89: =IFERROR(MATCH(85,D_Points!$K$5:$K$204,0),"")
A90: =IF($C90="","",86) | B90: =IF($M90="","",TEXT(INT(INDEX(D_Points!$A$5:$A$204,$M90)/1000),"0")&"+"&TEXT(MOD(INDEX(D_Points!$A$5:$A$204,$M90),1000),"000")) | C90: =IF($M90="","",UPPER(TRIM(INDEX(D_Points!$C$5:$C$204,$M90)))) | D90: =IF($M90="","",INDEX(D_Points!$D$5:$D$204,$M90)) | E90: =IF($M90="","",UPPER(TRIM(INDEX(D_Points!$E$5:$E$204,$M90)))) | F90: =IF($M90="","",INDEX(D_Points!$F$5:$F$204,$M90)) | G90: =IF($M90="","",""&IF(INDEX(D_Points!$G$5:$G$204,$M90)="","Right Angle",TRIM(INDEX(D_Points!$G$5:$G$204,$M90)))) | H90: =IF($C90="","",IF($G90="Skew","Catchpit inlet","Normal endwalls")) | I90: =IF($C90="","","Normal outlet") | J90: =IF($C90="","",$C90&"|"&$D90&"/"&UPPER(TRIM($E90))) | K90: =IF($M90="","",INDEX(D_Points!$I$5:$I$204,$M90)) | M90: =IFERROR(MATCH(86,D_Points!$K$5:$K$204,0),"")
A91: =IF($C91="","",87) | B91: =IF($M91="","",TEXT(INT(INDEX(D_Points!$A$5:$A$204,$M91)/1000),"0")&"+"&TEXT(MOD(INDEX(D_Points!$A$5:$A$204,$M91),1000),"000")) | C91: =IF($M91="","",UPPER(TRIM(INDEX(D_Points!$C$5:$C$204,$M91)))) | D91: =IF($M91="","",INDEX(D_Points!$D$5:$D$204,$M91)) | E91: =IF($M91="","",UPPER(TRIM(INDEX(D_Points!$E$5:$E$204,$M91)))) | F91: =IF($M91="","",INDEX(D_Points!$F$5:$F$204,$M91)) | G91: =IF($M91="","",""&IF(INDEX(D_Points!$G$5:$G$204,$M91)="","Right Angle",TRIM(INDEX(D_Points!$G$5:$G$204,$M91)))) | H91: =IF($C91="","",IF($G91="Skew","Catchpit inlet","Normal endwalls")) | I91: =IF($C91="","","Normal outlet") | J91: =IF($C91="","",$C91&"|"&$D91&"/"&UPPER(TRIM($E91))) | K91: =IF($M91="","",INDEX(D_Points!$I$5:$I$204,$M91)) | M91: =IFERROR(MATCH(87,D_Points!$K$5:$K$204,0),"")
A92: =IF($C92="","",88) | B92: =IF($M92="","",TEXT(INT(INDEX(D_Points!$A$5:$A$204,$M92)/1000),"0")&"+"&TEXT(MOD(INDEX(D_Points!$A$5:$A$204,$M92),1000),"000")) | C92: =IF($M92="","",UPPER(TRIM(INDEX(D_Points!$C$5:$C$204,$M92)))) | D92: =IF($M92="","",INDEX(D_Points!$D$5:$D$204,$M92)) | E92: =IF($M92="","",UPPER(TRIM(INDEX(D_Points!$E$5:$E$204,$M92)))) | F92: =IF($M92="","",INDEX(D_Points!$F$5:$F$204,$M92)) | G92: =IF($M92="","",""&IF(INDEX(D_Points!$G$5:$G$204,$M92)="","Right Angle",TRIM(INDEX(D_Points!$G$5:$G$204,$M92)))) | H92: =IF($C92="","",IF($G92="Skew","Catchpit inlet","Normal endwalls")) | I92: =IF($C92="","","Normal outlet") | J92: =IF($C92="","",$C92&"|"&$D92&"/"&UPPER(TRIM($E92))) | K92: =IF($M92="","",INDEX(D_Points!$I$5:$I$204,$M92)) | M92: =IFERROR(MATCH(88,D_Points!$K$5:$K$204,0),"")
A93: =IF($C93="","",89) | B93: =IF($M93="","",TEXT(INT(INDEX(D_Points!$A$5:$A$204,$M93)/1000),"0")&"+"&TEXT(MOD(INDEX(D_Points!$A$5:$A$204,$M93),1000),"000")) | C93: =IF($M93="","",UPPER(TRIM(INDEX(D_Points!$C$5:$C$204,$M93)))) | D93: =IF($M93="","",INDEX(D_Points!$D$5:$D$204,$M93)) | E93: =IF($M93="","",UPPER(TRIM(INDEX(D_Points!$E$5:$E$204,$M93)))) | F93: =IF($M93="","",INDEX(D_Points!$F$5:$F$204,$M93)) | G93: =IF($M93="","",""&IF(INDEX(D_Points!$G$5:$G$204,$M93)="","Right Angle",TRIM(INDEX(D_Points!$G$5:$G$204,$M93)))) | H93: =IF($C93="","",IF($G93="Skew","Catchpit inlet","Normal endwalls")) | I93: =IF($C93="","","Normal outlet") | J93: =IF($C93="","",$C93&"|"&$D93&"/"&UPPER(TRIM($E93))) | K93: =IF($M93="","",INDEX(D_Points!$I$5:$I$204,$M93)) | M93: =IFERROR(MATCH(89,D_Points!$K$5:$K$204,0),"")
A94: =IF($C94="","",90) | B94: =IF($M94="","",TEXT(INT(INDEX(D_Points!$A$5:$A$204,$M94)/1000),"0")&"+"&TEXT(MOD(INDEX(D_Points!$A$5:$A$204,$M94),1000),"000")) | C94: =IF($M94="","",UPPER(TRIM(INDEX(D_Points!$C$5:$C$204,$M94)))) | D94: =IF($M94="","",INDEX(D_Points!$D$5:$D$204,$M94)) | E94: =IF($M94="","",UPPER(TRIM(INDEX(D_Points!$E$5:$E$204,$M94)))) | F94: =IF($M94="","",INDEX(D_Points!$F$5:$F$204,$M94)) | G94: =IF($M94="","",""&IF(INDEX(D_Points!$G$5:$G$204,$M94)="","Right Angle",TRIM(INDEX(D_Points!$G$5:$G$204,$M94)))) | H94: =IF($C94="","",IF($G94="Skew","Catchpit inlet","Normal endwalls")) | I94: =IF($C94="","","Normal outlet") | J94: =IF($C94="","",$C94&"|"&$D94&"/"&UPPER(TRIM($E94))) | K94: =IF($M94="","",INDEX(D_Points!$I$5:$I$204,$M94)) | M94: =IFERROR(MATCH(90,D_Points!$K$5:$K$204,0),"")
A95: =IF($C95="","",91) | B95: =IF($M95="","",TEXT(INT(INDEX(D_Points!$A$5:$A$204,$M95)/1000),"0")&"+"&TEXT(MOD(INDEX(D_Points!$A$5:$A$204,$M95),1000),"000")) | C95: =IF($M95="","",UPPER(TRIM(INDEX(D_Points!$C$5:$C$204,$M95)))) | D95: =IF($M95="","",INDEX(D_Points!$D$5:$D$204,$M95)) | E95: =IF($M95="","",UPPER(TRIM(INDEX(D_Points!$E$5:$E$204,$M95)))) | F95: =IF($M95="","",INDEX(D_Points!$F$5:$F$204,$M95)) | G95: =IF($M95="","",""&IF(INDEX(D_Points!$G$5:$G$204,$M95)="","Right Angle",TRIM(INDEX(D_Points!$G$5:$G$204,$M95)))) | H95: =IF($C95="","",IF($G95="Skew","Catchpit inlet","Normal endwalls")) | I95: =IF($C95="","","Normal outlet") | J95: =IF($C95="","",$C95&"|"&$D95&"/"&UPPER(TRIM($E95))) | K95: =IF($M95="","",INDEX(D_Points!$I$5:$I$204,$M95)) | M95: =IFERROR(MATCH(91,D_Points!$K$5:$K$204,0),"")
